Workbook

Sheet Титул
B2: ="Финансовая модель проекта "&Проект -> Финансовая модель проекта «Наследие»
B3: Визуальная новелла на основе фольклора народов России
B4: Версия для защиты перед инвестором / банком / грантовым комитетом
B6: Ключевые параметры
B7: Период планирования | C7: =CHOOSE(MONTH(Дата_начала),"Январь","Февраль","Март","Апрель","Май","Июнь","Июль","Август","Сентябрь","Октябрь","Ноябрь","Декабрь")&" "&YEAR(Дата_начала)&" - "&CHOOSE(MONTH(DATE(YEAR(Дата_начала),MONTH(Дата_начала)+11,1)),"Январь","Февраль","Март","Апрель","Май","Июнь","Июль","Август","Сентябрь","Октябрь","Ноябрь","Декабрь")&" "&YEAR(DATE(YEAR(Дата_начала),MONTH(Дата_начала)+11,1))&" (12 месяцев)" -> Сентябрь 2026 - Август 2027 (12 месяцев)
B8: Бюджет проекта | C8: =FIXED(Собств_капитал,0)&" ₽ собственных средств команды (по "&FIXED(Взнос_участника,0)&" ₽ с человека)" -> 200,000 ₽ собственных средств команды (по 50,000 ₽ с человека)
B9: Команда | C9: =Участников&" человека, прибыль после релиза делится поровну" -> 4 человека, прибыль после релиза делится поровну
B10: Контент MVP | C10: =Контент_MVP -> 4 истории × 4 главы = 16 глав
B11: Релиз | C11: =Месяц_релиза_текст -> Янв 2027
B12: Активный сценарий | C12: =Сценарий -> Базовый
B13: Статус проверок модели | C13: =Статус_проверок -> Все проверки пройдены
B15: Главные результаты (активный сценарий)
B16: Выручка за 12 мес. | C16: =FIXED(KPI_выручка,0)&" ₽" -> 612,516 ₽
B17: Чистая прибыль | C17: =FIXED(KPI_ЧП,0)&" ₽ (рентабельность "&FIXED(KPI_ЧП_м*100,1)&"%)" -> 110,635 ₽ (рентабельность 18.1%)
B18: ROI на собственный капитал | C18: =FIXED(KPI_ROI*100,0)&"%" -> 55%
B19: Точка безубыточности | C19: =FIXED(BEP_MAU,0)&" MAU; EBITDA положительна с: "&BEP_месяц -> 6,236 MAU; EBITDA положительна с: Апр 2027
B20: Окупаемость вложений команды | C20: =IF(ISNUMBER(PP_docx),FIXED(PP_docx,1)&" мес.: выход в плюс в "&PP_docx_мес&" ("&ROUNDUP(PP_docx,0)&"-й месяц проекта)","за пределами 12 месяцев") -> 11.0 мес.: выход в плюс в Июл 2027 (11-й месяц проекта)
B21: Деньги на конец периода | C21: =FIXED(KPI_деньги,0)&" ₽, минимум "&FIXED(KPI_мин_деньги,0)&" ₽" -> 310,635 ₽, минимум 69,243 ₽
B23: Содержание
B24: =HYPERLINK("#'Дашборд'!A1","Дашборд") -> Дашборд | C24: Ключевые цифры и графики
B25: =HYPERLINK("#'Допущения'!A1","Допущения") -> Допущения | C25: Все вводные: меняйте только жёлтые ячейки с синими цифрами. Здесь же выбор сценария
B26: =HYPERLINK("#'Выручка'!A1","Выручка") -> Выручка | C26: Помесячная выручка: MAU, реклама interstitial и rewarded, покупки IAP
B27: =HYPERLINK("#'Расходы'!A1","Расходы") -> Расходы | C27: Операционные расходы по фазам проекта и комиссия магазина
B28: =HYPERLINK("#'Кредит'!A1","Кредит") -> Кредит | C28: График кредита: льготный период и аннуитет
B29: =HYPERLINK("#'ОПиУ'!A1","ОПиУ") -> ОПиУ | C29: Отчёт о прибылях и убытках с расчётом налога УСН
B30: =HYPERLINK("#'ДДС'!A1","ДДС") -> ДДС | C30: Движение денежных средств и остаток денег
B31: =HYPERLINK("#'Баланс'!A1","Баланс") -> Баланс | C31: Упрощённый баланс: проверка, что всё сходится
B32: =HYPERLINK("#'Показатели'!A1","Показатели") -> Показатели | C32: Точка безубыточности, окупаемость, NPV/IRR, DSCR, юнит-экономика
B33: =HYPERLINK("#'Сценарии'!A1","Сценарии") -> Сценарии | C33: Четыре сценария полной логикой + стресс-тест задержки релиза
B34: =HYPERLINK("#'Чувствительность'!A1","Чувствительность") -> Чувствительность | C34: Торнадо, сетка MAU × eCPM, стресс-тест DAU/MAU
B35: =HYPERLINK("#'Команда'!A1","Команда") -> Команда | C35: Роли, взносы и что получит каждый участник
B36: =HYPERLINK("#'Риски'!A1","Риски") -> Риски | C36: Матрица рисков docx с оценкой эффекта в модели
B37: =HYPERLINK("#'Защита'!A1","Защита") -> Защита | C37: Выводы и ответы на вопросы с живыми цифрами
B38: =HYPERLINK("#'Проверки'!A1","Проверки") -> Проверки | C38: Проверки целостности, сверка с docx и что стоит поправить
B40: Условные обозначения
B41: 1000 | C41: Ввод: можно менять
B42: 1000 | C42: Ключевое допущение, которое стоит перепроверить
B43: 1000 | C43: Формула
B44: 1000 | C44: Ссылка на другой лист
B45: -1000 | C45: Отрицательные значения красным
B46: OK | C46: Проверка пройдена
B48: Как пользоваться
B49: 1. Меняйте допущения на листе «Допущения»: всё остальное пересчитается само.
B50: 2. Сценарий переключается в «Допущениях», п. 9 (выпадающий список).
B51: 3. Лист «Проверки» показывает, что модель сходится, и где цифры отличаются от docx.
B52: 4. Для защиты: «Дашборд» для слайдов, «Защита» для ответов на вопросы.

Sheet Дашборд
B2: ="Дашборд: проект "&Проект -> Дашборд: проект «Наследие»
B3: ="Сценарий: «"&Сценарий&"» | "&Статус_проверок&" | релиз: "&Месяц_релиза_текст -> Сценарий: «Базовый» | Все проверки пройдены | релиз: Янв 2027
R4: Данные для графиков (ссылки на листы модели)
B5: ВЫРУЧКА ЗА 12 МЕС. | F5: EBITDA | J5: ЧИСТАЯ ПРИБЫЛЬ | N5: ДЕНЬГИ НА КОНЕЦ ПЕРИОДА | R5: Показатель | S5: =Выручка!H$5 -> Сен 2026 | T5: =Выручка!I$5 -> Окт 2026 | U5: =Выручка!J$5 -> Ноя 2026 | V5: =Выручка!K$5 -> Дек 2026 | W5: =Выручка!L$5 -> Янв 2027 | X5: =Выручка!M$5 -> Фев 2027 | Y5: =Выручка!N$5 -> Мар 2027 | Z5: =Выручка!O$5 -> Апр 2027 | ... AD5: =Выручка!S$5 -> Авг 2027
B6: =KPI_выручка -> 612516.15 | F6: =KPI_EBITDA -> 110635.14 | J6: =KPI_ЧП -> 110635.14 | N6: =KPI_деньги -> 310635.14 | R6: Interstitial | S6: =Выручка!H19 -> 0 | T6: =Выручка!I19 -> 0 | U6: =Выручка!J19 -> 0 | V6: =Выручка!K19 -> 0 | W6: =Выручка!L19 -> 2733.75 | X6: =Выручка!M19 -> 5467.5 | Y6: =Выручка!N19 -> 9112.5 | Z6: =Выручка!O19 -> 12757.5 | ... AD6: =Выручка!S19 -> 36450
B7: ="реклама "&(FIXED((Выручка!$F$37)*100,0)&"%")&", покупки "&(FIXED((1-Выручка!$F$37)*100,0)&"%") -> реклама 59%, покупки 41% | F7: ="рентабельность "&(FIXED((KPI_EBITDA_м)*100,1)&"%") -> рентабельность 18.1% | J7: ="рентабельность "&(FIXED((KPI_ЧП_м)*100,1)&"%")&", на участника "&(FIXED(ОПиУ!$F$31*Доля_1,0))&" ₽" -> рентабельность 18.1%, на участника 27,659 ₽ | N7: ="минимум "&(FIXED(KPI_мин_деньги,0))&" ₽ ("&(KPI_мин_деньги_мес)&")" -> минимум 69,243 ₽ (Мар 2027) | R7: Rewarded | S7: =Выручка!H25 -> 0 | T7: =Выручка!I25 -> 0 | U7: =Выручка!J25 -> 0 | V7: =Выручка!K25 -> 0 | W7: =Выручка!L25 -> 4320 | X7: =Выручка!M25 -> 8748 | Y7: =Выручка!N25 -> 14940 | Z7: =Выручка!O25 -> 21420 | ... AD7: =Выручка!S25 -> 64800
R8: IAP | S8: =Выручка!H31 -> 0 | T8: =Выручка!I31 -> 0 | U8: =Выручка!J31 -> 0 | V8: =Выручка!K31 -> 0 | W8: =Выручка!L31 -> 3251.6 | X8: =Выручка!M31 -> 7163.2 | Y8: =Выручка!N31 -> 12752.8 | Z8: =Выручка!O31 -> 19353.6 | ... AD8: =Выручка!S31 -> 79120
B9: ROI НА СОБСТВЕННЫЙ КАПИТАЛ | F9: ТОЧКА БЕЗУБЫТОЧНОСТИ | J9: ОКУПАЕМОСТЬ ВЛОЖЕНИЙ | N9: ЧДД (NPV) ПРОЕКТА | R9: MAU | S9: =Выручка!H13 -> 0 | T9: =Выручка!I13 -> 0 | U9: =Выручка!J13 -> 0 | V9: =Выручка!K13 -> 0 | W9: =Выручка!L13 -> 1500 | X9: =Выручка!M13 -> 3000 | Y9: =Выручка!N13 -> 5000 | Z9: =Выручка!O13 -> 7000 | ... AD9: =Выручка!S13 -> 20000
B10: =KPI_ROI -> 0.5531757 | F10: =FIXED(BEP_MAU,0)&" MAU" -> 6,236 MAU | J10: =IF(ISNUMBER(PP_docx),FIXED(PP_docx,1)&" мес.","> 12 мес.") -> 11.0 мес. | N10: =ЧДД -> 79741.265 | R10: EBITDA | S10: =ОПиУ!H26 -> -4000 | T10: =ОПиУ!I26 -> -6000 | U10: =ОПиУ!J26 -> -16000 | V10: =ОПиУ!K26 -> -26000 | W10: =ОПиУ!L26 -> -37093.64 | X10: =ОПиУ!M26 -> -27518.28 | Y10: =ОПиУ!N26 -> -14145.12 | Z10: =ОПиУ!O26 -> 375.56 | ... AD10: =ОПиУ!S26 -> 110352
B11: ="вложено "&FIXED(Собств_капитал,0)&" ₽ собственных средств" -> вложено 200,000 ₽ собственных средств | F11: ="EBITDA ≥ 0 с: "&(BEP_месяц) -> EBITDA ≥ 0 с: Апр 2027 | J11: ="выход в плюс: "&(PP_docx_мес)&"; проект: "&(IF(ISNUMBER(PP_проект),FIXED(PP_проект,1)&" мес.","> 12 мес.")) -> выход в плюс: Июл 2027; проект: 11.0 мес. | N11: ="ВНД "&(IF(ISNUMBER(ВНД),FIXED(ВНД*100,0)&"% годовых",ВНД))&", ставка "&(FIXED((Ставка_дисконта)*100,0)&"%") -> ВНД 211% годовых, ставка 22% | R11: Чистая прибыль | S11: =ОПиУ!H31 -> -4000 | T11: =ОПиУ!I31 -> -6000 | U11: =ОПиУ!J31 -> -16000 | V11: =ОПиУ!K31 -> -26000 | W11: =ОПиУ!L31 -> -37093.64 | X11: =ОПиУ!M31 -> -27518.28 | Y11: =ОПиУ!N31 -> -14145.12 | Z11: =ОПиУ!O31 -> 375.56 | ... AD11: =ОПиУ!S31 -> 110352
R12: Чистый денежный поток | S12: =ДДС!H25 -> 196000 | T12: =ДДС!I25 -> -6000 | U12: =ДДС!J25 -> -16000 | V12: =ДДС!K25 -> -26000 | W12: =ДДС!L25 -> -37093.64 | X12: =ДДС!M25 -> -27518.28 | Y12: =ДДС!N25 -> -14145.12 | Z12: =ДДС!O25 -> 375.56 | ... AD12: =ДДС!S25 -> 110352
R13: Остаток денег | S13: =ДДС!H27 -> 196000 | T13: =ДДС!I27 -> 190000 | U13: =ДДС!J27 -> 174000 | V13: =ДДС!K27 -> 148000 | W13: =ДДС!L27 -> 110906.36 | X13: =ДДС!M27 -> 83388.08 | Y13: =ДДС!N27 -> 69242.96 | Z13: =ДДС!O27 -> 69618.52 | ... AD13: =ДДС!S27 -> 310635.14
R14: Накопленный поток проекта | S14: =Показатели!H122 -> -4000 | T14: =Показатели!I122 -> -10000 | U14: =Показатели!J122 -> -26000 | V14: =Показатели!K122 -> -52000 | W14: =Показатели!L122 -> -89093.64 | X14: =Показатели!M122 -> -116611.92 | Y14: =Показатели!N122 -> -130757.04 | Z14: =Показатели!O122 -> -130381.48 | ... AD14: =Показатели!S122 -> 110635.14
R15: Короткая подпись месяца (для осей) | S15: =CHOOSE(MONTH(Выручка!H$7),"Янв","Фев","Мар","Апр","Май","Июн","Июл","Авг","Сен","Окт","Ноя","Дек")&" "&RIGHT(YEAR(Выручка!H$7),2) -> Сен 26 | T15: =CHOOSE(MONTH(Выручка!I$7),"Янв","Фев","Мар","Апр","Май","Июн","Июл","Авг","Сен","Окт","Ноя","Дек")&" "&RIGHT(YEAR(Выручка!I$7),2) -> Окт 26 | U15: =CHOOSE(MONTH(Выручка!J$7),"Янв","Фев","Мар","Апр","Май","Июн","Июл","Авг","Сен","Окт","Ноя","Дек")&" "&RIGHT(YEAR(Выручка!J$7),2) -> Ноя 26 | V15: =CHOOSE(MONTH(Выручка!K$7),"Янв","Фев","Мар","Апр","Май","Июн","Июл","Авг","Сен","Окт","Ноя","Дек")&" "&RIGHT(YEAR(Выручка!K$7),2) -> Дек 26 | W15: =CHOOSE(MONTH(Выручка!L$7),"Янв","Фев","Мар","Апр","Май","Июн","Июл","Авг","Сен","Окт","Ноя","Дек")&" "&RIGHT(YEAR(Выручка!L$7),2) -> Янв 27 | X15: =CHOOSE(MONTH(Выручка!M$7),"Янв","Фев","Мар","Апр","Май","Июн","Июл","Авг","Сен","Окт","Ноя","Дек")&" "&RIGHT(YEAR(Выручка!M$7),2) -> Фев 27 | Y15: =CHOOSE(MONTH(Выручка!N$7),"Янв","Фев","Мар","Апр","Май","Июн","Июл","Авг","Сен","Окт","Ноя","Дек")&" "&RIGHT(YEAR(Выручка!N$7),2) -> Мар 27 | Z15: =CHOOSE(MONTH(Выручка!O$7),"Янв","Фев","Мар","Апр","Май","Июн","Июл","Авг","Сен","Окт","Ноя","Дек")&" "&RIGHT(YEAR(Выручка!O$7),2) -> Апр 27 | ... AD15: =CHOOSE(MONTH(Выручка!S$7),"Янв","Фев","Мар","Апр","Май","Июн","Июл","Авг","Сен","Окт","Ноя","Дек")&" "&RIGHT(YEAR(Выручка!S$7),2) -> Авг 27
B46: Графики строятся по блоку данных справа (столбцы R-AD); он ссылается на листы модели.

Sheet Допущения
B2: Допущения и вводные данные
B3: Меняйте только ячейки с синими цифрами на жёлтом фоне. Всё остальное считается формулами. Оранжевым выделены ключевые допущения, которые стоит перепроверить (см. лист «Проверки»).
B5: 1. Общие параметры
B6: Название проекта | E6: «Наследие» | F6: Визуальная новелла на основе фольклора народов России
B7: Дата начала проекта | D7: дата | E7: 46266 | F7: docx: период планирования сентябрь 2026 - август 2027
B8: Горизонт модели | D8: мес. | E8: 12 | F8: Модель рассчитана на 12 помесячных колонок
B9: Длительность разработки до релиза | D9: мес. | E9: 4 | F9: docx: разработка 4 мес., релиз в январе 2027
B10: Задержка релиза (стресс-тест) | D10: мес. | E10: 0 | F10: 0 = по плану. Сдвигает кривую MAU и продлевает разработку
B11: Месяц релиза (расчёт) | E11: =IF(Мес_разработки+Задержка_релиза>=12,"за горизонтом",CHOOSE(MONTH(DATE(YEAR(Дата_начала),MONTH(Дата_начала)+Мес_разработки+Задержка_релиза,1)),"Янв","Фев","Мар","Апр","Май","Июн","Июл","Авг","Сен","Окт","Ноя","Дек")&" "&YEAR(DATE(YEAR(Дата_начала),MONTH(Дата_начала)+Мес_разработки+Задержка_релиза,1))) -> Янв 2027
B12: Дней в месяце (для расчёта показов рекламы) | D12: дн. | E12: 30 | F12: docx: «пользователей × 30 дней»
B13: Контент MVP | E13: 4 истории × 4 главы = 16 глав
B15: 2. Финансирование
B16: Число участников команды | D16: чел. | E16: 4 | F16: docx: команда из 4 человек
B17: Взнос каждого участника | D17: ₽ | E17: 50000 | F17: docx: по 50 000 ₽ с участника
B18: Собственный капитал команды | D18: ₽ | E18: =Участников*Взнос_участника -> 200000 | F18: Покрывает разработку и резерв
B19: Месяц внесения капитала | D19: № мес. | E19: 1
B20: Кредит: банк
B21: Сумма кредита | D21: ₽
B22: Ставка по кредиту | D22: % годовых
B23: Срок кредита | D23: мес.
B24: Льготный период (только проценты) | D24: мес.
B25: Месяц получения кредита | D25: № мес.
B26: Итого финансирование (собственные средства) | D26: ₽ | E26: =Собств_капитал -> 200000 | F26: Заёмных средств нет
B27: Доля собственных средств | D27: % | E27: =IF(Финансирование>0,Собств_капитал/Финансирование,0) -> 1 | F27: docx: смешанная модель 50/50
B29: 3. Аудитория и монетизация
B30: DAU/MAU: доля MAU, заходящих в игру каждый день | D30: % | E30: 0.3 | F30: В docx неявно 100%: показы = MAU × 30 дней. Главное допущение модели, см. «Проверки»
B31: Interstitial: доля пользователей, видящих рекламу | D31: % | E31: 0.9 | F31: Реклама как в презентации: обязательная, видят 90% DAU (остальные: платящие). В приложении interstitial показывается при входе в главу и при выходе из истории, не чаще раза в 30 минут. Провайдеры пока не подключены, в приложении заглушки
B32: Interstitial: показов в день на пользователя | D32: шт. | E32: 1.5 | F32: 1 показ раз в 30 минут при сессии 30 минут, около 1,5 сессии в день. Реализовано в приложении заглушкой `Ads.Interstitial`
B33: Interstitial: eCPM | D33: ₽ | E33: 150 | F33: docx: eCPM = 100 ₽
B34: Rewarded: просмотров в день на смотрящего | D34: шт. | E34: 2 | F34: Ролик за награду: 3 алмаза каждые 30 минут (раздел «Награды»), +энергия в чате, спин колеса. В приложении заглушка `Ads.Rewarded`. Доля смотрящих по месяцам в п. 4
B35: Rewarded: eCPM | D35: ₽ | E35: 200 | F35: docx: eCPM = 150 ₽
B36: Комиссия магазина с IAP (алмазы и энергия) | D36: % | E36: 0.15 | F36: Установка игры из RuStore бесплатна, платных загрузок нет. Комиссия магазина 15% удерживается только с покупок внутри игры
B37: Лаг поступления выручки на счёт | D37: мес. | E37: 0 | F37: 0 = деньги приходят в месяце начисления (как в docx). Рекламные сети платят по итогам месяца
B39: 4. План по месяцам после релиза (docx, раздел 5.2)
B40: Месяц после релиза | D40: Ед. | E40: 1 | F40: 2 | G40: 3 | H40: 4 | I40: 5 | J40: 6 | K40: 7 | L40: 8 | M40: 9 | N40: 10 | O40: 11 | P40: 12
B41: Календарный месяц при текущих вводных | E41: =IF(Мес_разработки+Задержка_релиза+E$40>12,"вне горизонта",CHOOSE(MONTH(DATE(YEAR(Дата_начала),MONTH(Дата_начала)+Мес_разработки+Задержка_релиза+E$40-1,1)),"Янв","Фев","Мар","Апр","Май","Июн","Июл","Авг","Сен","Окт","Ноя","Дек")&" "&YEAR(DATE(YEAR(Дата_начала),MONTH(Дата_начала)+Мес_разработки+Задержка_релиза+E$40-1,1))) -> Янв 2027 | F41: =IF(Мес_разработки+Задержка_релиза+F$40>12,"вне горизонта",CHOOSE(MONTH(DATE(YEAR(Дата_начала),MONTH(Дата_начала)+Мес_разработки+Задержка_релиза+F$40-1,1)),"Янв","Фев","Мар","Апр","Май","Июн","Июл","Авг","Сен","Окт","Ноя","Дек")&" "&YEAR(DATE(YEAR(Дата_начала),MONTH(Дата_начала)+Мес_разработки+Задержка_релиза+F$40-1,1))) -> Фев 2027 | G41: =IF(Мес_разработки+Задержка_релиза+G$40>12,"вне горизонта",CHOOSE(MONTH(DATE(YEAR(Дата_начала),MONTH(Дата_начала)+Мес_разработки+Задержка_релиза+G$40-1,1)),"Янв","Фев","Мар","Апр","Май","Июн","Июл","Авг","Сен","Окт","Ноя","Дек")&" "&YEAR(DATE(YEAR(Дата_начала),MONTH(Дата_начала)+Мес_разработки+Задержка_релиза+G$40-1,1))) -> Мар 2027 | H41: =IF(Мес_разработки+Задержка_релиза+H$40>12,"вне горизонта",CHOOSE(MONTH(DATE(YEAR(Дата_начала),MONTH(Дата_начала)+Мес_разработки+Задержка_релиза+H$40-1,1)),"Янв","Фев","Мар","Апр","Май","Июн","Июл","Авг","Сен","Окт","Ноя","Дек")&" "&YEAR(DATE(YEAR(Дата_начала),MONTH(Дата_начала)+Мес_разработки+Задержка_релиза+H$40-1,1))) -> Апр 2027 | I41: =IF(Мес_разработки+Задержка_релиза+I$40>12,"вне горизонта",CHOOSE(MONTH(DATE(YEAR(Дата_начала),MONTH(Дата_начала)+Мес_разработки+Задержка_релиза+I$40-1,1)),"Янв","Фев","Мар","Апр","Май","Июн","Июл","Авг","Сен","Окт","Ноя","Дек")&" "&YEAR(DATE(YEAR(Дата_начала),MONTH(Дата_начала)+Мес_разработки+Задержка_релиза+I$40-1,1))) -> Май 2027 | J41: =IF(Мес_разработки+Задержка_релиза+J$40>12,"вне горизонта",CHOOSE(MONTH(DATE(YEAR(Дата_начала),MONTH(Дата_начала)+Мес_разработки+Задержка_релиза+J$40-1,1)),"Янв","Фев","Мар","Апр","Май","Июн","Июл","Авг","Сен","Окт","Ноя","Дек")&" "&YEAR(DATE(YEAR(Дата_начала),MONTH(Дата_начала)+Мес_разработки+Задержка_релиза+J$40-1,1))) -> Июн 2027 | K41: =IF(Мес_разработки+Задержка_релиза+K$40>12,"вне горизонта",CHOOSE(MONTH(DATE(YEAR(Дата_начала),MONTH(Дата_начала)+Мес_разработки+Задержка_релиза+K$40-1,1)),"Янв","Фев","Мар","Апр","Май","Июн","Июл","Авг","Сен","Окт","Ноя","Дек")&" "&YEAR(DATE(YEAR(Дата_начала),MONTH(Дата_начала)+Мес_разработки+Задержка_релиза+K$40-1,1))) -> Июл 2027 | L41: =IF(Мес_разработки+Задержка_релиза+L$40>12,"вне горизонта",CHOOSE(MONTH(DATE(YEAR(Дата_начала),MONTH(Дата_начала)+Мес_разработки+Задержка_релиза+L$40-1,1)),"Янв","Фев","Мар","Апр","Май","Июн","Июл","Авг","Сен","Окт","Ноя","Дек")&" "&YEAR(DATE(YEAR(Дата_начала),MONTH(Дата_начала)+Мес_разработки+Задержка_релиза+L$40-1,1))) -> Авг 2027 | ... P41: =IF(Мес_разработки+Задержка_релиза+P$40>12,"вне горизонта",CHOOSE(MONTH(DATE(YEAR(Дата_начала),MONTH(Дата_начала)+Мес_разработки+Задержка_релиза+P$40-1,1)),"Янв","Фев","Мар","Апр","Май","Июн","Июл","Авг","Сен","Окт","Ноя","Дек")&" "&YEAR(DATE(YEAR(Дата_начала),MONTH(Дата_начала)+Мес_разработки+Задержка_релиза+P$40-1,1))) -> вне горизонта
B42: MAU (активные пользователи в месяц) | D42: чел. | E42: 1500 | F42: 3000 | G42: 5000 | H42: 7000 | I42: 9000 | J42: 12000 | K42: 16000 | L42: 20000 | M42: 25000 | N42: 25000 | O42: 25000 | P42: 25000
B43: Rewarded: доля смотрящих рекламу | D43: % | E43: 0.8 | F43: 0.81 | G43: 0.83 | H43: 0.85 | I43: 0.86 | J43: 0.87 | K43: 0.88 | L43: 0.9 | M43: 0.95 | N43: 0.95 | O43: 0.95 | P43: 0.95
B44: IAP: конверсия в плательщиков | D44: % | E44: 0.007 | F44: 0.0072 | G44: 0.0075 | H44: 0.008 | I44: 0.0085 | J44: 0.009 | K44: 0.0095 | L44: 0.01 | M44: 0.01 | N44: 0.01 | O44: 0.01 | P44: 0.01
B45: IAP: средний чек (ARPPU) | D45: ₽ | E45: 199 | F45: 229 | G45: 239 | H45: 249 | I45: 259 | J45: 279 | K45: 289 | L45: 299 | M45: 329 | N45: 349 | O45: 359 | P45: 359
B46: Месяцы 1-8 из docx. Месяцы 9-12 после релиза в горизонт не попадают при релизе на 5-м месяце; значения удержаны на уровне 8-го месяца и нужны, только если сократить разработку.
B48: 5. Операционные расходы, ₽ в месяц (docx, раздел 4)
B49: Статья | C49: Месяц начала расходов | D49: Ед. | E49: Разработка | F49: Операционка
B50: Затраты на ИИ-сервисы | C50: 1 | D50: ₽/мес | E50: 4000 | F50: 4000 | G50: Расходы на ИИ-сервисы. Оплаты команде нет: после релиза чистая прибыль делится поровну (п. 7)
B51: Поддержка серверов и хостинг | C51: 2 | D51: ₽/мес | E51: 2000 | F51: 2000
B52: Бухгалтерия и юр. сопровождение | C52: 4 | D52: ₽/мес | E52: 10000 | F52: 10000 | G52: Аутсорсинг, обязательные платежи (docx)
B53: Маркетинг и реклама (трафик, посевы) | C53: 3 | D53: ₽/мес | E53: 10000 | F53: =Сц_маркетинг -> 30000 | G53: ="После релиза задаётся по сценарию (п. 9), в активном сценарии "&FIXED(Допущения!$I$85,0)&" ₽/мес" -> После релиза задаётся по сценарию (п. 9), в активном сценарии 30,000 ₽/мес
B54: Итого в месяц | D54: ₽/мес | E54: =SUM(E50:E53) -> 26000 | F54: =SUM(F50:F53) -> 46000 | G54: docx: 37 000 ₽/мес в разработке и 52 000 ₽/мес после релиза
B56: 6. Налоги
B57: Режим налогообложения | E57: УСН «Доходы» | F57: docx: УСН 6% с вычетом взносов
B58: Ставка УСН | D58: % | E58: 0.06
B59: Страховые взносы, уменьшающие налог | D59: ₽/год | E59: 54000 | F59: у нас ИП
B60: Лимит уменьшения налога на взносы | D60: % | E60: 1 | F60: у нас ИП
B61: НДФЛ с дивидендов (справочно) | D61: % | E61: 0.13 | F61: Для расчёта суммы «на руки» на листе «Команда», если прибыль выплачивается как дивиденды ООО
B63: 7. Распределение чистой прибыли (docx, раздел 1)
B64: Технический разработчик | D64: % прибыли | E64: 0.25
B65: Проджект-менеджер | D65: % прибыли | E65: 0.25
B66: Арт-директор / Сценарист | D66: % прибыли | E66: 0.25
B67: Аналитик проекта | D67: % прибыли | E67: 0.25
B68: Итого | D68: % | E68: =SUM(E64:E67) -> 1 | F68: Должно быть 100%
B70: 8. Оценка эффективности и сравнение
B71: Ставка дисконтирования | D71: % годовых | E71: 0.22 | F71: Для рискованного проекта можно ставить выше: например, ключевая ставка плюс премия за риск
B72: CAC: стоимость привлечения пользователя | D72: ₽ | E72: 25 | F72: docx: 20-25 ₽ при узкой ЦА
B73: LTV: доход с пользователя за время жизни | D73: ₽ | E73: 80 | F73: docx: ~80 ₽. В docx не выводится расчётом
B74: Ставка банковского депозита | D74: % годовых | E74: 0.14 | F74: docx: 18%. Ключевая ставка ЦБ 14% (решение от 11.09.2026)
B75: Доходность индекса Мосбиржи | D75: % годовых | E75: 0.15 | F75: docx: ~15% годовых
B77: 9. Сценарии
B78: Активный сценарий (выберите из списка) | E78: Базовый | G78: От выбора зависят все отчёты, показатели и дашборд
B79: Номер активного сценария | E79: =MATCH(Сценарий,$E$80:$H$80,0) -> 2
B80: Параметр сценария | D80: Ед. | E80: Оптимистичный | F80: Базовый | G80: Пессимистичный | H80: Пессимистичный + меры | I80: Активный
B81: Вероятность (docx) | D81: % | E81: 0.25 | F81: 0.5 | G81: 0.25 | H81: 0 | I81: =INDEX($E81:$H81,1,Сц_номер) -> 0.5
B82: Множитель MAU к плану | D82: x | E82: 1.4 | F82: 1 | G82: 0.6 | H82: 0.6 | I82: =INDEX($E82:$H82,1,Сц_номер) -> 1
B83: Множитель eCPM (обе рекламные сети) | D83: x | E83: 1 | F83: 1 | G83: 1 | H83: 1 | I83: =INDEX($E83:$H83,1,Сц_номер) -> 1
B84: Множитель конверсии IAP | D84: x | E84: 1 | F84: 1 | G84: 1 | H84: 1 | I84: =INDEX($E84:$H84,1,Сц_номер) -> 1
B85: Маркетинг после релиза | D85: ₽/мес | E85: 40000 | F85: 30000 | G85: 25000 | H85: 20000 | I85: =INDEX($E85:$H85,1,Сц_номер) -> 30000
B86: MAU в последнем месяце горизонта (расчёт) | D86: чел. | E86: =Выручка!$S$12*E82 -> 28000 | F86: =Выручка!$S$12*F82 -> 20000 | G86: =Выручка!$S$12*G82 -> 12000 | H86: =Выручка!$S$12*H82 -> 12000 | I86: =INDEX($E86:$H86,1,Сц_номер) -> 20000
B87: docx: MAU к августу 35 000 / 25 000 / 15 000, вероятности 25% / 50% / 25%. «Пессимистичный + меры»: сокращение маркетинга до 20 000 ₽/мес из матрицы рисков (MAU при этом не пересчитывается от бюджета). Вероятность 0%: в ожидаемое значение не входит.

Sheet Выручка
B2: Выручка: помесячный расчёт
B3: ₽. Логика docx, раздел 5: реклама interstitial + rewarded + внутриигровые покупки (IAP). Сценарные множители берутся из «Допущений», п. 9.
B5: Показатель | C5: Ед. | D5: ="Разработка"&CHAR(10)&"("&Дев_мес&" мес.)" -> Разработка (4 мес.) | E5: ="Операционка"&CHAR(10)&"("&Опер_мес&" мес.)" -> Операционка (8 мес.) | F5: ="Итого"&CHAR(10)&"12 мес." -> Итого 12 мес. | H5: =CHOOSE(MONTH(H7),"Янв","Фев","Мар","Апр","Май","Июн","Июл","Авг","Сен","Окт","Ноя","Дек")&" "&YEAR(H7) -> Сен 2026 | I5: =CHOOSE(MONTH(I7),"Янв","Фев","Мар","Апр","Май","Июн","Июл","Авг","Сен","Окт","Ноя","Дек")&" "&YEAR(I7) -> Окт 2026 | J5: =CHOOSE(MONTH(J7),"Янв","Фев","Мар","Апр","Май","Июн","Июл","Авг","Сен","Окт","Ноя","Дек")&" "&YEAR(J7) -> Ноя 2026 | K5: =CHOOSE(MONTH(K7),"Янв","Фев","Мар","Апр","Май","Июн","Июл","Авг","Сен","Окт","Ноя","Дек")&" "&YEAR(K7) -> Дек 2026 | L5: =CHOOSE(MONTH(L7),"Янв","Фев","Мар","Апр","Май","Июн","Июл","Авг","Сен","Окт","Ноя","Дек")&" "&YEAR(L7) -> Янв 2027 | M5: =CHOOSE(MONTH(M7),"Янв","Фев","Мар","Апр","Май","Июн","Июл","Авг","Сен","Окт","Ноя","Дек")&" "&YEAR(M7) -> Фев 2027 | N5: =CHOOSE(MONTH(N7),"Янв","Фев","Мар","Апр","Май","Июн","Июл","Авг","Сен","Окт","Ноя","Дек")&" "&YEAR(N7) -> Мар 2027 | O5: =CHOOSE(MONTH(O7),"Янв","Фев","Мар","Апр","Май","Июн","Июл","Авг","Сен","Окт","Ноя","Дек")&" "&YEAR(O7) -> Апр 2027 | ... S5: =CHOOSE(MONTH(S7),"Янв","Фев","Мар","Апр","Май","Июн","Июл","Авг","Сен","Окт","Ноя","Дек")&" "&YEAR(S7) -> Авг 2027
B6: № месяца проекта | H6: 1 | I6: =H6+1 -> 2 | J6: =I6+1 -> 3 | K6: =J6+1 -> 4 | L6: =K6+1 -> 5 | M6: =L6+1 -> 6 | N6: =M6+1 -> 7 | O6: =N6+1 -> 8 | P6: =O6+1 -> 9 | ... S6: =R6+1 -> 12
B7: Дата (начало месяца) | H7: =DATE(YEAR(Дата_начала),MONTH(Дата_начала)+H6-1,1) -> 46266 | I7: =DATE(YEAR(Дата_начала),MONTH(Дата_начала)+I6-1,1) -> 46296 | J7: =DATE(YEAR(Дата_начала),MONTH(Дата_начала)+J6-1,1) -> 46327 | K7: =DATE(YEAR(Дата_начала),MONTH(Дата_начала)+K6-1,1) -> 46357 | L7: =DATE(YEAR(Дата_начала),MONTH(Дата_начала)+L6-1,1) -> 46388 | M7: =DATE(YEAR(Дата_начала),MONTH(Дата_начала)+M6-1,1) -> 46419 | N7: =DATE(YEAR(Дата_начала),MONTH(Дата_начала)+N6-1,1) -> 46447 | O7: =DATE(YEAR(Дата_начала),MONTH(Дата_начала)+O6-1,1) -> 46478 | ... S7: =DATE(YEAR(Дата_начала),MONTH(Дата_начала)+S6-1,1) -> 46600
B8: Фаза | D8: =COUNTIF($H$8:$S$8,"Разработка") -> 4 | E8: =COUNTIF($H$8:$S$8,"Операционка") -> 8 | F8: =D8+E8 -> 12 | H8: =IF(H6<=Мес_разработки+Задержка_релиза,"Разработка","Операционка") -> Разработка | I8: =IF(I6<=Мес_разработки+Задержка_релиза,"Разработка","Операционка") -> Разработка | J8: =IF(J6<=Мес_разработки+Задержка_релиза,"Разработка","Операционка") -> Разработка | K8: =IF(K6<=Мес_разработки+Задержка_релиза,"Разработка","Операционка") -> Разработка | L8: =IF(L6<=Мес_разработки+Задержка_релиза,"Разработка","Операционка") -> Операционка | M8: =IF(M6<=Мес_разработки+Задержка_релиза,"Разработка","Операционка") -> Операционка | N8: =IF(N6<=Мес_разработки+Задержка_релиза,"Разработка","Операционка") -> Операционка | O8: =IF(O6<=Мес_разработки+Задержка_релиза,"Разработка","Операционка") -> Операционка | ... S8: =IF(S6<=Мес_разработки+Задержка_релиза,"Разработка","Операционка") -> Операционка
B9: Месяцев после релиза | H9: =MAX(0,H6-Мес_разработки-Задержка_релиза) -> 0 | I9: =MAX(0,I6-Мес_разработки-Задержка_релиза) -> 0 | J9: =MAX(0,J6-Мес_разработки-Задержка_релиза) -> 0 | K9: =MAX(0,K6-Мес_разработки-Задержка_релиза) -> 0 | L9: =MAX(0,L6-Мес_разработки-Задержка_релиза) -> 1 | M9: =MAX(0,M6-Мес_разработки-Задержка_релиза) -> 2 | N9: =MAX(0,N6-Мес_разработки-Задержка_релиза) -> 3 | O9: =MAX(0,O6-Мес_разработки-Задержка_релиза) -> 4 | ... S9: =MAX(0,S6-Мес_разработки-Задержка_релиза) -> 8
B11: Аудитория
B12: MAU по плану (до сценарного множителя) | C12: чел. | D12: =INDEX($H$12:$S$12,1,Дев_мес) -> 0 | E12: =IF(Опер_мес>0,S12,"") -> 20000 | F12: =S12 -> 20000 | H12: =IF(H$9>0,INDEX(План_MAU,1,H$9),0) -> 0 | I12: =IF(I$9>0,INDEX(План_MAU,1,I$9),0) -> 0 | J12: =IF(J$9>0,INDEX(План_MAU,1,J$9),0) -> 0 | K12: =IF(K$9>0,INDEX(План_MAU,1,K$9),0) -> 0 | L12: =IF(L$9>0,INDEX(План_MAU,1,L$9),0) -> 1500 | M12: =IF(M$9>0,INDEX(План_MAU,1,M$9),0) -> 3000 | N12: =IF(N$9>0,INDEX(План_MAU,1,N$9),0) -> 5000 | O12: =IF(O$9>0,INDEX(План_MAU,1,O$9),0) -> 7000 | ... S12: =IF(S$9>0,INDEX(План_MAU,1,S$9),0) -> 20000
B13: MAU (активный сценарий) | C13: чел. | D13: =INDEX($H$13:$S$13,1,Дев_мес) -> 0 | E13: =IF(Опер_мес>0,S13,"") -> 20000 | F13: =S13 -> 20000 | H13: =H12*Сц_MAU -> 0 | I13: =I12*Сц_MAU -> 0 | J13: =J12*Сц_MAU -> 0 | K13: =K12*Сц_MAU -> 0 | L13: =L12*Сц_MAU -> 1500 | M13: =M12*Сц_MAU -> 3000 | N13: =N12*Сц_MAU -> 5000 | O13: =O12*Сц_MAU -> 7000 | ... S13: =S12*Сц_MAU -> 20000
B14: DAU: заходят в игру в среднем за день | C14: чел. | D14: =INDEX($H$14:$S$14,1,Дев_мес) -> 0 | E14: =IF(Опер_мес>0,S14,"") -> 6000 | F14: =S14 -> 6000 | H14: =H13*DAU_MAU -> 0 | I14: =I13*DAU_MAU -> 0 | J14: =J13*DAU_MAU -> 0 | K14: =K13*DAU_MAU -> 0 | L14: =L13*DAU_MAU -> 450 | M14: =M13*DAU_MAU -> 900 | N14: =N13*DAU_MAU -> 1500 | O14: =O13*DAU_MAU -> 2100 | ... S14: =S13*DAU_MAU -> 6000
B16: Interstitial (обязательная реклама)
B17: Показов в месяц | C17: шт. | D17: =SUMIF($H$8:$S$8,"Разработка",$H$17:$S$17) -> 0 | E17: =SUMIF($H$8:$S$8,"Операционка",$H$17:$S$17) -> 893025 | F17: =SUM($H$17:$S$17) -> 893025 | H17: =H14*Int_доля*Int_показов*Дней_в_месяце -> 0 | I17: =I14*Int_доля*Int_показов*Дней_в_месяце -> 0 | J17: =J14*Int_доля*Int_показов*Дней_в_месяце -> 0 | K17: =K14*Int_доля*Int_показов*Дней_в_месяце -> 0 | L17: =L14*Int_доля*Int_показов*Дней_в_месяце -> 18225 | M17: =M14*Int_доля*Int_показов*Дней_в_месяце -> 36450 | N17: =N14*Int_доля*Int_показов*Дней_в_месяце -> 60750 | O17: =O14*Int_доля*Int_показов*Дней_в_месяце -> 85050 | ... S17: =S14*Int_доля*Int_показов*Дней_в_месяце -> 243000
B18: eCPM (доход за 1000 показов) | C18: ₽ | E18: =IFERROR(AVERAGEIF($H$8:$S$8,"Операционка",$H$18:$S$18),0) -> 150 | F18: =IFERROR(AVERAGEIF($H$8:$S$8,"Операционка",$H$18:$S$18),0) -> 150 | H18: =IF(H$9>0,Int_eCPM*Сц_eCPM,0) -> 0 | I18: =IF(I$9>0,Int_eCPM*Сц_eCPM,0) -> 0 | J18: =IF(J$9>0,Int_eCPM*Сц_eCPM,0) -> 0 | K18: =IF(K$9>0,Int_eCPM*Сц_eCPM,0) -> 0 | L18: =IF(L$9>0,Int_eCPM*Сц_eCPM,0) -> 150 | M18: =IF(M$9>0,Int_eCPM*Сц_eCPM,0) -> 150 | N18: =IF(N$9>0,Int_eCPM*Сц_eCPM,0) -> 150 | O18: =IF(O$9>0,Int_eCPM*Сц_eCPM,0) -> 150 | ... S18: =IF(S$9>0,Int_eCPM*Сц_eCPM,0) -> 150
B19: Доход от Interstitial | C19: ₽ | D19: =SUMIF($H$8:$S$8,"Разработка",$H$19:$S$19) -> 0 | E19: =SUMIF($H$8:$S$8,"Операционка",$H$19:$S$19) -> 133953.75 | F19: =SUM($H$19:$S$19) -> 133953.75 | H19: =H17*H18/1000 -> 0 | I19: =I17*I18/1000 -> 0 | J19: =J17*J18/1000 -> 0 | K19: =K17*K18/1000 -> 0 | L19: =L17*L18/1000 -> 2733.75 | M19: =M17*M18/1000 -> 5467.5 | N19: =N17*N18/1000 -> 9112.5 | O19: =O17*O18/1000 -> 12757.5 | ... S19: =S17*S18/1000 -> 36450
B21: Rewarded (реклама за вознаграждение)
B22: Доля смотрящих rewarded | C22: % | E22: =IFERROR(AVERAGEIF($H$8:$S$8,"Операционка",$H$22:$S$22),0) -> 0.85 | F22: =IFERROR(AVERAGEIF($H$8:$S$8,"Операционка",$H$22:$S$22),0) -> 0.85 | H22: =IF(H$9>0,INDEX(План_rew_доля,1,H$9),0) -> 0 | I22: =IF(I$9>0,INDEX(План_rew_доля,1,I$9),0) -> 0 | J22: =IF(J$9>0,INDEX(План_rew_доля,1,J$9),0) -> 0 | K22: =IF(K$9>0,INDEX(План_rew_доля,1,K$9),0) -> 0 | L22: =IF(L$9>0,INDEX(План_rew_доля,1,L$9),0) -> 0.8 | M22: =IF(M$9>0,INDEX(План_rew_доля,1,M$9),0) -> 0.81 | N22: =IF(N$9>0,INDEX(План_rew_доля,1,N$9),0) -> 0.83 | O22: =IF(O$9>0,INDEX(План_rew_доля,1,O$9),0) -> 0.85 | ... S22: =IF(S$9>0,INDEX(План_rew_доля,1,S$9),0) -> 0.9
B23: Просмотров в месяц | C23: шт. | D23: =SUMIF($H$8:$S$8,"Разработка",$H$23:$S$23) -> 0 | E23: =SUMIF($H$8:$S$8,"Операционка",$H$23:$S$23) -> 1151820 | F23: =SUM($H$23:$S$23) -> 1151820 | H23: =H14*H22*Rew_просмотров*Дней_в_месяце -> 0 | I23: =I14*I22*Rew_просмотров*Дней_в_месяце -> 0 | J23: =J14*J22*Rew_просмотров*Дней_в_месяце -> 0 | K23: =K14*K22*Rew_просмотров*Дней_в_месяце -> 0 | L23: =L14*L22*Rew_просмотров*Дней_в_месяце -> 21600 | M23: =M14*M22*Rew_просмотров*Дней_в_месяце -> 43740 | N23: =N14*N22*Rew_просмотров*Дней_в_месяце -> 74700 | O23: =O14*O22*Rew_просмотров*Дней_в_месяце -> 107100 | ... S23: =S14*S22*Rew_просмотров*Дней_в_месяце -> 324000
B24: eCPM (доход за 1000 просмотров) | C24: ₽ | E24: =IFERROR(AVERAGEIF($H$8:$S$8,"Операционка",$H$24:$S$24),0) -> 200 | F24: =IFERROR(AVERAGEIF($H$8:$S$8,"Операционка",$H$24:$S$24),0) -> 200 | H24: =IF(H$9>0,Rew_eCPM*Сц_eCPM,0) -> 0 | I24: =IF(I$9>0,Rew_eCPM*Сц_eCPM,0) -> 0 | J24: =IF(J$9>0,Rew_eCPM*Сц_eCPM,0) -> 0 | K24: =IF(K$9>0,Rew_eCPM*Сц_eCPM,0) -> 0 | L24: =IF(L$9>0,Rew_eCPM*Сц_eCPM,0) -> 200 | M24: =IF(M$9>0,Rew_eCPM*Сц_eCPM,0) -> 200 | N24: =IF(N$9>0,Rew_eCPM*Сц_eCPM,0) -> 200 | O24: =IF(O$9>0,Rew_eCPM*Сц_eCPM,0) -> 200 | ... S24: =IF(S$9>0,Rew_eCPM*Сц_eCPM,0) -> 200
B25: Доход от Rewarded | C25: ₽ | D25: =SUMIF($H$8:$S$8,"Разработка",$H$25:$S$25) -> 0 | E25: =SUMIF($H$8:$S$8,"Операционка",$H$25:$S$25) -> 230364 | F25: =SUM($H$25:$S$25) -> 230364 | H25: =H23*H24/1000 -> 0 | I25: =I23*I24/1000 -> 0 | J25: =J23*J24/1000 -> 0 | K25: =K23*K24/1000 -> 0 | L25: =L23*L24/1000 -> 4320 | M25: =M23*M24/1000 -> 8748 | N25: =N23*N24/1000 -> 14940 | O25: =O23*O24/1000 -> 21420 | ... S25: =S23*S24/1000 -> 64800
B27: IAP (внутриигровые покупки)
B28: Конверсия в плательщиков | C28: % | E28: =IFERROR(AVERAGEIF($H$8:$S$8,"Операционка",$H$28:$S$28),0) -> 0.0083375 | F28: =IFERROR(AVERAGEIF($H$8:$S$8,"Операционка",$H$28:$S$28),0) -> 0.0083375 | H28: =IF(H$9>0,INDEX(План_конв,1,H$9)*Сц_конв,0) -> 0 | I28: =IF(I$9>0,INDEX(План_конв,1,I$9)*Сц_конв,0) -> 0 | J28: =IF(J$9>0,INDEX(План_конв,1,J$9)*Сц_конв,0) -> 0 | K28: =IF(K$9>0,INDEX(План_конв,1,K$9)*Сц_конв,0) -> 0 | L28: =IF(L$9>0,INDEX(План_конв,1,L$9)*Сц_конв,0) -> 0.007 | M28: =IF(M$9>0,INDEX(План_конв,1,M$9)*Сц_конв,0) -> 0.0072 | N28: =IF(N$9>0,INDEX(План_конв,1,N$9)*Сц_конв,0) -> 0.0075 | O28: =IF(O$9>0,INDEX(План_конв,1,O$9)*Сц_конв,0) -> 0.008 | ... S28: =IF(S$9>0,INDEX(План_конв,1,S$9)*Сц_конв,0) -> 0.01
B29: Плательщиков (округлено до целых, как в docx) | C29: чел. | D29: =SUMIF($H$8:$S$8,"Разработка",$H$29:$S$29) -> 0 | E29: =SUMIF($H$8:$S$8,"Операционка",$H$29:$S$29) -> 664 | F29: =SUM($H$29:$S$29) -> 664 | H29: =ROUND(H13*H28,0) -> 0 | I29: =ROUND(I13*I28,0) -> 0 | J29: =ROUND(J13*J28,0) -> 0 | K29: =ROUND(K13*K28,0) -> 0 | L29: =ROUND(L13*L28,0) -> 11 | M29: =ROUND(M13*M28,0) -> 22 | N29: =ROUND(N13*N28,0) -> 38 | O29: =ROUND(O13*O28,0) -> 56 | ... S29: =ROUND(S13*S28,0) -> 200
B30: Средний чек (ARPPU): алмазы + энергия | C30: ₽ | E30: =IFERROR(AVERAGEIF($H$8:$S$8,"Операционка",$H$30:$S$30),0) -> 351.85 | F30: =IFERROR(AVERAGEIF($H$8:$S$8,"Операционка",$H$30:$S$30),0) -> 351.85 | H30: =IF(H$9>0,INDEX(План_ARPPU,1,H$9),0)+IF(H$9>0,Энергия!$D$30,0) -> 0 | I30: =IF(I$9>0,INDEX(План_ARPPU,1,I$9),0)+IF(I$9>0,Энергия!$D$30,0) -> 0 | J30: =IF(J$9>0,INDEX(План_ARPPU,1,J$9),0)+IF(J$9>0,Энергия!$D$30,0) -> 0 | K30: =IF(K$9>0,INDEX(План_ARPPU,1,K$9),0)+IF(K$9>0,Энергия!$D$30,0) -> 0 | L30: =IF(L$9>0,INDEX(План_ARPPU,1,L$9),0)+IF(L$9>0,Энергия!$D$30,0) -> 295.6 | M30: =IF(M$9>0,INDEX(План_ARPPU,1,M$9),0)+IF(M$9>0,Энергия!$D$30,0) -> 325.6 | N30: =IF(N$9>0,INDEX(План_ARPPU,1,N$9),0)+IF(N$9>0,Энергия!$D$30,0) -> 335.6 | O30: =IF(O$9>0,INDEX(План_ARPPU,1,O$9),0)+IF(O$9>0,Энергия!$D$30,0) -> 345.6 | ... S30: =IF(S$9>0,INDEX(План_ARPPU,1,S$9),0)+IF(S$9>0,Энергия!$D$30,0) -> 395.6
B31: Доход от IAP (алмазы и энергия) | C31: ₽ | D31: =SUMIF($H$8:$S$8,"Разработка",$H$31:$S$31) -> 0 | E31: =SUMIF($H$8:$S$8,"Операционка",$H$31:$S$31) -> 248198.4 | F31: =SUM($H$31:$S$31) -> 248198.4 | H31: =H29*H30 -> 0 | I31: =I29*I30 -> 0 | J31: =J29*J30 -> 0 | K31: =K29*K30 -> 0 | L31: =L29*L30 -> 3251.6 | M31: =M29*M30 -> 7163.2 | N31: =N29*N30 -> 12752.8 | O31: =O29*O30 -> 19353.6 | ... S31: =S29*S30 -> 79120
B33: Итого
B34: Доход от рекламы | C34: ₽ | D34: =SUMIF($H$8:$S$8,"Разработка",$H$34:$S$34) -> 0 | E34: =SUMIF($H$8:$S$8,"Операционка",$H$34:$S$34) -> 364317.75 | F34: =SUM($H$34:$S$34) -> 364317.75 | H34: =H19+H25 -> 0 | I34: =I19+I25 -> 0 | J34: =J19+J25 -> 0 | K34: =K19+K25 -> 0 | L34: =L19+L25 -> 7053.75 | M34: =M19+M25 -> 14215.5 | N34: =N19+N25 -> 24052.5 | O34: =O19+O25 -> 34177.5 | ... S34: =S19+S25 -> 101250
B35: Доход от IAP (алмазы и энергия) | C35: ₽ | D35: =SUMIF($H$8:$S$8,"Разработка",$H$35:$S$35) -> 0 | E35: =SUMIF($H$8:$S$8,"Операционка",$H$35:$S$35) -> 248198.4 | F35: =SUM($H$35:$S$35) -> 248198.4 | H35: =H31 -> 0 | I35: =I31 -> 0 | J35: =J31 -> 0 | K35: =K31 -> 0 | L35: =L31 -> 3251.6 | M35: =M31 -> 7163.2 | N35: =N31 -> 12752.8 | O35: =O31 -> 19353.6 | ... S35: =S31 -> 79120
B36: ИТОГО ВЫРУЧКА | C36: ₽ | D36: =SUMIF($H$8:$S$8,"Разработка",$H$36:$S$36) -> 0 | E36: =SUMIF($H$8:$S$8,"Операционка",$H$36:$S$36) -> 612516.15 | F36: =SUM($H$36:$S$36) -> 612516.15 | H36: =H34+H35 -> 0 | I36: =I34+I35 -> 0 | J36: =J34+J35 -> 0 | K36: =K34+K35 -> 0 | L36: =L34+L35 -> 10305.35 | M36: =M34+M35 -> 21378.7 | N36: =N34+N35 -> 36805.3 | O36: =O34+O35 -> 53531.1 | ... S36: =S34+S35 -> 180370
B37: Доля рекламы в выручке | C37: % | D37: =IF(D36<>0,D34/D36,0) -> 0 | E37: =IF(E36<>0,E34/E36,0) -> 0.59478881 | F37: =IF(F36<>0,F34/F36,0) -> 0.59478881 | H37: =IF(H36>0,H34/H36,0) -> 0 | I37: =IF(I36>0,I34/I36,0) -> 0 | J37: =IF(J36>0,J34/J36,0) -> 0 | K37: =IF(K36>0,K34/K36,0) -> 0 | L37: =IF(L36>0,L34/L36,0) -> 0.68447457 | M37: =IF(M36>0,M34/M36,0) -> 0.66493753 | N37: =IF(N36>0,N34/N36,0) -> 0.65350642 | O37: =IF(O36>0,O34/O36,0) -> 0.63846063 | ... S37: =IF(S36>0,S34/S36,0) -> 0.56134612
B38: ARPU: выручка на 1 MAU в месяц | C38: ₽ | E38: =IFERROR(E36/SUMIF($H$8:$S$8,"Операционка",$H$13:$S$13),0) -> 8.3335531 | F38: =IFERROR(F36/SUM($H$13:$S$13),0) -> 8.3335531 | H38: =IF(H13>0,H36/H13,0) -> 0 | I38: =IF(I13>0,I36/I13,0) -> 0 | J38: =IF(J13>0,J36/J13,0) -> 0 | K38: =IF(K13>0,K36/K13,0) -> 0 | L38: =IF(L13>0,L36/L13,0) -> 6.8702333 | M38: =IF(M13>0,M36/M13,0) -> 7.1262333 | N38: =IF(N13>0,N36/N13,0) -> 7.36106 | O38: =IF(O13>0,O36/O13,0) -> 7.6473 | ... S38: =IF(S13>0,S36/S13,0) -> 9.0185
B40: Удельные показатели базового плана (без сценарных множителей; для листов «Сценарии» и «Чувствительность»)
B41: Interstitial на 1 MAU (по плану) | C41: ₽ | E41: =IFERROR(AVERAGEIF($H$8:$S$8,"Операционка",$H$41:$S$41),0) -> 1.8225 | F41: =IFERROR(AVERAGEIF($H$8:$S$8,"Операционка",$H$41:$S$41),0) -> 1.8225 | H41: =IF(H$9>0,DAU_MAU*Int_доля*Int_показов*Дней_в_месяце*Int_eCPM/1000,0) -> 0 | I41: =IF(I$9>0,DAU_MAU*Int_доля*Int_показов*Дней_в_месяце*Int_eCPM/1000,0) -> 0 | J41: =IF(J$9>0,DAU_MAU*Int_доля*Int_показов*Дней_в_месяце*Int_eCPM/1000,0) -> 0 | K41: =IF(K$9>0,DAU_MAU*Int_доля*Int_показов*Дней_в_месяце*Int_eCPM/1000,0) -> 0 | L41: =IF(L$9>0,DAU_MAU*Int_доля*Int_показов*Дней_в_месяце*Int_eCPM/1000,0) -> 1.8225 | M41: =IF(M$9>0,DAU_MAU*Int_доля*Int_показов*Дней_в_месяце*Int_eCPM/1000,0) -> 1.8225 | N41: =IF(N$9>0,DAU_MAU*Int_доля*Int_показов*Дней_в_месяце*Int_eCPM/1000,0) -> 1.8225 | O41: =IF(O$9>0,DAU_MAU*Int_доля*Int_показов*Дней_в_месяце*Int_eCPM/1000,0) -> 1.8225 | ... S41: =IF(S$9>0,DAU_MAU*Int_доля*Int_показов*Дней_в_месяце*Int_eCPM/1000,0) -> 1.8225
B42: Rewarded на 1 MAU (по плану) | C42: ₽ | E42: =IFERROR(AVERAGEIF($H$8:$S$8,"Операционка",$H$42:$S$42),0) -> 3.06 | F42: =IFERROR(AVERAGEIF($H$8:$S$8,"Операционка",$H$42:$S$42),0) -> 3.06 | H42: =IF(H$9>0,DAU_MAU*H22*Rew_просмотров*Дней_в_месяце*Rew_eCPM/1000,0) -> 0 | I42: =IF(I$9>0,DAU_MAU*I22*Rew_просмотров*Дней_в_месяце*Rew_eCPM/1000,0) -> 0 | J42: =IF(J$9>0,DAU_MAU*J22*Rew_просмотров*Дней_в_месяце*Rew_eCPM/1000,0) -> 0 | K42: =IF(K$9>0,DAU_MAU*K22*Rew_просмотров*Дней_в_месяце*Rew_eCPM/1000,0) -> 0 | L42: =IF(L$9>0,DAU_MAU*L22*Rew_просмотров*Дней_в_месяце*Rew_eCPM/1000,0) -> 2.88 | M42: =IF(M$9>0,DAU_MAU*M22*Rew_просмотров*Дней_в_месяце*Rew_eCPM/1000,0) -> 2.916 | N42: =IF(N$9>0,DAU_MAU*N22*Rew_просмотров*Дней_в_месяце*Rew_eCPM/1000,0) -> 2.988 | O42: =IF(O$9>0,DAU_MAU*O22*Rew_просмотров*Дней_в_месяце*Rew_eCPM/1000,0) -> 3.06 | ... S42: =IF(S$9>0,DAU_MAU*S22*Rew_просмотров*Дней_в_месяце*Rew_eCPM/1000,0) -> 3.24
B43: Конверсия IAP (по плану) | C43: % | E43: =IFERROR(AVERAGEIF($H$8:$S$8,"Операционка",$H$43:$S$43),0) -> 0.0083375 | F43: =IFERROR(AVERAGEIF($H$8:$S$8,"Операционка",$H$43:$S$43),0) -> 0.0083375 | H43: =IF(H$9>0,INDEX(План_конв,1,H$9),0) -> 0 | I43: =IF(I$9>0,INDEX(План_конв,1,I$9),0) -> 0 | J43: =IF(J$9>0,INDEX(План_конв,1,J$9),0) -> 0 | K43: =IF(K$9>0,INDEX(План_конв,1,K$9),0) -> 0 | L43: =IF(L$9>0,INDEX(План_конв,1,L$9),0) -> 0.007 | M43: =IF(M$9>0,INDEX(План_конв,1,M$9),0) -> 0.0072 | N43: =IF(N$9>0,INDEX(План_конв,1,N$9),0) -> 0.0075 | O43: =IF(O$9>0,INDEX(План_конв,1,O$9),0) -> 0.008 | ... S43: =IF(S$9>0,INDEX(План_конв,1,S$9),0) -> 0.01

Sheet Энергия
B2: Энергия и ИИ-чат: экономика
B3: ₽. Энергия = токены ИИ: 1 сообщение герою = 1 энергия, со 2-й главы каждой истории глава тоже тратит энергию. Продажа энергии идёт в средний чек IAP (лист «Выручка», строка 30), затраты на токены идут в «Затраты на ИИ-сервисы» (лист «Расходы», строка 12).
B5: Показатель | C5: Ед. | D5: Значение / Разработка | E5: Операционка | F5: Итого 12 мес. | H5: =Выручка!H$5 -> Сен 2026 | I5: =Выручка!I$5 -> Окт 2026 | J5: =Выручка!J$5 -> Ноя 2026 | K5: =Выручка!K$5 -> Дек 2026 | L5: =Выручка!L$5 -> Янв 2027 | M5: =Выручка!M$5 -> Фев 2027 | N5: =Выручка!N$5 -> Мар 2027 | O5: =Выручка!O$5 -> Апр 2027 | ... S5: =Выручка!S$5 -> Авг 2027
B6: № месяца проекта | H6: =Выручка!H$6 -> 1 | I6: =Выручка!I$6 -> 2 | J6: =Выручка!J$6 -> 3 | K6: =Выручка!K$6 -> 4 | L6: =Выручка!L$6 -> 5 | M6: =Выручка!M$6 -> 6 | N6: =Выручка!N$6 -> 7 | O6: =Выручка!O$6 -> 8 | ... S6: =Выручка!S$6 -> 12
B7: Дата (начало месяца) | H7: =Выручка!H$7 -> 46266 | I7: =Выручка!I$7 -> 46296 | J7: =Выручка!J$7 -> 46327 | K7: =Выручка!K$7 -> 46357 | L7: =Выручка!L$7 -> 46388 | M7: =Выручка!M$7 -> 46419 | N7: =Выручка!N$7 -> 46447 | O7: =Выручка!O$7 -> 46478 | ... S7: =Выручка!S$7 -> 46600
B8: Фаза | H8: =Выручка!H$8 -> Разработка | I8: =Выручка!I$8 -> Разработка | J8: =Выручка!J$8 -> Разработка | K8: =Выручка!K$8 -> Разработка | L8: =Выручка!L$8 -> Операционка | M8: =Выручка!M$8 -> Операционка | N8: =Выручка!N$8 -> Операционка | O8: =Выручка!O$8 -> Операционка | ... S8: =Выручка!S$8 -> Операционка
B9: Месяцев после релиза | H9: =Выручка!H$9 -> 0 | I9: =Выручка!I$9 -> 0 | J9: =Выручка!J$9 -> 0 | K9: =Выручка!K$9 -> 0 | L9: =Выручка!L$9 -> 1 | M9: =Выручка!M$9 -> 2 | N9: =Выручка!N$9 -> 3 | O9: =Выручка!O$9 -> 4 | ... S9: =Выручка!S$9 -> 8
B11: 1. Вводные (меняйте жёлтые ячейки)
B12: Курс ₽ за $ | C12: ₽ | D12: 90 | E12: Допущение. Обновите по курсу ЦБ на дату защиты
B13: Себестоимость одного ответа героя | C13: $ | D13: 0.0005 | E13: Замер 29.10.2026: ~3,8 тыс. токенов на входе, модель z-ai/glm-5.3-flash через OpenRouter
B14: Себестоимость одного ответа героя | C14: ₽ | D14: =D12*D13 -> 0.045 | E14: Расчёт
B15: Доля DAU, пишущих герою в день | C15: % | D15: 0.25 | E15: Гипотеза, проверить в закрытой бете
B16: Сообщений в день на пишущего | C16: шт. | D16: 6 | E16: Гипотеза, проверить в закрытой бете
B17: Цена сообщения | C17: энергии | D17: 1 | E17: Как в приложении
B18: Цена главы (со 2-й главы истории) | C18: энергии | D18: 5 | E18: Решение: первая глава каждой истории бесплатна. В приложении пока не включено
B19: Пак «5 энергии» | C19: ₽ | D19: 59 | E19: Цены в рублях, как будут в магазине приложений
B20: Пак «15 энергии» | C20: ₽ | D20: 149
B21: Пак «30 энергии» (лучшая выгода) | C21: ₽ | D21: 249
B22: Доля покупок: пак 5 | C22: % | D22: 0.2 | E22: Гипотеза
B23: Доля покупок: пак 15 | C23: % | D23: 0.5 | E23: Гипотеза
B24: Доля покупок: пак 30 | C24: % | D24: 0.3 | E24: Гипотеза. Три доли должны давать 100%
B25: Средняя цена пака | C25: ₽ | D25: =D19*D22+D20*D23+D21*D24 -> 161 | E25: Расчёт
B26: Средний размер пака | C26: энергии | D26: =5*D22+15*D23+30*D24 -> 17.5 | E26: Расчёт
B27: Средняя цена одной энергии | C27: ₽ | D27: =D25/D26 -> 9.2 | E27: Расчёт
B28: Доля платящих, которые покупают энергию | C28: % | D28: 0.6 | E28: Платящие = конверсия IAP (лист «Допущения», п. 4). Гипотеза
B29: Паков энергии в месяц на такого плательщика | C29: шт. | D29: 1 | E29: Гипотеза
B30: Добавка к среднему чеку IAP за энергию | C30: ₽ | D30: =D28*D29*D25 -> 96.6 | E30: Расчёт. Уходит в лист «Выручка», строка 30
B31: Проверка: доли паков в сумме | D31: =IF(ABS(D22+D23+D24-1)<0.0001,"OK","ОШИБКА") -> OK
B32: Расход энергии на пишущего игрока в месяц | C32: энергии | D32: =D16*Дней_в_месяце*D17 -> 180
B34: 2. Помесячный расчёт (активный сценарий)
B35: MAU | C35: чел. | H35: =Выручка!H13 -> 0 | I35: =Выручка!I13 -> 0 | J35: =Выручка!J13 -> 0 | K35: =Выручка!K13 -> 0 | L35: =Выручка!L13 -> 1500 | M35: =Выручка!M13 -> 3000 | N35: =Выручка!N13 -> 5000 | O35: =Выручка!O13 -> 7000 | ... S35: =Выручка!S13 -> 20000
B36: DAU | C36: чел. | H36: =Выручка!H14 -> 0 | I36: =Выручка!I14 -> 0 | J36: =Выручка!J14 -> 0 | K36: =Выручка!K14 -> 0 | L36: =Выручка!L14 -> 450 | M36: =Выручка!M14 -> 900 | N36: =Выручка!N14 -> 1500 | O36: =Выручка!O14 -> 2100 | ... S36: =Выручка!S14 -> 6000
B37: Пишущих герою в день | C37: чел. | H37: =H36*$D$15 -> 0 | I37: =I36*$D$15 -> 0 | J37: =J36*$D$15 -> 0 | K37: =K36*$D$15 -> 0 | L37: =L36*$D$15 -> 112.5 | M37: =M36*$D$15 -> 225 | N37: =N36*$D$15 -> 375 | O37: =O36*$D$15 -> 525 | ... S37: =S36*$D$15 -> 1500
B38: Сообщений в месяц | C38: шт. | D38: =SUMIF($H$8:$S$8,"Разработка",$H38:$S38) -> 0 | E38: =SUMIF($H$8:$S$8,"Операционка",$H38:$S38) -> 992250 | F38: =SUM($H38:$S38) -> 992250 | H38: =H37*$D$16*Дней_в_месяце -> 0 | I38: =I37*$D$16*Дней_в_месяце -> 0 | J38: =J37*$D$16*Дней_в_месяце -> 0 | K38: =K37*$D$16*Дней_в_месяце -> 0 | L38: =L37*$D$16*Дней_в_месяце -> 20250 | M38: =M37*$D$16*Дней_в_месяце -> 40500 | N38: =N37*$D$16*Дней_в_месяце -> 67500 | O38: =O37*$D$16*Дней_в_месяце -> 94500 | ... S38: =S37*$D$16*Дней_в_месяце -> 270000
B39: Затраты на токены чата | C39: ₽ | D39: =SUMIF($H$8:$S$8,"Разработка",$H39:$S39) -> 0 | E39: =SUMIF($H$8:$S$8,"Операционка",$H39:$S39) -> 44651.25 | F39: =SUM($H39:$S39) -> 44651.25 | H39: =H38*$D$14 -> 0 | I39: =I38*$D$14 -> 0 | J39: =J38*$D$14 -> 0 | K39: =K38*$D$14 -> 0 | L39: =L38*$D$14 -> 911.25 | M39: =M38*$D$14 -> 1822.5 | N39: =N38*$D$14 -> 3037.5 | O39: =O38*$D$14 -> 4252.5 | ... S39: =S38*$D$14 -> 12150
B40: Затраты на токены на 1 MAU | C40: ₽ | H40: =IF(H35>0,H39/H35,0) -> 0 | I40: =IF(I35>0,I39/I35,0) -> 0 | J40: =IF(J35>0,J39/J35,0) -> 0 | K40: =IF(K35>0,K39/K35,0) -> 0 | L40: =IF(L35>0,L39/L35,0) -> 0.6075 | M40: =IF(M35>0,M39/M35,0) -> 0.6075 | N40: =IF(N35>0,N39/N35,0) -> 0.6075 | O40: =IF(O35>0,O39/O35,0) -> 0.6075 | ... S40: =IF(S35>0,S39/S35,0) -> 0.6075
B41: Платящих всего (IAP) | C41: чел. | H41: =Выручка!H29 -> 0 | I41: =Выручка!I29 -> 0 | J41: =Выручка!J29 -> 0 | K41: =Выручка!K29 -> 0 | L41: =Выручка!L29 -> 11 | M41: =Выручка!M29 -> 22 | N41: =Выручка!N29 -> 38 | O41: =Выручка!O29 -> 56 | ... S41: =Выручка!S29 -> 200
B42: Выручка от энергии (валовая) | C42: ₽ | D42: =SUMIF($H$8:$S$8,"Разработка",$H42:$S42) -> 0 | E42: =SUMIF($H$8:$S$8,"Операционка",$H42:$S42) -> 64142.4 | F42: =SUM($H42:$S42) -> 64142.4 | H42: =H41*$D$30 -> 0 | I42: =I41*$D$30 -> 0 | J42: =J41*$D$30 -> 0 | K42: =K41*$D$30 -> 0 | L42: =L41*$D$30 -> 1062.6 | M42: =M41*$D$30 -> 2125.2 | N42: =N41*$D$30 -> 3670.8 | O42: =O41*$D$30 -> 5409.6 | ... S42: =S41*$D$30 -> 19320
B43: Комиссия магазина с энергии | C43: ₽ | D43: =SUMIF($H$8:$S$8,"Разработка",$H43:$S43) -> 0 | E43: =SUMIF($H$8:$S$8,"Операционка",$H43:$S43) -> 9621.36 | F43: =SUM($H43:$S43) -> 9621.36 | H43: =H42*Комиссия_стора -> 0 | I43: =I42*Комиссия_стора -> 0 | J43: =J42*Комиссия_стора -> 0 | K43: =K42*Комиссия_стора -> 0 | L43: =L42*Комиссия_стора -> 159.39 | M43: =M42*Комиссия_стора -> 318.78 | N43: =N42*Комиссия_стора -> 550.62 | O43: =O42*Комиссия_стора -> 811.44 | ... S43: =S42*Комиссия_стора -> 2898
B44: Результат энергии: выручка − комиссия − токены | C44: ₽ | D44: =SUMIF($H$8:$S$8,"Разработка",$H44:$S44) -> 0 | E44: =SUMIF($H$8:$S$8,"Операционка",$H44:$S44) -> 9869.79 | F44: =SUM($H44:$S44) -> 9869.79 | H44: =H42-H43-H39 -> 0 | I44: =I42-I43-I39 -> 0 | J44: =J42-J43-J39 -> 0 | K44: =K42-K43-K39 -> 0 | L44: =L42-L43-L39 -> -8.04 | M44: =M42-M43-M39 -> -16.08 | N44: =N42-N43-N39 -> 82.68 | O44: =O42-O43-O39 -> 345.66 | ... S44: =S42-S43-S39 -> 4272
B45: Энергии продано | C45: шт. | D45: =SUMIF($H$8:$S$8,"Разработка",$H45:$S45) -> 0 | E45: =SUMIF($H$8:$S$8,"Операционка",$H45:$S45) -> 6972 | F45: =SUM($H45:$S45) -> 6972 | H45: =IF($D$27>0,H42/$D$27,0) -> 0 | I45: =IF($D$27>0,I42/$D$27,0) -> 0 | J45: =IF($D$27>0,J42/$D$27,0) -> 0 | K45: =IF($D$27>0,K42/$D$27,0) -> 0 | L45: =IF($D$27>0,L42/$D$27,0) -> 115.5 | M45: =IF($D$27>0,M42/$D$27,0) -> 231 | N45: =IF($D$27>0,N42/$D$27,0) -> 399 | O45: =IF($D$27>0,O42/$D$27,0) -> 588 | ... S45: =IF($D$27>0,S42/$D$27,0) -> 2100
B46: Энергии потрачено на чат | C46: шт. | D46: =SUMIF($H$8:$S$8,"Разработка",$H46:$S46) -> 0 | E46: =SUMIF($H$8:$S$8,"Операционка",$H46:$S46) -> 992250 | F46: =SUM($H46:$S46) -> 992250 | H46: =H38*$D$17 -> 0 | I46: =I38*$D$17 -> 0 | J46: =J38*$D$17 -> 0 | K46: =K38*$D$17 -> 0 | L46: =L38*$D$17 -> 20250 | M46: =M38*$D$17 -> 40500 | N46: =N38*$D$17 -> 67500 | O46: =O38*$D$17 -> 94500 | ... S46: =S38*$D$17 -> 270000
B47: Покрытие токенов чата продажей энергии (после комиссии) | C47: раз | F47: =IFERROR((F42-F43)/F39,0) -> 1.2210417
B48: Себестоимость сообщения / цена сообщения в ₽ (доля себестоимости) | C48: % | D48: =IFERROR(D14/(D27*D17),0) -> 0.0048913043
B50: Вывод
B51: ="Чат сам по себе окупается продажей энергии: покрытие "&FIXED(F47,2)&" раза. Себестоимость сообщения "&FIXED(D14,3)&" ₽ при цене энергии "&FIXED(D27,1)&" ₽." -> Чат сам по себе окупается продажей энергии: покрытие 1.22 раза. Себестоимость сообщения 0.045 ₽ при цене энергии 9.2 ₽.

Sheet Расходы
B2: Операционные расходы (OpEx)
B3: ₽. Ставки по фазам проекта задаются в «Допущениях», п. 5; маркетинг после релиза зависит от сценария.
B5: Показатель | C5: Ед. | D5: ="Разработка"&CHAR(10)&"("&Дев_мес&" мес.)" -> Разработка (4 мес.) | E5: ="Операционка"&CHAR(10)&"("&Опер_мес&" мес.)" -> Операционка (8 мес.) | F5: ="Итого"&CHAR(10)&"12 мес." -> Итого 12 мес. | H5: =Выручка!H$5 -> Сен 2026 | I5: =Выручка!I$5 -> Окт 2026 | J5: =Выручка!J$5 -> Ноя 2026 | K5: =Выручка!K$5 -> Дек 2026 | L5: =Выручка!L$5 -> Янв 2027 | M5: =Выручка!M$5 -> Фев 2027 | N5: =Выручка!N$5 -> Мар 2027 | O5: =Выручка!O$5 -> Апр 2027 | ... S5: =Выручка!S$5 -> Авг 2027
B6: № месяца проекта | H6: =Выручка!H$6 -> 1 | I6: =Выручка!I$6 -> 2 | J6: =Выручка!J$6 -> 3 | K6: =Выручка!K$6 -> 4 | L6: =Выручка!L$6 -> 5 | M6: =Выручка!M$6 -> 6 | N6: =Выручка!N$6 -> 7 | O6: =Выручка!O$6 -> 8 | ... S6: =Выручка!S$6 -> 12
B7: Дата (начало месяца) | H7: =Выручка!H$7 -> 46266 | I7: =Выручка!I$7 -> 46296 | J7: =Выручка!J$7 -> 46327 | K7: =Выручка!K$7 -> 46357 | L7: =Выручка!L$7 -> 46388 | M7: =Выручка!M$7 -> 46419 | N7: =Выручка!N$7 -> 46447 | O7: =Выручка!O$7 -> 46478 | ... S7: =Выручка!S$7 -> 46600
B8: Фаза | H8: =Выручка!H$8 -> Разработка | I8: =Выручка!I$8 -> Разработка | J8: =Выручка!J$8 -> Разработка | K8: =Выручка!K$8 -> Разработка | L8: =Выручка!L$8 -> Операционка | M8: =Выручка!M$8 -> Операционка | N8: =Выручка!N$8 -> Операционка | O8: =Выручка!O$8 -> Операционка | ... S8: =Выручка!S$8 -> Операционка
B9: Месяцев после релиза | H9: =Выручка!H$9 -> 0 | I9: =Выручка!I$9 -> 0 | J9: =Выручка!J$9 -> 0 | K9: =Выручка!K$9 -> 0 | L9: =Выручка!L$9 -> 1 | M9: =Выручка!M$9 -> 2 | N9: =Выручка!N$9 -> 3 | O9: =Выручка!O$9 -> 4 | ... S9: =Выручка!S$9 -> 8
B11: Операционные расходы
B12: Затраты на ИИ-сервисы (контент + токены чата) | C12: ₽ | D12: =SUMIF($H$8:$S$8,"Разработка",$H$12:$S$12) -> 16000 | E12: =SUMIF($H$8:$S$8,"Операционка",$H$12:$S$12) -> 76651.25 | F12: =SUM($H$12:$S$12) -> 92651.25 | H12: =IF(H$6>=Допущения!$C$50,IF(H$8="Разработка",Зп_дев,Зп_опер),0)+Энергия!H39 -> 4000 | I12: =IF(I$6>=Допущения!$C$50,IF(I$8="Разработка",Зп_дев,Зп_опер),0)+Энергия!I39 -> 4000 | J12: =IF(J$6>=Допущения!$C$50,IF(J$8="Разработка",Зп_дев,Зп_опер),0)+Энергия!J39 -> 4000 | K12: =IF(K$6>=Допущения!$C$50,IF(K$8="Разработка",Зп_дев,Зп_опер),0)+Энергия!K39 -> 4000 | L12: =IF(L$6>=Допущения!$C$50,IF(L$8="Разработка",Зп_дев,Зп_опер),0)+Энергия!L39 -> 4911.25 | M12: =IF(M$6>=Допущения!$C$50,IF(M$8="Разработка",Зп_дев,Зп_опер),0)+Энергия!M39 -> 5822.5 | N12: =IF(N$6>=Допущения!$C$50,IF(N$8="Разработка",Зп_дев,Зп_опер),0)+Энергия!N39 -> 7037.5 | O12: =IF(O$6>=Допущения!$C$50,IF(O$8="Разработка",Зп_дев,Зп_опер),0)+Энергия!O39 -> 8252.5 | ... S12: =IF(S$6>=Допущения!$C$50,IF(S$8="Разработка",Зп_дев,Зп_опер),0)+Энергия!S39 -> 16150
B13: Поддержка серверов и хостинг | C13: ₽ | D13: =SUMIF($H$8:$S$8,"Разработка",$H$13:$S$13) -> 6000 | E13: =SUMIF($H$8:$S$8,"Операционка",$H$13:$S$13) -> 16000 | F13: =SUM($H$13:$S$13) -> 22000 | H13: =IF(H$6>=Допущения!$C$51,IF(H$8="Разработка",Серверы_дев,Серверы_опер),0) -> 0 | I13: =IF(I$6>=Допущения!$C$51,IF(I$8="Разработка",Серверы_дев,Серверы_опер),0) -> 2000 | J13: =IF(J$6>=Допущения!$C$51,IF(J$8="Разработка",Серверы_дев,Серверы_опер),0) -> 2000 | K13: =IF(K$6>=Допущения!$C$51,IF(K$8="Разработка",Серверы_дев,Серверы_опер),0) -> 2000 | L13: =IF(L$6>=Допущения!$C$51,IF(L$8="Разработка",Серверы_дев,Серверы_опер),0) -> 2000 | M13: =IF(M$6>=Допущения!$C$51,IF(M$8="Разработка",Серверы_дев,Серверы_опер),0) -> 2000 | N13: =IF(N$6>=Допущения!$C$51,IF(N$8="Разработка",Серверы_дев,Серверы_опер),0) -> 2000 | O13: =IF(O$6>=Допущения!$C$51,IF(O$8="Разработка",Серверы_дев,Серверы_опер),0) -> 2000 | ... S13: =IF(S$6>=Допущения!$C$51,IF(S$8="Разработка",Серверы_дев,Серверы_опер),0) -> 2000
B14: Бухгалтерия и юр. сопровождение | C14: ₽ | D14: =SUMIF($H$8:$S$8,"Разработка",$H$14:$S$14) -> 10000 | E14: =SUMIF($H$8:$S$8,"Операционка",$H$14:$S$14) -> 80000 | F14: =SUM($H$14:$S$14) -> 90000 | H14: =IF(H$6>=Допущения!$C$52,IF(H$8="Разработка",Бух_дев,Бух_опер),0) -> 0 | I14: =IF(I$6>=Допущения!$C$52,IF(I$8="Разработка",Бух_дев,Бух_опер),0) -> 0 | J14: =IF(J$6>=Допущения!$C$52,IF(J$8="Разработка",Бух_дев,Бух_опер),0) -> 0 | K14: =IF(K$6>=Допущения!$C$52,IF(K$8="Разработка",Бух_дев,Бух_опер),0) -> 10000 | L14: =IF(L$6>=Допущения!$C$52,IF(L$8="Разработка",Бух_дев,Бух_опер),0) -> 10000 | M14: =IF(M$6>=Допущения!$C$52,IF(M$8="Разработка",Бух_дев,Бух_опер),0) -> 10000 | N14: =IF(N$6>=Допущения!$C$52,IF(N$8="Разработка",Бух_дев,Бух_опер),0) -> 10000 | O14: =IF(O$6>=Допущения!$C$52,IF(O$8="Разработка",Бух_дев,Бух_опер),0) -> 10000 | ... S14: =IF(S$6>=Допущения!$C$52,IF(S$8="Разработка",Бух_дев,Бух_опер),0) -> 10000
B15: Маркетинг и реклама (трафик, посевы) | C15: ₽ | D15: =SUMIF($H$8:$S$8,"Разработка",$H$15:$S$15) -> 20000 | E15: =SUMIF($H$8:$S$8,"Операционка",$H$15:$S$15) -> 240000 | F15: =SUM($H$15:$S$15) -> 260000 | H15: =IF(H$6>=Допущения!$C$53,IF(H$8="Разработка",Маркетинг_дев,Сц_маркетинг),0) -> 0 | I15: =IF(I$6>=Допущения!$C$53,IF(I$8="Разработка",Маркетинг_дев,Сц_маркетинг),0) -> 0 | J15: =IF(J$6>=Допущения!$C$53,IF(J$8="Разработка",Маркетинг_дев,Сц_маркетинг),0) -> 10000 | K15: =IF(K$6>=Допущения!$C$53,IF(K$8="Разработка",Маркетинг_дев,Сц_маркетинг),0) -> 10000 | L15: =IF(L$6>=Допущения!$C$53,IF(L$8="Разработка",Маркетинг_дев,Сц_маркетинг),0) -> 30000 | M15: =IF(M$6>=Допущения!$C$53,IF(M$8="Разработка",Маркетинг_дев,Сц_маркетинг),0) -> 30000 | N15: =IF(N$6>=Допущения!$C$53,IF(N$8="Разработка",Маркетинг_дев,Сц_маркетинг),0) -> 30000 | O15: =IF(O$6>=Допущения!$C$53,IF(O$8="Разработка",Маркетинг_дев,Сц_маркетинг),0) -> 30000 | ... S15: =IF(S$6>=Допущения!$C$53,IF(S$8="Разработка",Маркетинг_дев,Сц_маркетинг),0) -> 30000
B16: ИТОГО OpEx | C16: ₽ | D16: =SUMIF($H$8:$S$8,"Разработка",$H$16:$S$16) -> 52000 | E16: =SUMIF($H$8:$S$8,"Операционка",$H$16:$S$16) -> 412651.25 | F16: =SUM($H$16:$S$16) -> 464651.25 | H16: =SUM(H12:H15) -> 4000 | I16: =SUM(I12:I15) -> 6000 | J16: =SUM(J12:J15) -> 16000 | K16: =SUM(K12:K15) -> 26000 | L16: =SUM(L12:L15) -> 46911.25 | M16: =SUM(M12:M15) -> 47822.5 | N16: =SUM(N12:N15) -> 49037.5 | O16: =SUM(O12:O15) -> 50252.5 | ... S16: =SUM(S12:S15) -> 58150
B18: Переменные расходы
B19: Комиссия магазина приложений с IAP | C19: ₽ | D19: =SUMIF($H$8:$S$8,"Разработка",$H$19:$S$19) -> 0 | E19: =SUMIF($H$8:$S$8,"Операционка",$H$19:$S$19) -> 37229.76 | F19: =SUM($H$19:$S$19) -> 37229.76 | H19: =Выручка!H31*Комиссия_стора -> 0 | I19: =Выручка!I31*Комиссия_стора -> 0 | J19: =Выручка!J31*Комиссия_стора -> 0 | K19: =Выручка!K31*Комиссия_стора -> 0 | L19: =Выручка!L31*Комиссия_стора -> 487.74 | M19: =Выручка!M31*Комиссия_стора -> 1074.48 | N19: =Выручка!N31*Комиссия_стора -> 1912.92 | O19: =Выручка!O31*Комиссия_стора -> 2903.04 | ... S19: =Выручка!S31*Комиссия_стора -> 11868
B20: В docx комиссия не учтена (ставка 0%). Ставка задаётся в «Допущениях», п. 3.
B22: Справочно
B23: Доля маркетинга в OpEx | C23: % | D23: =IF(D16<>0,D15/D16,0) -> 0.38461538 | E23: =IF(E16<>0,E15/E16,0) -> 0.58160493 | F23: =IF(F16<>0,F15/F16,0) -> 0.55955945 | H23: =IF(H16>0,H15/H16,0) -> 0 | I23: =IF(I16>0,I15/I16,0) -> 0 | J23: =IF(J16>0,J15/J16,0) -> 0.625 | K23: =IF(K16>0,K15/K16,0) -> 0.38461538 | L23: =IF(L16>0,L15/L16,0) -> 0.63950545 | M23: =IF(M16>0,M15/M16,0) -> 0.62731978 | N23: =IF(N16>0,N15/N16,0) -> 0.6117767 | O23: =IF(O16>0,O15/O16,0) -> 0.59698522 | ... S23: =IF(S16>0,S15/S16,0) -> 0.51590714

Sheet ОПиУ
B2: Отчёт о прибылях и убытках (ОПиУ / P&L)
B3: ₽. Расходы со знаком минус.
B5: Показатель | C5: Ед. | D5: ="Разработка"&CHAR(10)&"("&Дев_мес&" мес.)" -> Разработка (4 мес.) | E5: ="Операционка"&CHAR(10)&"("&Опер_мес&" мес.)" -> Операционка (8 мес.) | F5: ="Итого"&CHAR(10)&"12 мес." -> Итого 12 мес. | H5: =Выручка!H$5 -> Сен 2026 | I5: =Выручка!I$5 -> Окт 2026 | J5: =Выручка!J$5 -> Ноя 2026 | K5: =Выручка!K$5 -> Дек 2026 | L5: =Выручка!L$5 -> Янв 2027 | M5: =Выручка!M$5 -> Фев 2027 | N5: =Выручка!N$5 -> Мар 2027 | O5: =Выручка!O$5 -> Апр 2027 | ... S5: =Выручка!S$5 -> Авг 2027
B6: № месяца проекта | H6: =Выручка!H$6 -> 1 | I6: =Выручка!I$6 -> 2 | J6: =Выручка!J$6 -> 3 | K6: =Выручка!K$6 -> 4 | L6: =Выручка!L$6 -> 5 | M6: =Выручка!M$6 -> 6 | N6: =Выручка!N$6 -> 7 | O6: =Выручка!O$6 -> 8 | ... S6: =Выручка!S$6 -> 12
B7: Дата (начало месяца) | H7: =Выручка!H$7 -> 46266 | I7: =Выручка!I$7 -> 46296 | J7: =Выручка!J$7 -> 46327 | K7: =Выручка!K$7 -> 46357 | L7: =Выручка!L$7 -> 46388 | M7: =Выручка!M$7 -> 46419 | N7: =Выручка!N$7 -> 46447 | O7: =Выручка!O$7 -> 46478 | ... S7: =Выручка!S$7 -> 46600
B8: Фаза | H8: =Выручка!H$8 -> Разработка | I8: =Выручка!I$8 -> Разработка | J8: =Выручка!J$8 -> Разработка | K8: =Выручка!K$8 -> Разработка | L8: =Выручка!L$8 -> Операционка | M8: =Выручка!M$8 -> Операционка | N8: =Выручка!N$8 -> Операционка | O8: =Выручка!O$8 -> Операционка | ... S8: =Выручка!S$8 -> Операционка
B9: Месяцев после релиза | H9: =Выручка!H$9 -> 0 | I9: =Выручка!I$9 -> 0 | J9: =Выручка!J$9 -> 0 | K9: =Выручка!K$9 -> 0 | L9: =Выручка!L$9 -> 1 | M9: =Выручка!M$9 -> 2 | N9: =Выручка!N$9 -> 3 | O9: =Выручка!O$9 -> 4 | ... S9: =Выручка!S$9 -> 8
B11: Выручка
B12: Interstitial | C12: ₽ | D12: =SUMIF($H$8:$S$8,"Разработка",$H$12:$S$12) -> 0 | E12: =SUMIF($H$8:$S$8,"Операционка",$H$12:$S$12) -> 133953.75 | F12: =SUM($H$12:$S$12) -> 133953.75 | H12: =Выручка!H19 -> 0 | I12: =Выручка!I19 -> 0 | J12: =Выручка!J19 -> 0 | K12: =Выручка!K19 -> 0 | L12: =Выручка!L19 -> 2733.75 | M12: =Выручка!M19 -> 5467.5 | N12: =Выручка!N19 -> 9112.5 | O12: =Выручка!O19 -> 12757.5 | ... S12: =Выручка!S19 -> 36450
B13: Rewarded | C13: ₽ | D13: =SUMIF($H$8:$S$8,"Разработка",$H$13:$S$13) -> 0 | E13: =SUMIF($H$8:$S$8,"Операционка",$H$13:$S$13) -> 230364 | F13: =SUM($H$13:$S$13) -> 230364 | H13: =Выручка!H25 -> 0 | I13: =Выручка!I25 -> 0 | J13: =Выручка!J25 -> 0 | K13: =Выручка!K25 -> 0 | L13: =Выручка!L25 -> 4320 | M13: =Выручка!M25 -> 8748 | N13: =Выручка!N25 -> 14940 | O13: =Выручка!O25 -> 21420 | ... S13: =Выручка!S25 -> 64800
B14: IAP (внутриигровые покупки) | C14: ₽ | D14: =SUMIF($H$8:$S$8,"Разработка",$H$14:$S$14) -> 0 | E14: =SUMIF($H$8:$S$8,"Операционка",$H$14:$S$14) -> 248198.4 | F14: =SUM($H$14:$S$14) -> 248198.4 | H14: =Выручка!H31 -> 0 | I14: =Выручка!I31 -> 0 | J14: =Выручка!J31 -> 0 | K14: =Выручка!K31 -> 0 | L14: =Выручка!L31 -> 3251.6 | M14: =Выручка!M31 -> 7163.2 | N14: =Выручка!N31 -> 12752.8 | O14: =Выручка!O31 -> 19353.6 | ... S14: =Выручка!S31 -> 79120
B15: 1. Выручка | C15: ₽ | D15: =SUMIF($H$8:$S$8,"Разработка",$H$15:$S$15) -> 0 | E15: =SUMIF($H$8:$S$8,"Операционка",$H$15:$S$15) -> 612516.15 | F15: =SUM($H$15:$S$15) -> 612516.15 | H15: =SUM(H12:H14) -> 0 | I15: =SUM(I12:I14) -> 0 | J15: =SUM(J12:J14) -> 0 | K15: =SUM(K12:K14) -> 0 | L15: =SUM(L12:L14) -> 10305.35 | M15: =SUM(M12:M14) -> 21378.7 | N15: =SUM(N12:N14) -> 36805.3 | O15: =SUM(O12:O14) -> 53531.1 | ... S15: =SUM(S12:S14) -> 180370
B16: Комиссия магазина приложений | C16: ₽ | D16: =SUMIF($H$8:$S$8,"Разработка",$H$16:$S$16) -> 0 | E16: =SUMIF($H$8:$S$8,"Операционка",$H$16:$S$16) -> -37229.76 | F16: =SUM($H$16:$S$16) -> -37229.76 | H16: =-Расходы!H19 -> 0 | I16: =-Расходы!I19 -> 0 | J16: =-Расходы!J19 -> 0 | K16: =-Расходы!K19 -> 0 | L16: =-Расходы!L19 -> -487.74 | M16: =-Расходы!M19 -> -1074.48 | N16: =-Расходы!N19 -> -1912.92 | O16: =-Расходы!O19 -> -2903.04 | ... S16: =-Расходы!S19 -> -11868
B17: 2. Валовая прибыль | C17: ₽ | D17: =SUMIF($H$8:$S$8,"Разработка",$H$17:$S$17) -> 0 | E17: =SUMIF($H$8:$S$8,"Операционка",$H$17:$S$17) -> 575286.39 | F17: =SUM($H$17:$S$17) -> 575286.39 | H17: =H15+H16 -> 0 | I17: =I15+I16 -> 0 | J17: =J15+J16 -> 0 | K17: =K15+K16 -> 0 | L17: =L15+L16 -> 9817.61 | M17: =M15+M16 -> 20304.22 | N17: =N15+N16 -> 34892.38 | O17: =O15+O16 -> 50628.06 | ... S17: =S15+S16 -> 168502
B19: Операционные расходы
B20: Затраты на ИИ-сервисы | C20: ₽ | D20: =SUMIF($H$8:$S$8,"Разработка",$H$20:$S$20) -> -16000 | E20: =SUMIF($H$8:$S$8,"Операционка",$H$20:$S$20) -> -76651.25 | F20: =SUM($H$20:$S$20) -> -92651.25 | H20: =-Расходы!H12 -> -4000 | I20: =-Расходы!I12 -> -4000 | J20: =-Расходы!J12 -> -4000 | K20: =-Расходы!K12 -> -4000 | L20: =-Расходы!L12 -> -4911.25 | M20: =-Расходы!M12 -> -5822.5 | N20: =-Расходы!N12 -> -7037.5 | O20: =-Расходы!O12 -> -8252.5 | ... S20: =-Расходы!S12 -> -16150
B21: Поддержка серверов и хостинг | C21: ₽ | D21: =SUMIF($H$8:$S$8,"Разработка",$H$21:$S$21) -> -6000 | E21: =SUMIF($H$8:$S$8,"Операционка",$H$21:$S$21) -> -16000 | F21: =SUM($H$21:$S$21) -> -22000 | H21: =-Расходы!H13 -> 0 | I21: =-Расходы!I13 -> -2000 | J21: =-Расходы!J13 -> -2000 | K21: =-Расходы!K13 -> -2000 | L21: =-Расходы!L13 -> -2000 | M21: =-Расходы!M13 -> -2000 | N21: =-Расходы!N13 -> -2000 | O21: =-Расходы!O13 -> -2000 | ... S21: =-Расходы!S13 -> -2000
B22: Бухгалтерия и юр. сопровождение | C22: ₽ | D22: =SUMIF($H$8:$S$8,"Разработка",$H$22:$S$22) -> -10000 | E22: =SUMIF($H$8:$S$8,"Операционка",$H$22:$S$22) -> -80000 | F22: =SUM($H$22:$S$22) -> -90000 | H22: =-Расходы!H14 -> 0 | I22: =-Расходы!I14 -> 0 | J22: =-Расходы!J14 -> 0 | K22: =-Расходы!K14 -> -10000 | L22: =-Расходы!L14 -> -10000 | M22: =-Расходы!M14 -> -10000 | N22: =-Расходы!N14 -> -10000 | O22: =-Расходы!O14 -> -10000 | ... S22: =-Расходы!S14 -> -10000
B23: Маркетинг и реклама | C23: ₽ | D23: =SUMIF($H$8:$S$8,"Разработка",$H$23:$S$23) -> -20000 | E23: =SUMIF($H$8:$S$8,"Операционка",$H$23:$S$23) -> -240000 | F23: =SUM($H$23:$S$23) -> -260000 | H23: =-Расходы!H15 -> 0 | I23: =-Расходы!I15 -> 0 | J23: =-Расходы!J15 -> -10000 | K23: =-Расходы!K15 -> -10000 | L23: =-Расходы!L15 -> -30000 | M23: =-Расходы!M15 -> -30000 | N23: =-Расходы!N15 -> -30000 | O23: =-Расходы!O15 -> -30000 | ... S23: =-Расходы!S15 -> -30000
B24: 3. Операционные расходы (OpEx) | C24: ₽ | D24: =SUMIF($H$8:$S$8,"Разработка",$H$24:$S$24) -> -52000 | E24: =SUMIF($H$8:$S$8,"Операционка",$H$24:$S$24) -> -412651.25 | F24: =SUM($H$24:$S$24) -> -464651.25 | H24: =SUM(H20:H23) -> -4000 | I24: =SUM(I20:I23) -> -6000 | J24: =SUM(J20:J23) -> -16000 | K24: =SUM(K20:K23) -> -26000 | L24: =SUM(L20:L23) -> -46911.25 | M24: =SUM(M20:M23) -> -47822.5 | N24: =SUM(N20:N23) -> -49037.5 | O24: =SUM(O20:O23) -> -50252.5 | ... S24: =SUM(S20:S23) -> -58150
B26: 4. EBITDA (прибыль до процентов и налогов) | C26: ₽ | D26: =SUMIF($H$8:$S$8,"Разработка",$H$26:$S$26) -> -52000 | E26: =SUMIF($H$8:$S$8,"Операционка",$H$26:$S$26) -> 162635.14 | F26: =SUM($H$26:$S$26) -> 110635.14 | H26: =H17+H24 -> -4000 | I26: =I17+I24 -> -6000 | J26: =J17+J24 -> -16000 | K26: =K17+K24 -> -26000 | L26: =L17+L24 -> -37093.64 | M26: =M17+M24 -> -27518.28 | N26: =N17+N24 -> -14145.12 | O26: =O17+O24 -> 375.56 | ... S26: =S17+S24 -> 110352
B27: Рентабельность по EBITDA | C27: % | D27: =IF(D15<>0,D26/D15,0) -> 0 | E27: =IF(E15<>0,E26/E15,0) -> 0.26551976 | F27: =IF(F15<>0,F26/F15,0) -> 0.18062404 | H27: =IF(H15>0,H26/H15,0) -> 0 | I27: =IF(I15>0,I26/I15,0) -> 0 | J27: =IF(J15>0,J26/J15,0) -> 0 | K27: =IF(K15>0,K26/K15,0) -> 0 | L27: =IF(L15>0,L26/L15,0) -> -3.5994547 | M27: =IF(M15>0,M26/M15,0) -> -1.2871821 | N27: =IF(N15>0,N26/N15,0) -> -0.38432291 | O27: =IF(O15>0,O26/O15,0) -> 0.0070157348 | ... S27: =IF(S15>0,S26/S15,0) -> 0.61180906
B28: 5. Проценты по кредиту | C28: ₽ | D28: =SUMIF($H$8:$S$8,"Разработка",$H$28:$S$28) -> 0 | E28: =SUMIF($H$8:$S$8,"Операционка",$H$28:$S$28) -> 0 | F28: =SUM($H$28:$S$28) -> 0 | H28: =0 -> 0 | I28: =0 -> 0 | J28: =0 -> 0 | K28: =0 -> 0 | L28: =0 -> 0 | M28: =0 -> 0 | N28: =0 -> 0 | O28: =0 -> 0 | ... S28: =0 -> 0
B29: 5. Прибыль до налогообложения | C29: ₽ | D29: =SUMIF($H$8:$S$8,"Разработка",$H$29:$S$29) -> -52000 | E29: =SUMIF($H$8:$S$8,"Операционка",$H$29:$S$29) -> 162635.14 | F29: =SUM($H$29:$S$29) -> 110635.14 | H29: =H26+H28 -> -4000 | I29: =I26+I28 -> -6000 | J29: =J26+J28 -> -16000 | K29: =K26+K28 -> -26000 | L29: =L26+L28 -> -37093.64 | M29: =M26+M28 -> -27518.28 | N29: =N26+N28 -> -14145.12 | O29: =O26+O28 -> 375.56 | ... S29: =S26+S28 -> 110352
B30: 6. Налог (УСН) | C30: ₽ | D30: =SUMIF($H$8:$S$8,"Разработка",$H$30:$S$30) -> 0 | E30: =SUMIF($H$8:$S$8,"Операционка",$H$30:$S$30) -> 0 | F30: =SUM($H$30:$S$30) -> 0 | H30: =-H41 -> 0 | I30: =-I41 -> 0 | J30: =-J41 -> 0 | K30: =-K41 -> 0 | L30: =-L41 -> 0 | M30: =-M41 -> 0 | N30: =-N41 -> 0 | O30: =-O41 -> 0 | ... S30: =-S41 -> 0
B31: 7. ЧИСТАЯ ПРИБЫЛЬ | C31: ₽ | D31: =SUMIF($H$8:$S$8,"Разработка",$H$31:$S$31) -> -52000 | E31: =SUMIF($H$8:$S$8,"Операционка",$H$31:$S$31) -> 162635.14 | F31: =SUM($H$31:$S$31) -> 110635.14 | H31: =H29+H30 -> -4000 | I31: =I29+I30 -> -6000 | J31: =J29+J30 -> -16000 | K31: =K29+K30 -> -26000 | L31: =L29+L30 -> -37093.64 | M31: =M29+M30 -> -27518.28 | N31: =N29+N30 -> -14145.12 | O31: =O29+O30 -> 375.56 | ... S31: =S29+S30 -> 110352
B32: Рентабельность по чистой прибыли | C32: % | D32: =IF(D15<>0,D31/D15,0) -> 0 | E32: =IF(E15<>0,E31/E15,0) -> 0.26551976 | F32: =IF(F15<>0,F31/F15,0) -> 0.18062404 | H32: =IF(H15>0,H31/H15,0) -> 0 | I32: =IF(I15>0,I31/I15,0) -> 0 | J32: =IF(J15>0,J31/J15,0) -> 0 | K32: =IF(K15>0,K31/K15,0) -> 0 | L32: =IF(L15>0,L31/L15,0) -> -3.5994547 | M32: =IF(M15>0,M31/M15,0) -> -1.2871821 | N32: =IF(N15>0,N31/N15,0) -> -0.38432291 | O32: =IF(O15>0,O31/O15,0) -> 0.0070157348 | ... S32: =IF(S15>0,S31/S15,0) -> 0.61180906
B33: Накопленная чистая прибыль | C33: ₽ | D33: =INDEX($H$33:$S$33,1,Дев_мес) -> -52000 | E33: =IF(Опер_мес>0,S33,"") -> 110635.14 | F33: =S33 -> 110635.14 | H33: =H31 -> -4000 | I33: =H33+I31 -> -10000 | J33: =I33+J31 -> -26000 | K33: =J33+K31 -> -52000 | L33: =K33+L31 -> -89093.64 | M33: =L33+M31 -> -116611.92 | N33: =M33+N31 -> -130757.04 | O33: =N33+O31 -> -130381.48 | P33: =O33+P31 -> -114308.46 | ... S33: =R33+S31 -> 110635.14
B35: Расчёт налога УСН «Доходы» (нарастающим итогом за календарный год)
B36: Налоговый год | H36: =YEAR(H$7) -> 2026 | I36: =YEAR(I$7) -> 2026 | J36: =YEAR(J$7) -> 2026 | K36: =YEAR(K$7) -> 2026 | L36: =YEAR(L$7) -> 2027 | M36: =YEAR(M$7) -> 2027 | N36: =YEAR(N$7) -> 2027 | O36: =YEAR(O$7) -> 2027 | ... S36: =YEAR(S$7) -> 2027
B37: Поступления выручки с начала года (база УСН, кассовый метод) | C37: ₽ | D37: =INDEX($H$37:$S$37,1,Дев_мес) -> 0 | E37: =IF(Опер_мес>0,S37,"") -> 612516.15 | F37: =S37 -> 612516.15 | H37: =ДДС!H12 -> 0 | I37: =IF(I36=H36,H37,0)+ДДС!I12 -> 0 | J37: =IF(J36=I36,I37,0)+ДДС!J12 -> 0 | K37: =IF(K36=J36,J37,0)+ДДС!K12 -> 0 | L37: =IF(L36=K36,K37,0)+ДДС!L12 -> 10305.35 | M37: =IF(M36=L36,L37,0)+ДДС!M12 -> 31684.05 | N37: =IF(N36=M36,M37,0)+ДДС!N12 -> 68489.35 | O37: =IF(O36=N36,N37,0)+ДДС!O12 -> 122020.45 | P37: =IF(P36=O36,O37,0)+ДДС!P12 -> 193668.15 | ... S37: =IF(S36=R36,R37,0)+ДДС!S12 -> 612516.15
B38: Налог по ставке с начала года | C38: ₽ | D38: =INDEX($H$38:$S$38,1,Дев_мес) -> 0 | E38: =IF(Опер_мес>0,S38,"") -> 36750.969 | F38: =S38 -> 36750.969 | H38: =Ставка_УСН*H37 -> 0 | I38: =Ставка_УСН*I37 -> 0 | J38: =Ставка_УСН*J37 -> 0 | K38: =Ставка_УСН*K37 -> 0 | L38: =Ставка_УСН*L37 -> 618.321 | M38: =Ставка_УСН*M37 -> 1901.043 | N38: =Ставка_УСН*N37 -> 4109.361 | O38: =Ставка_УСН*O37 -> 7321.227 | ... S38: =Ставка_УСН*S37 -> 36750.969
B39: Уменьшение на страховые взносы с начала года | C39: ₽ | D39: =INDEX($H$39:$S$39,1,Дев_мес) -> 0 | E39: =IF(Опер_мес>0,S39,"") -> 36750.969 | F39: =S39 -> 36750.969 | H39: =MIN(Взносы_вычет,Лимит_вычета*H38) -> 0 | I39: =MIN(Взносы_вычет,Лимит_вычета*I38) -> 0 | J39: =MIN(Взносы_вычет,Лимит_вычета*J38) -> 0 | K39: =MIN(Взносы_вычет,Лимит_вычета*K38) -> 0 | L39: =MIN(Взносы_вычет,Лимит_вычета*L38) -> 618.321 | M39: =MIN(Взносы_вычет,Лимит_вычета*M38) -> 1901.043 | N39: =MIN(Взносы_вычет,Лимит_вычета*N38) -> 4109.361 | O39: =MIN(Взносы_вычет,Лимит_вычета*O38) -> 7321.227 | ... S39: =MIN(Взносы_вычет,Лимит_вычета*S38) -> 36750.969
B40: Налог к уплате с начала года | C40: ₽ | D40: =INDEX($H$40:$S$40,1,Дев_мес) -> 0 | E40: =IF(Опер_мес>0,S40,"") -> 0 | F40: =S40 -> 0 | H40: =MAX(0,H38-H39) -> 0 | I40: =MAX(0,I38-I39) -> 0 | J40: =MAX(0,J38-J39) -> 0 | K40: =MAX(0,K38-K39) -> 0 | L40: =MAX(0,L38-L39) -> 0 | M40: =MAX(0,M38-M39) -> 0 | N40: =MAX(0,N38-N39) -> 0 | O40: =MAX(0,O38-O39) -> 0 | ... S40: =MAX(0,S38-S39) -> 0
B41: Налог за месяц | C41: ₽ | D41: =SUMIF($H$8:$S$8,"Разработка",$H$41:$S$41) -> 0 | E41: =SUMIF($H$8:$S$8,"Операционка",$H$41:$S$41) -> 0 | F41: =SUM($H$41:$S$41) -> 0 | H41: =H40 -> 0 | I41: =I40-IF(I36=H36,H40,0) -> 0 | J41: =J40-IF(J36=I36,I40,0) -> 0 | K41: =K40-IF(K36=J36,J40,0) -> 0 | L41: =L40-IF(L36=K36,K40,0) -> 0 | M41: =M40-IF(M36=L36,L40,0) -> 0 | N41: =N40-IF(N36=M36,M40,0) -> 0 | O41: =O40-IF(O36=N36,N40,0) -> 0 | P41: =P40-IF(P36=O36,O40,0) -> 0 | ... S41: =S40-IF(S36=R36,R40,0) -> 0
B42: УСН считается по поступлениям денег (кассовый метод). Упрощения: весь годовой вычет взносов доступен с начала года; налог платится в месяце начисления (в реальности авансы поквартально). Проценты по кредиту на УСН «Доходы» налог не уменьшают.

Sheet ДДС
B2: Отчёт о движении денежных средств (ДДС / Cash Flow)
B3: ₽. docx, раздел 7. Поступления со знаком плюс, платежи со знаком минус.
B5: Показатель | C5: Ед. | D5: ="Разработка"&CHAR(10)&"("&Дев_мес&" мес.)" -> Разработка (4 мес.) | E5: ="Операционка"&CHAR(10)&"("&Опер_мес&" мес.)" -> Операционка (8 мес.) | F5: ="Итого"&CHAR(10)&"12 мес." -> Итого 12 мес. | H5: =Выручка!H$5 -> Сен 2026 | I5: =Выручка!I$5 -> Окт 2026 | J5: =Выручка!J$5 -> Ноя 2026 | K5: =Выручка!K$5 -> Дек 2026 | L5: =Выручка!L$5 -> Янв 2027 | M5: =Выручка!M$5 -> Фев 2027 | N5: =Выручка!N$5 -> Мар 2027 | O5: =Выручка!O$5 -> Апр 2027 | ... S5: =Выручка!S$5 -> Авг 2027
B6: № месяца проекта | H6: =Выручка!H$6 -> 1 | I6: =Выручка!I$6 -> 2 | J6: =Выручка!J$6 -> 3 | K6: =Выручка!K$6 -> 4 | L6: =Выручка!L$6 -> 5 | M6: =Выручка!M$6 -> 6 | N6: =Выручка!N$6 -> 7 | O6: =Выручка!O$6 -> 8 | ... S6: =Выручка!S$6 -> 12
B7: Дата (начало месяца) | H7: =Выручка!H$7 -> 46266 | I7: =Выручка!I$7 -> 46296 | J7: =Выручка!J$7 -> 46327 | K7: =Выручка!K$7 -> 46357 | L7: =Выручка!L$7 -> 46388 | M7: =Выручка!M$7 -> 46419 | N7: =Выручка!N$7 -> 46447 | O7: =Выручка!O$7 -> 46478 | ... S7: =Выручка!S$7 -> 46600
B8: Фаза | H8: =Выручка!H$8 -> Разработка | I8: =Выручка!I$8 -> Разработка | J8: =Выручка!J$8 -> Разработка | K8: =Выручка!K$8 -> Разработка | L8: =Выручка!L$8 -> Операционка | M8: =Выручка!M$8 -> Операционка | N8: =Выручка!N$8 -> Операционка | O8: =Выручка!O$8 -> Операционка | ... S8: =Выручка!S$8 -> Операционка
B9: Месяцев после релиза | H9: =Выручка!H$9 -> 0 | I9: =Выручка!I$9 -> 0 | J9: =Выручка!J$9 -> 0 | K9: =Выручка!K$9 -> 0 | L9: =Выручка!L$9 -> 1 | M9: =Выручка!M$9 -> 2 | N9: =Выручка!N$9 -> 3 | O9: =Выручка!O$9 -> 4 | ... S9: =Выручка!S$9 -> 8
B11: Поступления
B12: Выручка от продаж и рекламы (поступление на счёт) | C12: ₽ | D12: =SUMIF($H$8:$S$8,"Разработка",$H$12:$S$12) -> 0 | E12: =SUMIF($H$8:$S$8,"Операционка",$H$12:$S$12) -> 612516.15 | F12: =SUM($H$12:$S$12) -> 612516.15 | H12: =IF(H$6-Лаг_выручки>=1,INDEX(Выручка!$H$36:$S$36,1,H$6-Лаг_выручки),0) -> 0 | I12: =IF(I$6-Лаг_выручки>=1,INDEX(Выручка!$H$36:$S$36,1,I$6-Лаг_выручки),0) -> 0 | J12: =IF(J$6-Лаг_выручки>=1,INDEX(Выручка!$H$36:$S$36,1,J$6-Лаг_выручки),0) -> 0 | K12: =IF(K$6-Лаг_выручки>=1,INDEX(Выручка!$H$36:$S$36,1,K$6-Лаг_выручки),0) -> 0 | L12: =IF(L$6-Лаг_выручки>=1,INDEX(Выручка!$H$36:$S$36,1,L$6-Лаг_выручки),0) -> 10305.35 | M12: =IF(M$6-Лаг_выручки>=1,INDEX(Выручка!$H$36:$S$36,1,M$6-Лаг_выручки),0) -> 21378.7 | N12: =IF(N$6-Лаг_выручки>=1,INDEX(Выручка!$H$36:$S$36,1,N$6-Лаг_выручки),0) -> 36805.3 | O12: =IF(O$6-Лаг_выручки>=1,INDEX(Выручка!$H$36:$S$36,1,O$6-Лаг_выручки),0) -> 53531.1 | ... S12: =IF(S$6-Лаг_выручки>=1,INDEX(Выручка!$H$36:$S$36,1,S$6-Лаг_выручки),0) -> 180370
B13: Собственный капитал команды | C13: ₽ | D13: =SUMIF($H$8:$S$8,"Разработка",$H$13:$S$13) -> 200000 | E13: =SUMIF($H$8:$S$8,"Операционка",$H$13:$S$13) -> 0 | F13: =SUM($H$13:$S$13) -> 200000 | H13: =IF(H$6=Мес_взноса,Собств_капитал,0) -> 200000 | I13: =IF(I$6=Мес_взноса,Собств_капитал,0) -> 0 | J13: =IF(J$6=Мес_взноса,Собств_капитал,0) -> 0 | K13: =IF(K$6=Мес_взноса,Собств_капитал,0) -> 0 | L13: =IF(L$6=Мес_взноса,Собств_капитал,0) -> 0 | M13: =IF(M$6=Мес_взноса,Собств_капитал,0) -> 0 | N13: =IF(N$6=Мес_взноса,Собств_капитал,0) -> 0 | O13: =IF(O$6=Мес_взноса,Собств_капитал,0) -> 0 | ... S13: =IF(S$6=Мес_взноса,Собств_капитал,0) -> 0
B14: Полученный кредит | C14: ₽ | D14: =SUMIF($H$8:$S$8,"Разработка",$H$14:$S$14) -> 0 | E14: =SUMIF($H$8:$S$8,"Операционка",$H$14:$S$14) -> 0 | F14: =SUM($H$14:$S$14) -> 0 | H14: =0 -> 0 | I14: =0 -> 0 | J14: =0 -> 0 | K14: =0 -> 0 | L14: =0 -> 0 | M14: =0 -> 0 | N14: =0 -> 0 | O14: =0 -> 0 | ... S14: =0 -> 0
B15: Итого поступлений | C15: ₽ | D15: =SUMIF($H$8:$S$8,"Разработка",$H$15:$S$15) -> 200000 | E15: =SUMIF($H$8:$S$8,"Операционка",$H$15:$S$15) -> 612516.15 | F15: =SUM($H$15:$S$15) -> 812516.15 | H15: =SUM(H12:H14) -> 200000 | I15: =SUM(I12:I14) -> 0 | J15: =SUM(J12:J14) -> 0 | K15: =SUM(K12:K14) -> 0 | L15: =SUM(L12:L14) -> 10305.35 | M15: =SUM(M12:M14) -> 21378.7 | N15: =SUM(N12:N14) -> 36805.3 | O15: =SUM(O12:O14) -> 53531.1 | ... S15: =SUM(S12:S14) -> 180370
B17: Платежи
B18: Оплата операционных расходов (OpEx) | C18: ₽ | D18: =SUMIF($H$8:$S$8,"Разработка",$H$18:$S$18) -> -52000 | E18: =SUMIF($H$8:$S$8,"Операционка",$H$18:$S$18) -> -412651.25 | F18: =SUM($H$18:$S$18) -> -464651.25 | H18: =-Расходы!H16 -> -4000 | I18: =-Расходы!I16 -> -6000 | J18: =-Расходы!J16 -> -16000 | K18: =-Расходы!K16 -> -26000 | L18: =-Расходы!L16 -> -46911.25 | M18: =-Расходы!M16 -> -47822.5 | N18: =-Расходы!N16 -> -49037.5 | O18: =-Расходы!O16 -> -50252.5 | ... S18: =-Расходы!S16 -> -58150
B19: Комиссия магазина приложений | C19: ₽ | D19: =SUMIF($H$8:$S$8,"Разработка",$H$19:$S$19) -> 0 | E19: =SUMIF($H$8:$S$8,"Операционка",$H$19:$S$19) -> -37229.76 | F19: =SUM($H$19:$S$19) -> -37229.76 | H19: =-IF(H$6-Лаг_выручки>=1,INDEX(Расходы!$H$19:$S$19,1,H$6-Лаг_выручки),0) -> 0 | I19: =-IF(I$6-Лаг_выручки>=1,INDEX(Расходы!$H$19:$S$19,1,I$6-Лаг_выручки),0) -> 0 | J19: =-IF(J$6-Лаг_выручки>=1,INDEX(Расходы!$H$19:$S$19,1,J$6-Лаг_выручки),0) -> 0 | K19: =-IF(K$6-Лаг_выручки>=1,INDEX(Расходы!$H$19:$S$19,1,K$6-Лаг_выручки),0) -> 0 | L19: =-IF(L$6-Лаг_выручки>=1,INDEX(Расходы!$H$19:$S$19,1,L$6-Лаг_выручки),0) -> -487.74 | M19: =-IF(M$6-Лаг_выручки>=1,INDEX(Расходы!$H$19:$S$19,1,M$6-Лаг_выручки),0) -> -1074.48 | N19: =-IF(N$6-Лаг_выручки>=1,INDEX(Расходы!$H$19:$S$19,1,N$6-Лаг_выручки),0) -> -1912.92 | O19: =-IF(O$6-Лаг_выручки>=1,INDEX(Расходы!$H$19:$S$19,1,O$6-Лаг_выручки),0) -> -2903.04 | ... S19: =-IF(S$6-Лаг_выручки>=1,INDEX(Расходы!$H$19:$S$19,1,S$6-Лаг_выручки),0) -> -11868
B20: Оплата налогов | C20: ₽ | D20: =SUMIF($H$8:$S$8,"Разработка",$H$20:$S$20) -> 0 | E20: =SUMIF($H$8:$S$8,"Операционка",$H$20:$S$20) -> 0 | F20: =SUM($H$20:$S$20) -> 0 | H20: =ОПиУ!H30 -> 0 | I20: =ОПиУ!I30 -> 0 | J20: =ОПиУ!J30 -> 0 | K20: =ОПиУ!K30 -> 0 | L20: =ОПиУ!L30 -> 0 | M20: =ОПиУ!M30 -> 0 | N20: =ОПиУ!N30 -> 0 | O20: =ОПиУ!O30 -> 0 | ... S20: =ОПиУ!S30 -> 0
B21: Оплата процентов по кредиту | C21: ₽ | D21: =SUMIF($H$8:$S$8,"Разработка",$H$21:$S$21) -> 0 | E21: =SUMIF($H$8:$S$8,"Операционка",$H$21:$S$21) -> 0 | F21: =SUM($H$21:$S$21) -> 0 | H21: =0 -> 0 | I21: =0 -> 0 | J21: =0 -> 0 | K21: =0 -> 0 | L21: =0 -> 0 | M21: =0 -> 0 | N21: =0 -> 0 | O21: =0 -> 0 | ... S21: =0 -> 0
B22: Погашение тела кредита | C22: ₽ | D22: =SUMIF($H$8:$S$8,"Разработка",$H$22:$S$22) -> 0 | E22: =SUMIF($H$8:$S$8,"Операционка",$H$22:$S$22) -> 0 | F22: =SUM($H$22:$S$22) -> 0 | H22: =0 -> 0 | I22: =0 -> 0 | J22: =0 -> 0 | K22: =0 -> 0 | L22: =0 -> 0 | M22: =0 -> 0 | N22: =0 -> 0 | O22: =0 -> 0 | ... S22: =0 -> 0
B23: Итого платежей | C23: ₽ | D23: =SUMIF($H$8:$S$8,"Разработка",$H$23:$S$23) -> -52000 | E23: =SUMIF($H$8:$S$8,"Операционка",$H$23:$S$23) -> -449881.01 | F23: =SUM($H$23:$S$23) -> -501881.01 | H23: =SUM(H18:H22) -> -4000 | I23: =SUM(I18:I22) -> -6000 | J23: =SUM(J18:J22) -> -16000 | K23: =SUM(K18:K22) -> -26000 | L23: =SUM(L18:L22) -> -47398.99 | M23: =SUM(M18:M22) -> -48896.98 | N23: =SUM(N18:N22) -> -50950.42 | O23: =SUM(O18:O22) -> -53155.54 | ... S23: =SUM(S18:S22) -> -70018
B25: ЧИСТЫЙ ДЕНЕЖНЫЙ ПОТОК (NCF) | C25: ₽ | D25: =SUMIF($H$8:$S$8,"Разработка",$H$25:$S$25) -> 148000 | E25: =SUMIF($H$8:$S$8,"Операционка",$H$25:$S$25) -> 162635.14 | F25: =SUM($H$25:$S$25) -> 310635.14 | H25: =H15+H23 -> 196000 | I25: =I15+I23 -> -6000 | J25: =J15+J23 -> -16000 | K25: =K15+K23 -> -26000 | L25: =L15+L23 -> -37093.64 | M25: =M15+M23 -> -27518.28 | N25: =N15+N23 -> -14145.12 | O25: =O15+O23 -> 375.56 | ... S25: =S15+S23 -> 110352
B26: Остаток денег на начало месяца | C26: ₽ | D26: =H26 -> 0 | E26: =IF(Опер_мес>0,INDEX($H$26:$S$26,1,Дев_мес+1),"") -> 148000 | F26: =H26 -> 0 | H26: =0 -> 0 | I26: =H27 -> 196000 | J26: =I27 -> 190000 | K26: =J27 -> 174000 | L26: =K27 -> 148000 | M26: =L27 -> 110906.36 | N26: =M27 -> 83388.08 | O26: =N27 -> 69242.96 | P26: =O27 -> 69618.52 | ... S26: =R27 -> 200283.14
B27: Остаток денег на конец месяца | C27: ₽ | D27: =INDEX($H$27:$S$27,1,Дев_мес) -> 148000 | E27: =IF(Опер_мес>0,S27,"") -> 310635.14 | F27: =S27 -> 310635.14 | H27: =H26+H25 -> 196000 | I27: =I26+I25 -> 190000 | J27: =J26+J25 -> 174000 | K27: =K26+K25 -> 148000 | L27: =L26+L25 -> 110906.36 | M27: =M26+M25 -> 83388.08 | N27: =N26+N25 -> 69242.96 | O27: =O26+O25 -> 69618.52 | ... S27: =S26+S25 -> 310635.14
B29: Справочно: структура денежного потока
B30: Операционный поток (CFO) | C30: ₽ | D30: =SUMIF($H$8:$S$8,"Разработка",$H$30:$S$30) -> -52000 | E30: =SUMIF($H$8:$S$8,"Операционка",$H$30:$S$30) -> 162635.14 | F30: =SUM($H$30:$S$30) -> 110635.14 | H30: =H12+H18+H19+H20 -> -4000 | I30: =I12+I18+I19+I20 -> -6000 | J30: =J12+J18+J19+J20 -> -16000 | K30: =K12+K18+K19+K20 -> -26000 | L30: =L12+L18+L19+L20 -> -37093.64 | M30: =M12+M18+M19+M20 -> -27518.28 | N30: =N12+N18+N19+N20 -> -14145.12 | O30: =O12+O18+O19+O20 -> 375.56 | ... S30: =S12+S18+S19+S20 -> 110352
B31: Финансовый поток (CFF) | C31: ₽ | D31: =SUMIF($H$8:$S$8,"Разработка",$H$31:$S$31) -> 200000 | E31: =SUMIF($H$8:$S$8,"Операционка",$H$31:$S$31) -> 0 | F31: =SUM($H$31:$S$31) -> 200000 | H31: =H13+H14+H21+H22 -> 200000 | I31: =I13+I14+I21+I22 -> 0 | J31: =J13+J14+J21+J22 -> 0 | K31: =K13+K14+K21+K22 -> 0 | L31: =L13+L14+L21+L22 -> 0 | M31: =M13+M14+M21+M22 -> 0 | N31: =N13+N14+N21+N22 -> 0 | O31: =O13+O14+O21+O22 -> 0 | ... S31: =S13+S14+S21+S22 -> 0
B32: Проверка: CFO + CFF - NCF (должно быть 0) | C32: ₽ | D32: =SUMIF($H$8:$S$8,"Разработка",$H$32:$S$32) -> 0 | E32: =SUMIF($H$8:$S$8,"Операционка",$H$32:$S$32) -> 0 | F32: =SUM($H$32:$S$32) -> 0 | H32: =ROUND(H30+H31-H25,2) -> 0 | I32: =ROUND(I30+I31-I25,2) -> 0 | J32: =ROUND(J30+J31-J25,2) -> 0 | K32: =ROUND(K30+K31-K25,2) -> 0 | L32: =ROUND(L30+L31-L25,2) -> 0 | M32: =ROUND(M30+M31-M25,2) -> 0 | N32: =ROUND(N30+N31-N25,2) -> 0 | O32: =ROUND(O30+O31-O25,2) -> 0 | ... S32: =ROUND(S30+S31-S25,2) -> 0
B33: Поток без привлечённого финансирования (метод docx для окупаемости) | C33: ₽ | D33: =SUMIF($H$8:$S$8,"Разработка",$H$33:$S$33) -> -52000 | E33: =SUMIF($H$8:$S$8,"Операционка",$H$33:$S$33) -> 162635.14 | F33: =SUM($H$33:$S$33) -> 110635.14 | H33: =H25-H13-H14 -> -4000 | I33: =I25-I13-I14 -> -6000 | J33: =J25-J13-J14 -> -16000 | K33: =K25-K13-K14 -> -26000 | L33: =L25-L13-L14 -> -37093.64 | M33: =M25-M13-M14 -> -27518.28 | N33: =N25-N13-N14 -> -14145.12 | O33: =O25-O13-O14 -> 375.56 | ... S33: =S25-S13-S14 -> 110352
B34: Накопленный поток без привлечённого финансирования | C34: ₽ | D34: =INDEX($H$34:$S$34,1,Дев_мес) -> -52000 | E34: =IF(Опер_мес>0,S34,"") -> 110635.14 | F34: =S34 -> 110635.14 | H34: =H33 -> -4000 | I34: =H34+I33 -> -10000 | J34: =I34+J33 -> -26000 | K34: =J34+K33 -> -52000 | L34: =K34+L33 -> -89093.64 | M34: =L34+M33 -> -116611.92 | N34: =M34+N33 -> -130757.04 | O34: =N34+O33 -> -130381.48 | P34: =O34+P33 -> -114308.46 | ... S34: =R34+S33 -> 110635.14
B36: Справочно: что будет с деньгами, если выручка придёт на 1 месяц позже
B37: Остаток денег на конец месяца при лаге выплат +1 мес. | C37: ₽ | F37: =MIN($H$37:$S$37) -> 18151.02 | H37: =H27-IF(H$6-Лаг_выручки>=1,INDEX(Выручка!$H$36:$S$36,1,H$6-Лаг_выручки)-INDEX(Расходы!$H$19:$S$19,1,H$6-Лаг_выручки),0) -> 196000 | I37: =I27-IF(I$6-Лаг_выручки>=1,INDEX(Выручка!$H$36:$S$36,1,I$6-Лаг_выручки)-INDEX(Расходы!$H$19:$S$19,1,I$6-Лаг_выручки),0) -> 190000 | J37: =J27-IF(J$6-Лаг_выручки>=1,INDEX(Выручка!$H$36:$S$36,1,J$6-Лаг_выручки)-INDEX(Расходы!$H$19:$S$19,1,J$6-Лаг_выручки),0) -> 174000 | K37: =K27-IF(K$6-Лаг_выручки>=1,INDEX(Выручка!$H$36:$S$36,1,K$6-Лаг_выручки)-INDEX(Расходы!$H$19:$S$19,1,K$6-Лаг_выручки),0) -> 148000 | L37: =L27-IF(L$6-Лаг_выручки>=1,INDEX(Выручка!$H$36:$S$36,1,L$6-Лаг_выручки)-INDEX(Расходы!$H$19:$S$19,1,L$6-Лаг_выручки),0) -> 101088.75 | M37: =M27-IF(M$6-Лаг_выручки>=1,INDEX(Выручка!$H$36:$S$36,1,M$6-Лаг_выручки)-INDEX(Расходы!$H$19:$S$19,1,M$6-Лаг_выручки),0) -> 63083.86 | N37: =N27-IF(N$6-Лаг_выручки>=1,INDEX(Выручка!$H$36:$S$36,1,N$6-Лаг_выручки)-INDEX(Расходы!$H$19:$S$19,1,N$6-Лаг_выручки),0) -> 34350.58 | O37: =O27-IF(O$6-Лаг_выручки>=1,INDEX(Выручка!$H$36:$S$36,1,O$6-Лаг_выручки)-INDEX(Расходы!$H$19:$S$19,1,O$6-Лаг_выручки),0) -> 18990.46 | ... S37: =S27-IF(S$6-Лаг_выручки>=1,INDEX(Выручка!$H$36:$S$36,1,S$6-Лаг_выручки)-INDEX(Расходы!$H$19:$S$19,1,S$6-Лаг_выручки),0) -> 142133.14
B38: Рекламные сети и магазины приложений выплачивают доход по итогам месяца. Итого: минимальный остаток.
B39: Остаток денег на конец месяца, если бы кредита не было | C39: ₽ | F39: =MIN($H$39:$S$39) -> 69242.96 | H39: =H27 -> 196000 | I39: =I27 -> 190000 | J39: =J27 -> 174000 | K39: =K27 -> 148000 | L39: =L27 -> 110906.36 | M39: =M27 -> 83388.08 | N39: =N27 -> 69242.96 | O39: =O27 -> 69618.52 | ... S39: =S27 -> 310635.14
B40: Показывает, зачем нужен кредит: без него минимальный остаток денег (Итого) был бы таким.

Sheet Баланс
B2: Упрощённый баланс
B3: ₽, на конец месяца. Связывает ОПиУ и ДДС: если модель собрана верно, активы равны пассивам в каждом месяце.
B5: Показатель | C5: Ед. | D5: ="Разработка"&CHAR(10)&"("&Дев_мес&" мес.)" -> Разработка (4 мес.) | E5: ="Операционка"&CHAR(10)&"("&Опер_мес&" мес.)" -> Операционка (8 мес.) | F5: ="Итого"&CHAR(10)&"12 мес." -> Итого 12 мес. | H5: =Выручка!H$5 -> Сен 2026 | I5: =Выручка!I$5 -> Окт 2026 | J5: =Выручка!J$5 -> Ноя 2026 | K5: =Выручка!K$5 -> Дек 2026 | L5: =Выручка!L$5 -> Янв 2027 | M5: =Выручка!M$5 -> Фев 2027 | N5: =Выручка!N$5 -> Мар 2027 | O5: =Выручка!O$5 -> Апр 2027 | ... S5: =Выручка!S$5 -> Авг 2027
B6: № месяца проекта | H6: =Выручка!H$6 -> 1 | I6: =Выручка!I$6 -> 2 | J6: =Выручка!J$6 -> 3 | K6: =Выручка!K$6 -> 4 | L6: =Выручка!L$6 -> 5 | M6: =Выручка!M$6 -> 6 | N6: =Выручка!N$6 -> 7 | O6: =Выручка!O$6 -> 8 | ... S6: =Выручка!S$6 -> 12
B7: Дата (начало месяца) | H7: =Выручка!H$7 -> 46266 | I7: =Выручка!I$7 -> 46296 | J7: =Выручка!J$7 -> 46327 | K7: =Выручка!K$7 -> 46357 | L7: =Выручка!L$7 -> 46388 | M7: =Выручка!M$7 -> 46419 | N7: =Выручка!N$7 -> 46447 | O7: =Выручка!O$7 -> 46478 | ... S7: =Выручка!S$7 -> 46600
B8: Фаза | H8: =Выручка!H$8 -> Разработка | I8: =Выручка!I$8 -> Разработка | J8: =Выручка!J$8 -> Разработка | K8: =Выручка!K$8 -> Разработка | L8: =Выручка!L$8 -> Операционка | M8: =Выручка!M$8 -> Операционка | N8: =Выручка!N$8 -> Операционка | O8: =Выручка!O$8 -> Операционка | ... S8: =Выручка!S$8 -> Операционка
B9: Месяцев после релиза | H9: =Выручка!H$9 -> 0 | I9: =Выручка!I$9 -> 0 | J9: =Выручка!J$9 -> 0 | K9: =Выручка!K$9 -> 0 | L9: =Выручка!L$9 -> 1 | M9: =Выручка!M$9 -> 2 | N9: =Выручка!N$9 -> 3 | O9: =Выручка!O$9 -> 4 | ... S9: =Выручка!S$9 -> 8
B11: Активы
B12: Денежные средства | C12: ₽ | D12: =INDEX($H$12:$S$12,1,Дев_мес) -> 148000 | E12: =IF(Опер_мес>0,S12,"") -> 310635.14 | F12: =S12 -> 310635.14 | H12: =ДДС!H27 -> 196000 | I12: =ДДС!I27 -> 190000 | J12: =ДДС!J27 -> 174000 | K12: =ДДС!K27 -> 148000 | L12: =ДДС!L27 -> 110906.36 | M12: =ДДС!M27 -> 83388.08 | N12: =ДДС!N27 -> 69242.96 | O12: =ДДС!O27 -> 69618.52 | ... S12: =ДДС!S27 -> 310635.14
B13: Дебиторская задолженность (выручка к получению) | C13: ₽ | D13: =INDEX($H$13:$S$13,1,Дев_мес) -> 0 | E13: =IF(Опер_мес>0,S13,"") -> 0 | F13: =S13 -> 0 | H13: =(Выручка!H36-Расходы!H19)-(ДДС!H12+ДДС!H19) -> 0 | I13: =H13+(Выручка!I36-Расходы!I19)-(ДДС!I12+ДДС!I19) -> 0 | J13: =I13+(Выручка!J36-Расходы!J19)-(ДДС!J12+ДДС!J19) -> 0 | K13: =J13+(Выручка!K36-Расходы!K19)-(ДДС!K12+ДДС!K19) -> 0 | L13: =K13+(Выручка!L36-Расходы!L19)-(ДДС!L12+ДДС!L19) -> 0 | M13: =L13+(Выручка!M36-Расходы!M19)-(ДДС!M12+ДДС!M19) -> 0 | N13: =M13+(Выручка!N36-Расходы!N19)-(ДДС!N12+ДДС!N19) -> 0 | O13: =N13+(Выручка!O36-Расходы!O19)-(ДДС!O12+ДДС!O19) -> 0 | P13: =O13+(Выручка!P36-Расходы!P19)-(ДДС!P12+ДДС!P19) -> 0 | ... S13: =R13+(Выручка!S36-Расходы!S19)-(ДДС!S12+ДДС!S19) -> 0
B14: ИТОГО АКТИВЫ | C14: ₽ | D14: =INDEX($H$14:$S$14,1,Дев_мес) -> 148000 | E14: =IF(Опер_мес>0,S14,"") -> 310635.14 | F14: =S14 -> 310635.14 | H14: =H12+H13 -> 196000 | I14: =I12+I13 -> 190000 | J14: =J12+J13 -> 174000 | K14: =K12+K13 -> 148000 | L14: =L12+L13 -> 110906.36 | M14: =M12+M13 -> 83388.08 | N14: =N12+N13 -> 69242.96 | O14: =O12+O13 -> 69618.52 | ... S14: =S12+S13 -> 310635.14
B16: Обязательства
B17: Кредит банка | C17: ₽ | D17: =INDEX($H$17:$S$17,1,Дев_мес) -> 0 | E17: =IF(Опер_мес>0,S17,"") -> 0 | F17: =S17 -> 0 | H17: =0 -> 0 | I17: =0 -> 0 | J17: =0 -> 0 | K17: =0 -> 0 | L17: =0 -> 0 | M17: =0 -> 0 | N17: =0 -> 0 | O17: =0 -> 0 | ... S17: =0 -> 0
B18: Капитал
B19: Вклады участников | C19: ₽ | D19: =INDEX($H$19:$S$19,1,Дев_мес) -> 200000 | E19: =IF(Опер_мес>0,S19,"") -> 200000 | F19: =S19 -> 200000 | H19: =ДДС!H13 -> 200000 | I19: =H19+ДДС!I13 -> 200000 | J19: =I19+ДДС!J13 -> 200000 | K19: =J19+ДДС!K13 -> 200000 | L19: =K19+ДДС!L13 -> 200000 | M19: =L19+ДДС!M13 -> 200000 | N19: =M19+ДДС!N13 -> 200000 | O19: =N19+ДДС!O13 -> 200000 | P19: =O19+ДДС!P13 -> 200000 | ... S19: =R19+ДДС!S13 -> 200000
B20: Нераспределённая прибыль (накопленная чистая прибыль) | C20: ₽ | D20: =INDEX($H$20:$S$20,1,Дев_мес) -> -52000 | E20: =IF(Опер_мес>0,S20,"") -> 110635.14 | F20: =S20 -> 110635.14 | H20: =ОПиУ!H33 -> -4000 | I20: =ОПиУ!I33 -> -10000 | J20: =ОПиУ!J33 -> -26000 | K20: =ОПиУ!K33 -> -52000 | L20: =ОПиУ!L33 -> -89093.64 | M20: =ОПиУ!M33 -> -116611.92 | N20: =ОПиУ!N33 -> -130757.04 | O20: =ОПиУ!O33 -> -130381.48 | ... S20: =ОПиУ!S33 -> 110635.14
B21: Итого капитал | C21: ₽ | D21: =INDEX($H$21:$S$21,1,Дев_мес) -> 148000 | E21: =IF(Опер_мес>0,S21,"") -> 310635.14 | F21: =S21 -> 310635.14 | H21: =H19+H20 -> 196000 | I21: =I19+I20 -> 190000 | J21: =J19+J20 -> 174000 | K21: =K19+K20 -> 148000 | L21: =L19+L20 -> 110906.36 | M21: =M19+M20 -> 83388.08 | N21: =N19+N20 -> 69242.96 | O21: =O19+O20 -> 69618.52 | ... S21: =S19+S20 -> 310635.14
B22: ИТОГО ПАССИВЫ | C22: ₽ | D22: =INDEX($H$22:$S$22,1,Дев_мес) -> 148000 | E22: =IF(Опер_мес>0,S22,"") -> 310635.14 | F22: =S22 -> 310635.14 | H22: =H17+H21 -> 196000 | I22: =I17+I21 -> 190000 | J22: =J17+J21 -> 174000 | K22: =K17+K21 -> 148000 | L22: =L17+L21 -> 110906.36 | M22: =M17+M21 -> 83388.08 | N22: =N17+N21 -> 69242.96 | O22: =O17+O21 -> 69618.52 | ... S22: =S17+S21 -> 310635.14
B24: Проверка: активы - пассивы (должно быть 0) | C24: ₽ | F24: =SUMPRODUCT(ABS($H$24:$S$24)) -> 0 | H24: =ROUND(H14-H22,2) -> 0 | I24: =ROUND(I14-I22,2) -> 0 | J24: =ROUND(J14-J22,2) -> 0 | K24: =ROUND(K14-K22,2) -> 0 | L24: =ROUND(L14-L22,2) -> 0 | M24: =ROUND(M14-M22,2) -> 0 | N24: =ROUND(N14-N22,2) -> 0 | O24: =ROUND(O14-O22,2) -> 0 | ... S24: =ROUND(S14-S22,2) -> 0

Sheet Сценарии
B2: Сценарный анализ (docx, раздел 10.2)
B3: Все четыре сценария считаются параллельно полной логикой модели. Параметры сценариев: «Допущения», п. 9.
B5: Показатель за 12 мес. | C5: Ед. | D5: =Допущения!$E$80 -> Оптимистичный | E5: =Допущения!$F$80 -> Базовый | F5: =Допущения!$G$80 -> Пессимистичный | G5: =Допущения!$H$80 -> Пессимистичный + меры | H5: Ожидаемое (по вероятностям)
B6: Вероятность сценария (docx) | C6: % | D6: =Допущения!$E$81 -> 0.25 | E6: =Допущения!$F$81 -> 0.5 | F6: =Допущения!$G$81 -> 0.25 | G6: =Допущения!$H$81 -> 0 | H6: =SUM(D6:G6) -> 1
B7: MAU в последнем месяце | C7: чел. | D7: =S43 -> 28000 | E7: =S62 -> 20000 | F7: =S81 -> 12000 | G7: =S100 -> 12000 | H7: =SUMPRODUCT(Допущения!$E$81:$H$81,D7:G7) -> 20000
B8: Выручка | C8: ₽ | D8: =F46 -> 856656.05 | E8: =F65 -> 612516.15 | F8: =F84 -> 367399.45 | G8: =F103 -> 367399.45 | H8: =SUMPRODUCT(Допущения!$E$81:$H$81,D8:G8) -> 612271.95
B9: EBITDA | C9: ₽ | D9: =F49 -> 242152.62 | E9: =F68 -> 110635.14 | F9: =F87 -> -61712.62 | G9: =F106 -> -21712.62 | H9: =SUMPRODUCT(Допущения!$E$81:$H$81,D9:G9) -> 100427.57
B10: Чистая прибыль | C10: ₽ | D10: =F54 -> 242152.62 | E10: =F73 -> 110635.14 | F10: =F92 -> -61712.62 | G10: =F111 -> -21712.62 | H10: =SUMPRODUCT(Допущения!$E$81:$H$81,D10:G10) -> 100427.57
B11: Рентабельность по чистой прибыли | C11: % | D11: =IFERROR(F54/F46,0) -> 0.28267193 | E11: =IFERROR(F73/F65,0) -> 0.18062404 | F11: =IFERROR(F92/F84,0) -> -0.16797145 | G11: =IFERROR(F111/F103,0) -> -0.059098129
B12: ROI на собственный капитал | C12: % | D12: =IFERROR(F54/Собств_капитал,0) -> 1.2107631 | E12: =IFERROR(F73/Собств_капитал,0) -> 0.5531757 | F12: =IFERROR(F92/Собств_капитал,0) -> -0.3085631 | G12: =IFERROR(F111/Собств_капитал,0) -> -0.1085631 | H12: =SUMPRODUCT(Допущения!$E$81:$H$81,D12:G12) -> 0.50213785
B13: Деньги на конец горизонта | C13: ₽ | D13: =S57 -> 442152.62 | E13: =S76 -> 310635.14 | F13: =S95 -> 138287.38 | G13: =S114 -> 178287.38 | H13: =SUMPRODUCT(Допущения!$E$81:$H$81,D13:G13) -> 300427.57
B14: Минимальный остаток денег | C14: ₽ | D14: =MIN($H$57:$S$57) -> 62561.18 | E14: =MIN($H$76:$S$76) -> 69242.96 | F14: =MIN($H$95:$S$95) -> 43522.92 | G14: =MIN($H$114:$S$114) -> 67339.56
B15: Окупаемость вложений команды | C15: мес. | D15: =IF(COUNT($H$59:$S$59)=0,"за горизонтом",MIN($H$59:$S$59)) -> 10.292273 | E15: =IF(COUNT($H$78:$S$78)=0,"за горизонтом",MIN($H$78:$S$78)) -> 10.996171 | F15: =IF(COUNT($H$97:$S$97)=0,"за горизонтом",MIN($H$97:$S$97)) -> за горизонтом | G15: =IF(COUNT($H$116:$S$116)=0,"за горизонтом",MIN($H$116:$S$116)) -> за горизонтом
B16: Накопленный поток без финансирования на конец | C16: ₽ | D16: =S58 -> 242152.62 | E16: =S77 -> 110635.14 | F16: =S96 -> -61712.62 | G16: =S115 -> -21712.62
B17: Чистая прибыль на участника (равные доли) | C17: ₽ | D17: =IFERROR(F54/Участников,0) -> 60538.155 | E17: =IFERROR(F73/Участников,0) -> 27658.785 | F17: =IFERROR(F92/Участников,0) -> -15428.155 | G17: =IFERROR(F111/Участников,0) -> -5428.155 | H17: =SUMPRODUCT(Допущения!$E$81:$H$81,D17:G17) -> 25106.893
B19: Для сравнения: цифры docx (раздел 10.2)
B20: docx: выручка за год | C20: ₽ | D20: 1400000 | E20: 984227 | F20: 600000
B21: docx: чистая прибыль | C21: ₽ | D21: 600000 | E21: 383625 | F21: 150000
B22: docx: ROI | C22: % | D22: 3 | E22: 1.92 | F22: 0.75
B23: docx: срок окупаемости | D23: 9 мес. | E23: 12 мес. | F23: 14-15 мес.
B24: ="docx считал сценарии «на глаз». Модель считает их полной логикой: при MAU на "&(FIXED((1-Допущения!$G$82)*100,0))&"% ниже плана и тех же расходах чистая прибыль "&(FIXED(F10,0))&" ₽ (в docx около +150 000 ₽). С маркетингом "&(FIXED(Допущения!$H$85,0))&" ₽/мес: "&(FIXED(G10,0))&" ₽, если MAU при этом удержится (модель не связывает MAU с бюджетом)." -> docx считал сценарии «на глаз». Модель считает их полной логикой: при MAU на 40% ниже плана и тех же расходах чистая прибыль -61,713 ₽ (в docx около +150 000 ₽). С маркетингом 20,000 ₽/мес: -21,713 ₽, если MAU при этом удержится (модель не связывает MAU с бюджетом).
B26: ="Стресс-тест: релиз позже на "&Стресс_задержка&" мес. (сценарий «"&Сценарий&"»)" -> Стресс-тест: релиз позже на 2 мес. (сценарий «Базовый»)
B27: Чистая прибыль за 12 мес. | C27: ₽ | D27: =F128 -> -81664.38
B28: Изменение к активному сценарию | C28: ₽ | D28: =F128-ОПиУ!$F$31 -> -192299.52
B29: Минимальный остаток денег | C29: ₽ | D29: =MIN($H$131:$S$131) -> 61242.96
B34: Помесячный расчёт по сценариям
B36: Показатель | C36: Ед. | D36: ="Разработка"&CHAR(10)&"("&Дев_мес&" мес.)" -> Разработка (4 мес.) | E36: ="Операционка"&CHAR(10)&"("&Опер_мес&" мес.)" -> Операционка (8 мес.) | F36: ="Итого"&CHAR(10)&"12 мес." -> Итого 12 мес. | H36: =Выручка!H$5 -> Сен 2026 | I36: =Выручка!I$5 -> Окт 2026 | J36: =Выручка!J$5 -> Ноя 2026 | K36: =Выручка!K$5 -> Дек 2026 | L36: =Выручка!L$5 -> Янв 2027 | M36: =Выручка!M$5 -> Фев 2027 | N36: =Выручка!N$5 -> Мар 2027 | O36: =Выручка!O$5 -> Апр 2027 | ... S36: =Выручка!S$5 -> Авг 2027
B37: № месяца проекта | H37: =Выручка!H$6 -> 1 | I37: =Выручка!I$6 -> 2 | J37: =Выручка!J$6 -> 3 | K37: =Выручка!K$6 -> 4 | L37: =Выручка!L$6 -> 5 | M37: =Выручка!M$6 -> 6 | N37: =Выручка!N$6 -> 7 | O37: =Выручка!O$6 -> 8 | ... S37: =Выручка!S$6 -> 12
B38: Дата (начало месяца) | H38: =Выручка!H$7 -> 46266 | I38: =Выручка!I$7 -> 46296 | J38: =Выручка!J$7 -> 46327 | K38: =Выручка!K$7 -> 46357 | L38: =Выручка!L$7 -> 46388 | M38: =Выручка!M$7 -> 46419 | N38: =Выручка!N$7 -> 46447 | O38: =Выручка!O$7 -> 46478 | ... S38: =Выручка!S$7 -> 46600
B39: Фаза | H39: =Выручка!H$8 -> Разработка | I39: =Выручка!I$8 -> Разработка | J39: =Выручка!J$8 -> Разработка | K39: =Выручка!K$8 -> Разработка | L39: =Выручка!L$8 -> Операционка | M39: =Выручка!M$8 -> Операционка | N39: =Выручка!N$8 -> Операционка | O39: =Выручка!O$8 -> Операционка | ... S39: =Выручка!S$8 -> Операционка
B40: Месяцев после релиза | H40: =Выручка!H$9 -> 0 | I40: =Выручка!I$9 -> 0 | J40: =Выручка!J$9 -> 0 | K40: =Выручка!K$9 -> 0 | L40: =Выручка!L$9 -> 1 | M40: =Выручка!M$9 -> 2 | N40: =Выручка!N$9 -> 3 | O40: =Выручка!O$9 -> 4 | ... S40: =Выручка!S$9 -> 8
B42: ="Сценарий «"&(Допущения!$E$80)&"»: MAU ×"&(FIXED(Допущения!$E$82,1))&", eCPM ×"&(FIXED(Допущения!$E$83,1))&", конверсия ×"&(FIXED(Допущения!$E$84,1))&", маркетинг "&(FIXED(Допущения!$E$85,0))&" ₽/мес" -> Сценарий «Оптимистичный»: MAU ×1.4, eCPM ×1.0, конверсия ×1.0, маркетинг 40,000 ₽/мес
B43: MAU | C43: чел. | D43: =INDEX($H$43:$S$43,1,Дев_мес) -> 0 | E43: =IF(Опер_мес>0,S43,"") -> 28000 | F43: =S43 -> 28000 | H43: =Выручка!H12*Допущения!$E$82 -> 0 | I43: =Выручка!I12*Допущения!$E$82 -> 0 | J43: =Выручка!J12*Допущения!$E$82 -> 0 | K43: =Выручка!K12*Допущения!$E$82 -> 0 | L43: =Выручка!L12*Допущения!$E$82 -> 2100 | M43: =Выручка!M12*Допущения!$E$82 -> 4200 | N43: =Выручка!N12*Допущения!$E$82 -> 7000 | O43: =Выручка!O12*Допущения!$E$82 -> 9800 | ... S43: =Выручка!S12*Допущения!$E$82 -> 28000
B44: Доход от рекламы | C44: ₽ | D44: =SUMIF($H$39:$S$39,"Разработка",$H$44:$S$44) -> 0 | E44: =SUMIF($H$39:$S$39,"Операционка",$H$44:$S$44) -> 510044.85 | F44: =SUM($H$44:$S$44) -> 510044.85 | H44: =H43*(Выручка!H41+Выручка!H42)*Допущения!$E$83 -> 0 | I44: =I43*(Выручка!I41+Выручка!I42)*Допущения!$E$83 -> 0 | J44: =J43*(Выручка!J41+Выручка!J42)*Допущения!$E$83 -> 0 | K44: =K43*(Выручка!K41+Выручка!K42)*Допущения!$E$83 -> 0 | L44: =L43*(Выручка!L41+Выручка!L42)*Допущения!$E$83 -> 9875.25 | M44: =M43*(Выручка!M41+Выручка!M42)*Допущения!$E$83 -> 19901.7 | N44: =N43*(Выручка!N41+Выручка!N42)*Допущения!$E$83 -> 33673.5 | O44: =O43*(Выручка!O41+Выручка!O42)*Допущения!$E$83 -> 47848.5 | ... S44: =S43*(Выручка!S41+Выручка!S42)*Допущения!$E$83 -> 141750
B45: Доход от IAP | C45: ₽ | D45: =SUMIF($H$39:$S$39,"Разработка",$H$45:$S$45) -> 0 | E45: =SUMIF($H$39:$S$39,"Операционка",$H$45:$S$45) -> 346611.2 | F45: =SUM($H$45:$S$45) -> 346611.2 | H45: =ROUND(H43*(Выручка!H43*Допущения!$E$84),0)*Выручка!H30 -> 0 | I45: =ROUND(I43*(Выручка!I43*Допущения!$E$84),0)*Выручка!I30 -> 0 | J45: =ROUND(J43*(Выручка!J43*Допущения!$E$84),0)*Выручка!J30 -> 0 | K45: =ROUND(K43*(Выручка!K43*Допущения!$E$84),0)*Выручка!K30 -> 0 | L45: =ROUND(L43*(Выручка!L43*Допущения!$E$84),0)*Выручка!L30 -> 4434 | M45: =ROUND(M43*(Выручка!M43*Допущения!$E$84),0)*Выручка!M30 -> 9768 | N45: =ROUND(N43*(Выручка!N43*Допущения!$E$84),0)*Выручка!N30 -> 17786.8 | O45: =ROUND(O43*(Выручка!O43*Допущения!$E$84),0)*Выручка!O30 -> 26956.8 | ... S45: =ROUND(S43*(Выручка!S43*Допущения!$E$84),0)*Выручка!S30 -> 110768
B46: Выручка | C46: ₽ | D46: =SUMIF($H$39:$S$39,"Разработка",$H$46:$S$46) -> 0 | E46: =SUMIF($H$39:$S$39,"Операционка",$H$46:$S$46) -> 856656.05 | F46: =SUM($H$46:$S$46) -> 856656.05 | H46: =H44+H45 -> 0 | I46: =I44+I45 -> 0 | J46: =J44+J45 -> 0 | K46: =K44+K45 -> 0 | L46: =L44+L45 -> 14309.25 | M46: =M44+M45 -> 29669.7 | N46: =N44+N45 -> 51460.3 | O46: =O44+O45 -> 74805.3 | ... S46: =S44+S45 -> 252518
B47: Комиссия магазина | C47: ₽ | D47: =SUMIF($H$39:$S$39,"Разработка",$H$47:$S$47) -> 0 | E47: =SUMIF($H$39:$S$39,"Операционка",$H$47:$S$47) -> 51991.68 | F47: =SUM($H$47:$S$47) -> 51991.68 | H47: =H45*Комиссия_стора -> 0 | I47: =I45*Комиссия_стора -> 0 | J47: =J45*Комиссия_стора -> 0 | K47: =K45*Комиссия_стора -> 0 | L47: =L45*Комиссия_стора -> 665.1 | M47: =M45*Комиссия_стора -> 1465.2 | N47: =N45*Комиссия_стора -> 2668.02 | O47: =O45*Комиссия_стора -> 4043.52 | ... S47: =S45*Комиссия_стора -> 16615.2
B48: Операционные расходы | C48: ₽ | D48: =SUMIF($H$39:$S$39,"Разработка",$H$48:$S$48) -> 52000 | E48: =SUMIF($H$39:$S$39,"Операционка",$H$48:$S$48) -> 510511.75 | F48: =SUM($H$48:$S$48) -> 562511.75 | H48: =(Расходы!H12-Энергия!H39+H43*Энергия!H40)+Расходы!H13+Расходы!H14+IF(H$39="Разработка",Расходы!H15,Допущения!$E$85) -> 4000 | I48: =(Расходы!I12-Энергия!I39+I43*Энергия!I40)+Расходы!I13+Расходы!I14+IF(I$39="Разработка",Расходы!I15,Допущения!$E$85) -> 6000 | J48: =(Расходы!J12-Энергия!J39+J43*Энергия!J40)+Расходы!J13+Расходы!J14+IF(J$39="Разработка",Расходы!J15,Допущения!$E$85) -> 16000 | K48: =(Расходы!K12-Энергия!K39+K43*Энергия!K40)+Расходы!K13+Расходы!K14+IF(K$39="Разработка",Расходы!K15,Допущения!$E$85) -> 26000 | L48: =(Расходы!L12-Энергия!L39+L43*Энергия!L40)+Расходы!L13+Расходы!L14+IF(L$39="Разработка",Расходы!L15,Допущения!$E$85) -> 57275.75 | M48: =(Расходы!M12-Энергия!M39+M43*Энергия!M40)+Расходы!M13+Расходы!M14+IF(M$39="Разработка",Расходы!M15,Допущения!$E$85) -> 58551.5 | N48: =(Расходы!N12-Энергия!N39+N43*Энергия!N40)+Расходы!N13+Расходы!N14+IF(N$39="Разработка",Расходы!N15,Допущения!$E$85) -> 60252.5 | O48: =(Расходы!O12-Энергия!O39+O43*Энергия!O40)+Расходы!O13+Расходы!O14+IF(O$39="Разработка",Расходы!O15,Допущения!$E$85) -> 61953.5 | ... S48: =(Расходы!S12-Энергия!S39+S43*Энергия!S40)+Расходы!S13+Расходы!S14+IF(S$39="Разработка",Расходы!S15,Допущения!$E$85) -> 73010
B49: EBITDA | C49: ₽ | D49: =SUMIF($H$39:$S$39,"Разработка",$H$49:$S$49) -> -52000 | E49: =SUMIF($H$39:$S$39,"Операционка",$H$49:$S$49) -> 294152.62 | F49: =SUM($H$49:$S$49) -> 242152.62 | H49: =H46-H47-H48 -> -4000 | I49: =I46-I47-I48 -> -6000 | J49: =J46-J47-J48 -> -16000 | K49: =K46-K47-K48 -> -26000 | L49: =L46-L47-L48 -> -43631.6 | M49: =M46-M47-M48 -> -30347 | N49: =N46-N47-N48 -> -11460.22 | O49: =O46-O47-O48 -> 8808.28 | ... S49: =S46-S47-S48 -> 162892.8
B50: Проценты по кредиту | C50: ₽ | D50: =SUMIF($H$39:$S$39,"Разработка",$H$50:$S$50) -> 0 | E50: =SUMIF($H$39:$S$39,"Операционка",$H$50:$S$50) -> 0 | F50: =SUM($H$50:$S$50) -> 0 | H50: =0 -> 0 | I50: =0 -> 0 | J50: =0 -> 0 | K50: =0 -> 0 | L50: =0 -> 0 | M50: =0 -> 0 | N50: =0 -> 0 | O50: =0 -> 0 | ... S50: =0 -> 0
B51: Поступления выручки с начала года (база УСН) | C51: ₽ | D51: =INDEX($H$51:$S$51,1,Дев_мес) -> 0 | E51: =IF(Опер_мес>0,S51,"") -> 856656.05 | F51: =S51 -> 856656.05 | H51: =IF(H$37-Лаг_выручки>=1,INDEX($H46:$S46,1,H$37-Лаг_выручки),0) -> 0 | I51: =IF(YEAR(I$38)=YEAR(H$38),H51,0)+IF(I$37-Лаг_выручки>=1,INDEX($H46:$S46,1,I$37-Лаг_выручки),0) -> 0 | J51: =IF(YEAR(J$38)=YEAR(I$38),I51,0)+IF(J$37-Лаг_выручки>=1,INDEX($H46:$S46,1,J$37-Лаг_выручки),0) -> 0 | K51: =IF(YEAR(K$38)=YEAR(J$38),J51,0)+IF(K$37-Лаг_выручки>=1,INDEX($H46:$S46,1,K$37-Лаг_выручки),0) -> 0 | L51: =IF(YEAR(L$38)=YEAR(K$38),K51,0)+IF(L$37-Лаг_выручки>=1,INDEX($H46:$S46,1,L$37-Лаг_выручки),0) -> 14309.25 | M51: =IF(YEAR(M$38)=YEAR(L$38),L51,0)+IF(M$37-Лаг_выручки>=1,INDEX($H46:$S46,1,M$37-Лаг_выручки),0) -> 43978.95 | N51: =IF(YEAR(N$38)=YEAR(M$38),M51,0)+IF(N$37-Лаг_выручки>=1,INDEX($H46:$S46,1,N$37-Лаг_выручки),0) -> 95439.25 | O51: =IF(YEAR(O$38)=YEAR(N$38),N51,0)+IF(O$37-Лаг_выручки>=1,INDEX($H46:$S46,1,O$37-Лаг_выручки),0) -> 170244.55 | P51: =IF(YEAR(P$38)=YEAR(O$38),O51,0)+IF(P$37-Лаг_выручки>=1,INDEX($H46:$S46,1,P$37-Лаг_выручки),0) -> 270266.85 | ... S51: =IF(YEAR(S$38)=YEAR(R$38),R51,0)+IF(S$37-Лаг_выручки>=1,INDEX($H46:$S46,1,S$37-Лаг_выручки),0) -> 856656.05
B52: Налог к уплате с начала года | C52: ₽ | D52: =INDEX($H$52:$S$52,1,Дев_мес) -> 0 | E52: =IF(Опер_мес>0,S52,"") -> 0 | F52: =S52 -> 0 | H52: =MAX(0,Ставка_УСН*H51-MIN(Взносы_вычет,Лимит_вычета*Ставка_УСН*H51)) -> 0 | I52: =MAX(0,Ставка_УСН*I51-MIN(Взносы_вычет,Лимит_вычета*Ставка_УСН*I51)) -> 0 | J52: =MAX(0,Ставка_УСН*J51-MIN(Взносы_вычет,Лимит_вычета*Ставка_УСН*J51)) -> 0 | K52: =MAX(0,Ставка_УСН*K51-MIN(Взносы_вычет,Лимит_вычета*Ставка_УСН*K51)) -> 0 | L52: =MAX(0,Ставка_УСН*L51-MIN(Взносы_вычет,Лимит_вычета*Ставка_УСН*L51)) -> 0 | M52: =MAX(0,Ставка_УСН*M51-MIN(Взносы_вычет,Лимит_вычета*Ставка_УСН*M51)) -> 0 | N52: =MAX(0,Ставка_УСН*N51-MIN(Взносы_вычет,Лимит_вычета*Ставка_УСН*N51)) -> 0 | O52: =MAX(0,Ставка_УСН*O51-MIN(Взносы_вычет,Лимит_вычета*Ставка_УСН*O51)) -> 0 | ... S52: =MAX(0,Ставка_УСН*S51-MIN(Взносы_вычет,Лимит_вычета*Ставка_УСН*S51)) -> 0
B53: Налог (УСН) | C53: ₽ | D53: =SUMIF($H$39:$S$39,"Разработка",$H$53:$S$53) -> 0 | E53: =SUMIF($H$39:$S$39,"Операционка",$H$53:$S$53) -> 0 | F53: =SUM($H$53:$S$53) -> 0 | H53: =H52 -> 0 | I53: =I52-IF(YEAR(I$38)=YEAR(H$38),H52,0) -> 0 | J53: =J52-IF(YEAR(J$38)=YEAR(I$38),I52,0) -> 0 | K53: =K52-IF(YEAR(K$38)=YEAR(J$38),J52,0) -> 0 | L53: =L52-IF(YEAR(L$38)=YEAR(K$38),K52,0) -> 0 | M53: =M52-IF(YEAR(M$38)=YEAR(L$38),L52,0) -> 0 | N53: =N52-IF(YEAR(N$38)=YEAR(M$38),M52,0) -> 0 | O53: =O52-IF(YEAR(O$38)=YEAR(N$38),N52,0) -> 0 | P53: =P52-IF(YEAR(P$38)=YEAR(O$38),O52,0) -> 0 | ... S53: =S52-IF(YEAR(S$38)=YEAR(R$38),R52,0) -> 0
B54: Чистая прибыль | C54: ₽ | D54: =SUMIF($H$39:$S$39,"Разработка",$H$54:$S$54) -> -52000 | E54: =SUMIF($H$39:$S$39,"Операционка",$H$54:$S$54) -> 294152.62 | F54: =SUM($H$54:$S$54) -> 242152.62 | H54: =H49-H50-H53 -> -4000 | I54: =I49-I50-I53 -> -6000 | J54: =J49-J50-J53 -> -16000 | K54: =K49-K50-K53 -> -26000 | L54: =L49-L50-L53 -> -43631.6 | M54: =M49-M50-M53 -> -30347 | N54: =N49-N50-N53 -> -11460.22 | O54: =O49-O50-O53 -> 8808.28 | ... S54: =S49-S50-S53 -> 162892.8
B55: Поступления выручки на счёт (с лагом, за вычетом комиссии) | C55: ₽ | D55: =SUMIF($H$39:$S$39,"Разработка",$H$55:$S$55) -> 0 | E55: =SUMIF($H$39:$S$39,"Операционка",$H$55:$S$55) -> 804664.37 | F55: =SUM($H$55:$S$55) -> 804664.37 | H55: =IF(H$37-Лаг_выручки>=1,INDEX($H46:$S46,1,H$37-Лаг_выручки)-INDEX($H47:$S47,1,H$37-Лаг_выручки),0) -> 0 | I55: =IF(I$37-Лаг_выручки>=1,INDEX($H46:$S46,1,I$37-Лаг_выручки)-INDEX($H47:$S47,1,I$37-Лаг_выручки),0) -> 0 | J55: =IF(J$37-Лаг_выручки>=1,INDEX($H46:$S46,1,J$37-Лаг_выручки)-INDEX($H47:$S47,1,J$37-Лаг_выручки),0) -> 0 | K55: =IF(K$37-Лаг_выручки>=1,INDEX($H46:$S46,1,K$37-Лаг_выручки)-INDEX($H47:$S47,1,K$37-Лаг_выручки),0) -> 0 | L55: =IF(L$37-Лаг_выручки>=1,INDEX($H46:$S46,1,L$37-Лаг_выручки)-INDEX($H47:$S47,1,L$37-Лаг_выручки),0) -> 13644.15 | M55: =IF(M$37-Лаг_выручки>=1,INDEX($H46:$S46,1,M$37-Лаг_выручки)-INDEX($H47:$S47,1,M$37-Лаг_выручки),0) -> 28204.5 | N55: =IF(N$37-Лаг_выручки>=1,INDEX($H46:$S46,1,N$37-Лаг_выручки)-INDEX($H47:$S47,1,N$37-Лаг_выручки),0) -> 48792.28 | O55: =IF(O$37-Лаг_выручки>=1,INDEX($H46:$S46,1,O$37-Лаг_выручки)-INDEX($H47:$S47,1,O$37-Лаг_выручки),0) -> 70761.78 | ... S55: =IF(S$37-Лаг_выручки>=1,INDEX($H46:$S46,1,S$37-Лаг_выручки)-INDEX($H47:$S47,1,S$37-Лаг_выручки),0) -> 235902.8
B56: Чистый денежный поток | C56: ₽ | D56: =SUMIF($H$39:$S$39,"Разработка",$H$56:$S$56) -> 148000 | E56: =SUMIF($H$39:$S$39,"Операционка",$H$56:$S$56) -> 294152.62 | F56: =SUM($H$56:$S$56) -> 442152.62 | H56: =H55-H48-H53-H50+ДДС!H13 -> 196000 | I56: =I55-I48-I53-I50+ДДС!I13 -> -6000 | J56: =J55-J48-J53-J50+ДДС!J13 -> -16000 | K56: =K55-K48-K53-K50+ДДС!K13 -> -26000 | L56: =L55-L48-L53-L50+ДДС!L13 -> -43631.6 | M56: =M55-M48-M53-M50+ДДС!M13 -> -30347 | N56: =N55-N48-N53-N50+ДДС!N13 -> -11460.22 | O56: =O55-O48-O53-O50+ДДС!O13 -> 8808.28 | ... S56: =S55-S48-S53-S50+ДДС!S13 -> 162892.8
B57: Остаток денег на конец месяца | C57: ₽ | D57: =INDEX($H$57:$S$57,1,Дев_мес) -> 148000 | E57: =IF(Опер_мес>0,S57,"") -> 442152.62 | F57: =S57 -> 442152.62 | H57: =H56 -> 196000 | I57: =H57+I56 -> 190000 | J57: =I57+J56 -> 174000 | K57: =J57+K56 -> 148000 | L57: =K57+L56 -> 104368.4 | M57: =L57+M56 -> 74021.4 | N57: =M57+N56 -> 62561.18 | O57: =N57+O56 -> 71369.46 | P57: =O57+P56 -> 102029.88 | ... S57: =R57+S56 -> 442152.62
B58: Накопленный поток без привлечённого финансирования | C58: ₽ | D58: =INDEX($H$58:$S$58,1,Дев_мес) -> -52000 | E58: =IF(Опер_мес>0,S58,"") -> 242152.62 | F58: =S58 -> 242152.62 | H58: =H56-ДДС!H13-ДДС!H14 -> -4000 | I58: =H58+I56-ДДС!I13-ДДС!I14 -> -10000 | J58: =I58+J56-ДДС!J13-ДДС!J14 -> -26000 | K58: =J58+K56-ДДС!K13-ДДС!K14 -> -52000 | L58: =K58+L56-ДДС!L13-ДДС!L14 -> -95631.6 | M58: =L58+M56-ДДС!M13-ДДС!M14 -> -125978.6 | N58: =M58+N56-ДДС!N13-ДДС!N14 -> -137438.82 | O58: =N58+O56-ДДС!O13-ДДС!O14 -> -128630.54 | P58: =O58+P56-ДДС!P13-ДДС!P14 -> -97970.12 | ... S58: =R58+S56-ДДС!S13-ДДС!S14 -> 242152.62
B59: Точка пересечения нуля, мес. (служебная) | C59: мес. | H59: =IF(H58>=0,0,"") | I59: =IF(AND(I58>=0,H58<0),(I$37-1)+(-H58)/(I58-H58),"") | J59: =IF(AND(J58>=0,I58<0),(J$37-1)+(-I58)/(J58-I58),"") | K59: =IF(AND(K58>=0,J58<0),(K$37-1)+(-J58)/(K58-J58),"") | L59: =IF(AND(L58>=0,K58<0),(L$37-1)+(-K58)/(L58-K58),"") | M59: =IF(AND(M58>=0,L58<0),(M$37-1)+(-L58)/(M58-L58),"") | N59: =IF(AND(N58>=0,M58<0),(N$37-1)+(-M58)/(N58-M58),"") | O59: =IF(AND(O58>=0,N58<0),(O$37-1)+(-N58)/(O58-N58),"") | P59: =IF(AND(P58>=0,O58<0),(P$37-1)+(-O58)/(P58-O58),"") | ... S59: =IF(AND(S58>=0,R58<0),(S$37-1)+(-R58)/(S58-R58),"")
B61: ="Сценарий «"&(Допущения!$F$80)&"»: MAU ×"&(FIXED(Допущения!$F$82,1))&", eCPM ×"&(FIXED(Допущения!$F$83,1))&", конверсия ×"&(FIXED(Допущения!$F$84,1))&", маркетинг "&(FIXED(Допущения!$F$85,0))&" ₽/мес" -> Сценарий «Базовый»: MAU ×1.0, eCPM ×1.0, конверсия ×1.0, маркетинг 30,000 ₽/мес
B62: MAU | C62: чел. | D62: =INDEX($H$62:$S$62,1,Дев_мес) -> 0 | E62: =IF(Опер_мес>0,S62,"") -> 20000 | F62: =S62 -> 20000 | H62: =Выручка!H12*Допущения!$F$82 -> 0 | I62: =Выручка!I12*Допущения!$F$82 -> 0 | J62: =Выручка!J12*Допущения!$F$82 -> 0 | K62: =Выручка!K12*Допущения!$F$82 -> 0 | L62: =Выручка!L12*Допущения!$F$82 -> 1500 | M62: =Выручка!M12*Допущения!$F$82 -> 3000 | N62: =Выручка!N12*Допущения!$F$82 -> 5000 | O62: =Выручка!O12*Допущения!$F$82 -> 7000 | ... S62: =Выручка!S12*Допущения!$F$82 -> 20000
B63: Доход от рекламы | C63: ₽ | D63: =SUMIF($H$39:$S$39,"Разработка",$H$63:$S$63) -> 0 | E63: =SUMIF($H$39:$S$39,"Операционка",$H$63:$S$63) -> 364317.75 | F63: =SUM($H$63:$S$63) -> 364317.75 | H63: =H62*(Выручка!H41+Выручка!H42)*Допущения!$F$83 -> 0 | I63: =I62*(Выручка!I41+Выручка!I42)*Допущения!$F$83 -> 0 | J63: =J62*(Выручка!J41+Выручка!J42)*Допущения!$F$83 -> 0 | K63: =K62*(Выручка!K41+Выручка!K42)*Допущения!$F$83 -> 0 | L63: =L62*(Выручка!L41+Выручка!L42)*Допущения!$F$83 -> 7053.75 | M63: =M62*(Выручка!M41+Выручка!M42)*Допущения!$F$83 -> 14215.5 | N63: =N62*(Выручка!N41+Выручка!N42)*Допущения!$F$83 -> 24052.5 | O63: =O62*(Выручка!O41+Выручка!O42)*Допущения!$F$83 -> 34177.5 | ... S63: =S62*(Выручка!S41+Выручка!S42)*Допущения!$F$83 -> 101250
B64: Доход от IAP | C64: ₽ | D64: =SUMIF($H$39:$S$39,"Разработка",$H$64:$S$64) -> 0 | E64: =SUMIF($H$39:$S$39,"Операционка",$H$64:$S$64) -> 248198.4 | F64: =SUM($H$64:$S$64) -> 248198.4 | H64: =ROUND(H62*(Выручка!H43*Допущения!$F$84),0)*Выручка!H30 -> 0 | I64: =ROUND(I62*(Выручка!I43*Допущения!$F$84),0)*Выручка!I30 -> 0 | J64: =ROUND(J62*(Выручка!J43*Допущения!$F$84),0)*Выручка!J30 -> 0 | K64: =ROUND(K62*(Выручка!K43*Допущения!$F$84),0)*Выручка!K30 -> 0 | L64: =ROUND(L62*(Выручка!L43*Допущения!$F$84),0)*Выручка!L30 -> 3251.6 | M64: =ROUND(M62*(Выручка!M43*Допущения!$F$84),0)*Выручка!M30 -> 7163.2 | N64: =ROUND(N62*(Выручка!N43*Допущения!$F$84),0)*Выручка!N30 -> 12752.8 | O64: =ROUND(O62*(Выручка!O43*Допущения!$F$84),0)*Выручка!O30 -> 19353.6 | ... S64: =ROUND(S62*(Выручка!S43*Допущения!$F$84),0)*Выручка!S30 -> 79120
B65: Выручка | C65: ₽ | D65: =SUMIF($H$39:$S$39,"Разработка",$H$65:$S$65) -> 0 | E65: =SUMIF($H$39:$S$39,"Операционка",$H$65:$S$65) -> 612516.15 | F65: =SUM($H$65:$S$65) -> 612516.15 | H65: =H63+H64 -> 0 | I65: =I63+I64 -> 0 | J65: =J63+J64 -> 0 | K65: =K63+K64 -> 0 | L65: =L63+L64 -> 10305.35 | M65: =M63+M64 -> 21378.7 | N65: =N63+N64 -> 36805.3 | O65: =O63+O64 -> 53531.1 | ... S65: =S63+S64 -> 180370
B66: Комиссия магазина | C66: ₽ | D66: =SUMIF($H$39:$S$39,"Разработка",$H$66:$S$66) -> 0 | E66: =SUMIF($H$39:$S$39,"Операционка",$H$66:$S$66) -> 37229.76 | F66: =SUM($H$66:$S$66) -> 37229.76 | H66: =H64*Комиссия_стора -> 0 | I66: =I64*Комиссия_стора -> 0 | J66: =J64*Комиссия_стора -> 0 | K66: =K64*Комиссия_стора -> 0 | L66: =L64*Комиссия_стора -> 487.74 | M66: =M64*Комиссия_стора -> 1074.48 | N66: =N64*Комиссия_стора -> 1912.92 | O66: =O64*Комиссия_стора -> 2903.04 | ... S66: =S64*Комиссия_стора -> 11868
B67: Операционные расходы | C67: ₽ | D67: =SUMIF($H$39:$S$39,"Разработка",$H$67:$S$67) -> 52000 | E67: =SUMIF($H$39:$S$39,"Операционка",$H$67:$S$67) -> 412651.25 | F67: =SUM($H$67:$S$67) -> 464651.25 | H67: =(Расходы!H12-Энергия!H39+H62*Энергия!H40)+Расходы!H13+Расходы!H14+IF(H$39="Разработка",Расходы!H15,Допущения!$F$85) -> 4000 | I67: =(Расходы!I12-Энергия!I39+I62*Энергия!I40)+Расходы!I13+Расходы!I14+IF(I$39="Разработка",Расходы!I15,Допущения!$F$85) -> 6000 | J67: =(Расходы!J12-Энергия!J39+J62*Энергия!J40)+Расходы!J13+Расходы!J14+IF(J$39="Разработка",Расходы!J15,Допущения!$F$85) -> 16000 | K67: =(Расходы!K12-Энергия!K39+K62*Энергия!K40)+Расходы!K13+Расходы!K14+IF(K$39="Разработка",Расходы!K15,Допущения!$F$85) -> 26000 | L67: =(Расходы!L12-Энергия!L39+L62*Энергия!L40)+Расходы!L13+Расходы!L14+IF(L$39="Разработка",Расходы!L15,Допущения!$F$85) -> 46911.25 | M67: =(Расходы!M12-Энергия!M39+M62*Энергия!M40)+Расходы!M13+Расходы!M14+IF(M$39="Разработка",Расходы!M15,Допущения!$F$85) -> 47822.5 | N67: =(Расходы!N12-Энергия!N39+N62*Энергия!N40)+Расходы!N13+Расходы!N14+IF(N$39="Разработка",Расходы!N15,Допущения!$F$85) -> 49037.5 | O67: =(Расходы!O12-Энергия!O39+O62*Энергия!O40)+Расходы!O13+Расходы!O14+IF(O$39="Разработка",Расходы!O15,Допущения!$F$85) -> 50252.5 | ... S67: =(Расходы!S12-Энергия!S39+S62*Энергия!S40)+Расходы!S13+Расходы!S14+IF(S$39="Разработка",Расходы!S15,Допущения!$F$85) -> 58150
B68: EBITDA | C68: ₽ | D68: =SUMIF($H$39:$S$39,"Разработка",$H$68:$S$68) -> -52000 | E68: =SUMIF($H$39:$S$39,"Операционка",$H$68:$S$68) -> 162635.14 | F68: =SUM($H$68:$S$68) -> 110635.14 | H68: =H65-H66-H67 -> -4000 | I68: =I65-I66-I67 -> -6000 | J68: =J65-J66-J67 -> -16000 | K68: =K65-K66-K67 -> -26000 | L68: =L65-L66-L67 -> -37093.64 | M68: =M65-M66-M67 -> -27518.28 | N68: =N65-N66-N67 -> -14145.12 | O68: =O65-O66-O67 -> 375.56 | ... S68: =S65-S66-S67 -> 110352
B69: Проценты по кредиту | C69: ₽ | D69: =SUMIF($H$39:$S$39,"Разработка",$H$69:$S$69) -> 0 | E69: =SUMIF($H$39:$S$39,"Операционка",$H$69:$S$69) -> 0 | F69: =SUM($H$69:$S$69) -> 0 | H69: =0 -> 0 | I69: =0 -> 0 | J69: =0 -> 0 | K69: =0 -> 0 | L69: =0 -> 0 | M69: =0 -> 0 | N69: =0 -> 0 | O69: =0 -> 0 | ... S69: =0 -> 0
B70: Поступления выручки с начала года (база УСН) | C70: ₽ | D70: =INDEX($H$70:$S$70,1,Дев_мес) -> 0 | E70: =IF(Опер_мес>0,S70,"") -> 612516.15 | F70: =S70 -> 612516.15 | H70: =IF(H$37-Лаг_выручки>=1,INDEX($H65:$S65,1,H$37-Лаг_выручки),0) -> 0 | I70: =IF(YEAR(I$38)=YEAR(H$38),H70,0)+IF(I$37-Лаг_выручки>=1,INDEX($H65:$S65,1,I$37-Лаг_выручки),0) -> 0 | J70: =IF(YEAR(J$38)=YEAR(I$38),I70,0)+IF(J$37-Лаг_выручки>=1,INDEX($H65:$S65,1,J$37-Лаг_выручки),0) -> 0 | K70: =IF(YEAR(K$38)=YEAR(J$38),J70,0)+IF(K$37-Лаг_выручки>=1,INDEX($H65:$S65,1,K$37-Лаг_выручки),0) -> 0 | L70: =IF(YEAR(L$38)=YEAR(K$38),K70,0)+IF(L$37-Лаг_выручки>=1,INDEX($H65:$S65,1,L$37-Лаг_выручки),0) -> 10305.35 | M70: =IF(YEAR(M$38)=YEAR(L$38),L70,0)+IF(M$37-Лаг_выручки>=1,INDEX($H65:$S65,1,M$37-Лаг_выручки),0) -> 31684.05 | N70: =IF(YEAR(N$38)=YEAR(M$38),M70,0)+IF(N$37-Лаг_выручки>=1,INDEX($H65:$S65,1,N$37-Лаг_выручки),0) -> 68489.35 | O70: =IF(YEAR(O$38)=YEAR(N$38),N70,0)+IF(O$37-Лаг_выручки>=1,INDEX($H65:$S65,1,O$37-Лаг_выручки),0) -> 122020.45 | P70: =IF(YEAR(P$38)=YEAR(O$38),O70,0)+IF(P$37-Лаг_выручки>=1,INDEX($H65:$S65,1,P$37-Лаг_выручки),0) -> 193668.15 | ... S70: =IF(YEAR(S$38)=YEAR(R$38),R70,0)+IF(S$37-Лаг_выручки>=1,INDEX($H65:$S65,1,S$37-Лаг_выручки),0) -> 612516.15
B71: Налог к уплате с начала года | C71: ₽ | D71: =INDEX($H$71:$S$71,1,Дев_мес) -> 0 | E71: =IF(Опер_мес>0,S71,"") -> 0 | F71: =S71 -> 0 | H71: =MAX(0,Ставка_УСН*H70-MIN(Взносы_вычет,Лимит_вычета*Ставка_УСН*H70)) -> 0 | I71: =MAX(0,Ставка_УСН*I70-MIN(Взносы_вычет,Лимит_вычета*Ставка_УСН*I70)) -> 0 | J71: =MAX(0,Ставка_УСН*J70-MIN(Взносы_вычет,Лимит_вычета*Ставка_УСН*J70)) -> 0 | K71: =MAX(0,Ставка_УСН*K70-MIN(Взносы_вычет,Лимит_вычета*Ставка_УСН*K70)) -> 0 | L71: =MAX(0,Ставка_УСН*L70-MIN(Взносы_вычет,Лимит_вычета*Ставка_УСН*L70)) -> 0 | M71: =MAX(0,Ставка_УСН*M70-MIN(Взносы_вычет,Лимит_вычета*Ставка_УСН*M70)) -> 0 | N71: =MAX(0,Ставка_УСН*N70-MIN(Взносы_вычет,Лимит_вычета*Ставка_УСН*N70)) -> 0 | O71: =MAX(0,Ставка_УСН*O70-MIN(Взносы_вычет,Лимит_вычета*Ставка_УСН*O70)) -> 0 | ... S71: =MAX(0,Ставка_УСН*S70-MIN(Взносы_вычет,Лимит_вычета*Ставка_УСН*S70)) -> 0
B72: Налог (УСН) | C72: ₽ | D72: =SUMIF($H$39:$S$39,"Разработка",$H$72:$S$72) -> 0 | E72: =SUMIF($H$39:$S$39,"Операционка",$H$72:$S$72) -> 0 | F72: =SUM($H$72:$S$72) -> 0 | H72: =H71 -> 0 | I72: =I71-IF(YEAR(I$38)=YEAR(H$38),H71,0) -> 0 | J72: =J71-IF(YEAR(J$38)=YEAR(I$38),I71,0) -> 0 | K72: =K71-IF(YEAR(K$38)=YEAR(J$38),J71,0) -> 0 | L72: =L71-IF(YEAR(L$38)=YEAR(K$38),K71,0) -> 0 | M72: =M71-IF(YEAR(M$38)=YEAR(L$38),L71,0) -> 0 | N72: =N71-IF(YEAR(N$38)=YEAR(M$38),M71,0) -> 0 | O72: =O71-IF(YEAR(O$38)=YEAR(N$38),N71,0) -> 0 | P72: =P71-IF(YEAR(P$38)=YEAR(O$38),O71,0) -> 0 | ... S72: =S71-IF(YEAR(S$38)=YEAR(R$38),R71,0) -> 0
B73: Чистая прибыль | C73: ₽ | D73: =SUMIF($H$39:$S$39,"Разработка",$H$73:$S$73) -> -52000 | E73: =SUMIF($H$39:$S$39,"Операционка",$H$73:$S$73) -> 162635.14 | F73: =SUM($H$73:$S$73) -> 110635.14 | H73: =H68-H69-H72 -> -4000 | I73: =I68-I69-I72 -> -6000 | J73: =J68-J69-J72 -> -16000 | K73: =K68-K69-K72 -> -26000 | L73: =L68-L69-L72 -> -37093.64 | M73: =M68-M69-M72 -> -27518.28 | N73: =N68-N69-N72 -> -14145.12 | O73: =O68-O69-O72 -> 375.56 | ... S73: =S68-S69-S72 -> 110352
B74: Поступления выручки на счёт (с лагом, за вычетом комиссии) | C74: ₽ | D74: =SUMIF($H$39:$S$39,"Разработка",$H$74:$S$74) -> 0 | E74: =SUMIF($H$39:$S$39,"Операционка",$H$74:$S$74) -> 575286.39 | F74: =SUM($H$74:$S$74) -> 575286.39 | H74: =IF(H$37-Лаг_выручки>=1,INDEX($H65:$S65,1,H$37-Лаг_выручки)-INDEX($H66:$S66,1,H$37-Лаг_выручки),0) -> 0 | I74: =IF(I$37-Лаг_выручки>=1,INDEX($H65:$S65,1,I$37-Лаг_выручки)-INDEX($H66:$S66,1,I$37-Лаг_выручки),0) -> 0 | J74: =IF(J$37-Лаг_выручки>=1,INDEX($H65:$S65,1,J$37-Лаг_выручки)-INDEX($H66:$S66,1,J$37-Лаг_выручки),0) -> 0 | K74: =IF(K$37-Лаг_выручки>=1,INDEX($H65:$S65,1,K$37-Лаг_выручки)-INDEX($H66:$S66,1,K$37-Лаг_выручки),0) -> 0 | L74: =IF(L$37-Лаг_выручки>=1,INDEX($H65:$S65,1,L$37-Лаг_выручки)-INDEX($H66:$S66,1,L$37-Лаг_выручки),0) -> 9817.61 | M74: =IF(M$37-Лаг_выручки>=1,INDEX($H65:$S65,1,M$37-Лаг_выручки)-INDEX($H66:$S66,1,M$37-Лаг_выручки),0) -> 20304.22 | N74: =IF(N$37-Лаг_выручки>=1,INDEX($H65:$S65,1,N$37-Лаг_выручки)-INDEX($H66:$S66,1,N$37-Лаг_выручки),0) -> 34892.38 | O74: =IF(O$37-Лаг_выручки>=1,INDEX($H65:$S65,1,O$37-Лаг_выручки)-INDEX($H66:$S66,1,O$37-Лаг_выручки),0) -> 50628.06 | ... S74: =IF(S$37-Лаг_выручки>=1,INDEX($H65:$S65,1,S$37-Лаг_выручки)-INDEX($H66:$S66,1,S$37-Лаг_выручки),0) -> 168502
B75: Чистый денежный поток | C75: ₽ | D75: =SUMIF($H$39:$S$39,"Разработка",$H$75:$S$75) -> 148000 | E75: =SUMIF($H$39:$S$39,"Операционка",$H$75:$S$75) -> 162635.14 | F75: =SUM($H$75:$S$75) -> 310635.14 | H75: =H74-H67-H72-H69+ДДС!H13 -> 196000 | I75: =I74-I67-I72-I69+ДДС!I13 -> -6000 | J75: =J74-J67-J72-J69+ДДС!J13 -> -16000 | K75: =K74-K67-K72-K69+ДДС!K13 -> -26000 | L75: =L74-L67-L72-L69+ДДС!L13 -> -37093.64 | M75: =M74-M67-M72-M69+ДДС!M13 -> -27518.28 | N75: =N74-N67-N72-N69+ДДС!N13 -> -14145.12 | O75: =O74-O67-O72-O69+ДДС!O13 -> 375.56 | ... S75: =S74-S67-S72-S69+ДДС!S13 -> 110352
B76: Остаток денег на конец месяца | C76: ₽ | D76: =INDEX($H$76:$S$76,1,Дев_мес) -> 148000 | E76: =IF(Опер_мес>0,S76,"") -> 310635.14 | F76: =S76 -> 310635.14 | H76: =H75 -> 196000 | I76: =H76+I75 -> 190000 | J76: =I76+J75 -> 174000 | K76: =J76+K75 -> 148000 | L76: =K76+L75 -> 110906.36 | M76: =L76+M75 -> 83388.08 | N76: =M76+N75 -> 69242.96 | O76: =N76+O75 -> 69618.52 | P76: =O76+P75 -> 85691.54 | ... S76: =R76+S75 -> 310635.14
B77: Накопленный поток без привлечённого финансирования | C77: ₽ | D77: =INDEX($H$77:$S$77,1,Дев_мес) -> -52000 | E77: =IF(Опер_мес>0,S77,"") -> 110635.14 | F77: =S77 -> 110635.14 | H77: =H75-ДДС!H13-ДДС!H14 -> -4000 | I77: =H77+I75-ДДС!I13-ДДС!I14 -> -10000 | J77: =I77+J75-ДДС!J13-ДДС!J14 -> -26000 | K77: =J77+K75-ДДС!K13-ДДС!K14 -> -52000 | L77: =K77+L75-ДДС!L13-ДДС!L14 -> -89093.64 | M77: =L77+M75-ДДС!M13-ДДС!M14 -> -116611.92 | N77: =M77+N75-ДДС!N13-ДДС!N14 -> -130757.04 | O77: =N77+O75-ДДС!O13-ДДС!O14 -> -130381.48 | P77: =O77+P75-ДДС!P13-ДДС!P14 -> -114308.46 | ... S77: =R77+S75-ДДС!S13-ДДС!S14 -> 110635.14
B78: Точка пересечения нуля, мес. (служебная) | C78: мес. | H78: =IF(H77>=0,0,"") | I78: =IF(AND(I77>=0,H77<0),(I$37-1)+(-H77)/(I77-H77),"") | J78: =IF(AND(J77>=0,I77<0),(J$37-1)+(-I77)/(J77-I77),"") | K78: =IF(AND(K77>=0,J77<0),(K$37-1)+(-J77)/(K77-J77),"") | L78: =IF(AND(L77>=0,K77<0),(L$37-1)+(-K77)/(L77-K77),"") | M78: =IF(AND(M77>=0,L77<0),(M$37-1)+(-L77)/(M77-L77),"") | N78: =IF(AND(N77>=0,M77<0),(N$37-1)+(-M77)/(N77-M77),"") | O78: =IF(AND(O77>=0,N77<0),(O$37-1)+(-N77)/(O77-N77),"") | P78: =IF(AND(P77>=0,O77<0),(P$37-1)+(-O77)/(P77-O77),"") | ... S78: =IF(AND(S77>=0,R77<0),(S$37-1)+(-R77)/(S77-R77),"")
B80: ="Сценарий «"&(Допущения!$G$80)&"»: MAU ×"&(FIXED(Допущения!$G$82,1))&", eCPM ×"&(FIXED(Допущения!$G$83,1))&", конверсия ×"&(FIXED(Допущения!$G$84,1))&", маркетинг "&(FIXED(Допущения!$G$85,0))&" ₽/мес" -> Сценарий «Пессимистичный»: MAU ×0.6, eCPM ×1.0, конверсия ×1.0, маркетинг 25,000 ₽/мес
B81: MAU | C81: чел. | D81: =INDEX($H$81:$S$81,1,Дев_мес) -> 0 | E81: =IF(Опер_мес>0,S81,"") -> 12000 | F81: =S81 -> 12000 | H81: =Выручка!H12*Допущения!$G$82 -> 0 | I81: =Выручка!I12*Допущения!$G$82 -> 0 | J81: =Выручка!J12*Допущения!$G$82 -> 0 | K81: =Выручка!K12*Допущения!$G$82 -> 0 | L81: =Выручка!L12*Допущения!$G$82 -> 900 | M81: =Выручка!M12*Допущения!$G$82 -> 1800 | N81: =Выручка!N12*Допущения!$G$82 -> 3000 | O81: =Выручка!O12*Допущения!$G$82 -> 4200 | ... S81: =Выручка!S12*Допущения!$G$82 -> 12000
B82: Доход от рекламы | C82: ₽ | D82: =SUMIF($H$39:$S$39,"Разработка",$H$82:$S$82) -> 0 | E82: =SUMIF($H$39:$S$39,"Операционка",$H$82:$S$82) -> 218590.65 | F82: =SUM($H$82:$S$82) -> 218590.65 | H82: =H81*(Выручка!H41+Выручка!H42)*Допущения!$G$83 -> 0 | I82: =I81*(Выручка!I41+Выручка!I42)*Допущения!$G$83 -> 0 | J82: =J81*(Выручка!J41+Выручка!J42)*Допущения!$G$83 -> 0 | K82: =K81*(Выручка!K41+Выручка!K42)*Допущения!$G$83 -> 0 | L82: =L81*(Выручка!L41+Выручка!L42)*Допущения!$G$83 -> 4232.25 | M82: =M81*(Выручка!M41+Выручка!M42)*Допущения!$G$83 -> 8529.3 | N82: =N81*(Выручка!N41+Выручка!N42)*Допущения!$G$83 -> 14431.5 | O82: =O81*(Выручка!O41+Выручка!O42)*Допущения!$G$83 -> 20506.5 | ... S82: =S81*(Выручка!S41+Выручка!S42)*Допущения!$G$83 -> 60750
B83: Доход от IAP | C83: ₽ | D83: =SUMIF($H$39:$S$39,"Разработка",$H$83:$S$83) -> 0 | E83: =SUMIF($H$39:$S$39,"Операционка",$H$83:$S$83) -> 148808.8 | F83: =SUM($H$83:$S$83) -> 148808.8 | H83: =ROUND(H81*(Выручка!H43*Допущения!$G$84),0)*Выручка!H30 -> 0 | I83: =ROUND(I81*(Выручка!I43*Допущения!$G$84),0)*Выручка!I30 -> 0 | J83: =ROUND(J81*(Выручка!J43*Допущения!$G$84),0)*Выручка!J30 -> 0 | K83: =ROUND(K81*(Выручка!K43*Допущения!$G$84),0)*Выручка!K30 -> 0 | L83: =ROUND(L81*(Выручка!L43*Допущения!$G$84),0)*Выручка!L30 -> 1773.6 | M83: =ROUND(M81*(Выручка!M43*Допущения!$G$84),0)*Выручка!M30 -> 4232.8 | N83: =ROUND(N81*(Выручка!N43*Допущения!$G$84),0)*Выручка!N30 -> 7718.8 | O83: =ROUND(O81*(Выручка!O43*Допущения!$G$84),0)*Выручка!O30 -> 11750.4 | ... S83: =ROUND(S81*(Выручка!S43*Допущения!$G$84),0)*Выручка!S30 -> 47472
B84: Выручка | C84: ₽ | D84: =SUMIF($H$39:$S$39,"Разработка",$H$84:$S$84) -> 0 | E84: =SUMIF($H$39:$S$39,"Операционка",$H$84:$S$84) -> 367399.45 | F84: =SUM($H$84:$S$84) -> 367399.45 | H84: =H82+H83 -> 0 | I84: =I82+I83 -> 0 | J84: =J82+J83 -> 0 | K84: =K82+K83 -> 0 | L84: =L82+L83 -> 6005.85 | M84: =M82+M83 -> 12762.1 | N84: =N82+N83 -> 22150.3 | O84: =O82+O83 -> 32256.9 | ... S84: =S82+S83 -> 108222
B85: Комиссия магазина | C85: ₽ | D85: =SUMIF($H$39:$S$39,"Разработка",$H$85:$S$85) -> 0 | E85: =SUMIF($H$39:$S$39,"Операционка",$H$85:$S$85) -> 22321.32 | F85: =SUM($H$85:$S$85) -> 22321.32 | H85: =H83*Комиссия_стора -> 0 | I85: =I83*Комиссия_стора -> 0 | J85: =J83*Комиссия_стора -> 0 | K85: =K83*Комиссия_стора -> 0 | L85: =L83*Комиссия_стора -> 266.04 | M85: =M83*Комиссия_стора -> 634.92 | N85: =N83*Комиссия_стора -> 1157.82 | O85: =O83*Комиссия_стора -> 1762.56 | ... S85: =S83*Комиссия_стора -> 7120.8
B86: Операционные расходы | C86: ₽ | D86: =SUMIF($H$39:$S$39,"Разработка",$H$86:$S$86) -> 52000 | E86: =SUMIF($H$39:$S$39,"Операционка",$H$86:$S$86) -> 354790.75 | F86: =SUM($H$86:$S$86) -> 406790.75 | H86: =(Расходы!H12-Энергия!H39+H81*Энергия!H40)+Расходы!H13+Расходы!H14+IF(H$39="Разработка",Расходы!H15,Допущения!$G$85) -> 4000 | I86: =(Расходы!I12-Энергия!I39+I81*Энергия!I40)+Расходы!I13+Расходы!I14+IF(I$39="Разработка",Расходы!I15,Допущения!$G$85) -> 6000 | J86: =(Расходы!J12-Энергия!J39+J81*Энергия!J40)+Расходы!J13+Расходы!J14+IF(J$39="Разработка",Расходы!J15,Допущения!$G$85) -> 16000 | K86: =(Расходы!K12-Энергия!K39+K81*Энергия!K40)+Расходы!K13+Расходы!K14+IF(K$39="Разработка",Расходы!K15,Допущения!$G$85) -> 26000 | L86: =(Расходы!L12-Энергия!L39+L81*Энергия!L40)+Расходы!L13+Расходы!L14+IF(L$39="Разработка",Расходы!L15,Допущения!$G$85) -> 41546.75 | M86: =(Расходы!M12-Энергия!M39+M81*Энергия!M40)+Расходы!M13+Расходы!M14+IF(M$39="Разработка",Расходы!M15,Допущения!$G$85) -> 42093.5 | N86: =(Расходы!N12-Энергия!N39+N81*Энергия!N40)+Расходы!N13+Расходы!N14+IF(N$39="Разработка",Расходы!N15,Допущения!$G$85) -> 42822.5 | O86: =(Расходы!O12-Энергия!O39+O81*Энергия!O40)+Расходы!O13+Расходы!O14+IF(O$39="Разработка",Расходы!O15,Допущения!$G$85) -> 43551.5 | ... S86: =(Расходы!S12-Энергия!S39+S81*Энергия!S40)+Расходы!S13+Расходы!S14+IF(S$39="Разработка",Расходы!S15,Допущения!$G$85) -> 48290
B87: EBITDA | C87: ₽ | D87: =SUMIF($H$39:$S$39,"Разработка",$H$87:$S$87) -> -52000 | E87: =SUMIF($H$39:$S$39,"Операционка",$H$87:$S$87) -> -9712.62 | F87: =SUM($H$87:$S$87) -> -61712.62 | H87: =H84-H85-H86 -> -4000 | I87: =I84-I85-I86 -> -6000 | J87: =J84-J85-J86 -> -16000 | K87: =K84-K85-K86 -> -26000 | L87: =L84-L85-L86 -> -35806.94 | M87: =M84-M85-M86 -> -29966.32 | N87: =N84-N85-N86 -> -21830.02 | O87: =O84-O85-O86 -> -13057.16 | ... S87: =S84-S85-S86 -> 52811.2
B88: Проценты по кредиту | C88: ₽ | D88: =SUMIF($H$39:$S$39,"Разработка",$H$88:$S$88) -> 0 | E88: =SUMIF($H$39:$S$39,"Операционка",$H$88:$S$88) -> 0 | F88: =SUM($H$88:$S$88) -> 0 | H88: =0 -> 0 | I88: =0 -> 0 | J88: =0 -> 0 | K88: =0 -> 0 | L88: =0 -> 0 | M88: =0 -> 0 | N88: =0 -> 0 | O88: =0 -> 0 | ... S88: =0 -> 0
B89: Поступления выручки с начала года (база УСН) | C89: ₽ | D89: =INDEX($H$89:$S$89,1,Дев_мес) -> 0 | E89: =IF(Опер_мес>0,S89,"") -> 367399.45 | F89: =S89 -> 367399.45 | H89: =IF(H$37-Лаг_выручки>=1,INDEX($H84:$S84,1,H$37-Лаг_выручки),0) -> 0 | I89: =IF(YEAR(I$38)=YEAR(H$38),H89,0)+IF(I$37-Лаг_выручки>=1,INDEX($H84:$S84,1,I$37-Лаг_выручки),0) -> 0 | J89: =IF(YEAR(J$38)=YEAR(I$38),I89,0)+IF(J$37-Лаг_выручки>=1,INDEX($H84:$S84,1,J$37-Лаг_выручки),0) -> 0 | K89: =IF(YEAR(K$38)=YEAR(J$38),J89,0)+IF(K$37-Лаг_выручки>=1,INDEX($H84:$S84,1,K$37-Лаг_выручки),0) -> 0 | L89: =IF(YEAR(L$38)=YEAR(K$38),K89,0)+IF(L$37-Лаг_выручки>=1,INDEX($H84:$S84,1,L$37-Лаг_выручки),0) -> 6005.85 | M89: =IF(YEAR(M$38)=YEAR(L$38),L89,0)+IF(M$37-Лаг_выручки>=1,INDEX($H84:$S84,1,M$37-Лаг_выручки),0) -> 18767.95 | N89: =IF(YEAR(N$38)=YEAR(M$38),M89,0)+IF(N$37-Лаг_выручки>=1,INDEX($H84:$S84,1,N$37-Лаг_выручки),0) -> 40918.25 | O89: =IF(YEAR(O$38)=YEAR(N$38),N89,0)+IF(O$37-Лаг_выручки>=1,INDEX($H84:$S84,1,O$37-Лаг_выручки),0) -> 73175.15 | P89: =IF(YEAR(P$38)=YEAR(O$38),O89,0)+IF(P$37-Лаг_выручки>=1,INDEX($H84:$S84,1,P$37-Лаг_выручки),0) -> 116092.65 | ... S89: =IF(YEAR(S$38)=YEAR(R$38),R89,0)+IF(S$37-Лаг_выручки>=1,INDEX($H84:$S84,1,S$37-Лаг_выручки),0) -> 367399.45
B90: Налог к уплате с начала года | C90: ₽ | D90: =INDEX($H$90:$S$90,1,Дев_мес) -> 0 | E90: =IF(Опер_мес>0,S90,"") -> 0 | F90: =S90 -> 0 | H90: =MAX(0,Ставка_УСН*H89-MIN(Взносы_вычет,Лимит_вычета*Ставка_УСН*H89)) -> 0 | I90: =MAX(0,Ставка_УСН*I89-MIN(Взносы_вычет,Лимит_вычета*Ставка_УСН*I89)) -> 0 | J90: =MAX(0,Ставка_УСН*J89-MIN(Взносы_вычет,Лимит_вычета*Ставка_УСН*J89)) -> 0 | K90: =MAX(0,Ставка_УСН*K89-MIN(Взносы_вычет,Лимит_вычета*Ставка_УСН*K89)) -> 0 | L90: =MAX(0,Ставка_УСН*L89-MIN(Взносы_вычет,Лимит_вычета*Ставка_УСН*L89)) -> 0 | M90: =MAX(0,Ставка_УСН*M89-MIN(Взносы_вычет,Лимит_вычета*Ставка_УСН*M89)) -> 0 | N90: =MAX(0,Ставка_УСН*N89-MIN(Взносы_вычет,Лимит_вычета*Ставка_УСН*N89)) -> 0 | O90: =MAX(0,Ставка_УСН*O89-MIN(Взносы_вычет,Лимит_вычета*Ставка_УСН*O89)) -> 0 | ... S90: =MAX(0,Ставка_УСН*S89-MIN(Взносы_вычет,Лимит_вычета*Ставка_УСН*S89)) -> 0
B91: Налог (УСН) | C91: ₽ | D91: =SUMIF($H$39:$S$39,"Разработка",$H$91:$S$91) -> 0 | E91: =SUMIF($H$39:$S$39,"Операционка",$H$91:$S$91) -> 0 | F91: =SUM($H$91:$S$91) -> 0 | H91: =H90 -> 0 | I91: =I90-IF(YEAR(I$38)=YEAR(H$38),H90,0) -> 0 | J91: =J90-IF(YEAR(J$38)=YEAR(I$38),I90,0) -> 0 | K91: =K90-IF(YEAR(K$38)=YEAR(J$38),J90,0) -> 0 | L91: =L90-IF(YEAR(L$38)=YEAR(K$38),K90,0) -> 0 | M91: =M90-IF(YEAR(M$38)=YEAR(L$38),L90,0) -> 0 | N91: =N90-IF(YEAR(N$38)=YEAR(M$38),M90,0) -> 0 | O91: =O90-IF(YEAR(O$38)=YEAR(N$38),N90,0) -> 0 | P91: =P90-IF(YEAR(P$38)=YEAR(O$38),O90,0) -> 0 | ... S91: =S90-IF(YEAR(S$38)=YEAR(R$38),R90,0) -> 0
B92: Чистая прибыль | C92: ₽ | D92: =SUMIF($H$39:$S$39,"Разработка",$H$92:$S$92) -> -52000 | E92: =SUMIF($H$39:$S$39,"Операционка",$H$92:$S$92) -> -9712.62 | F92: =SUM($H$92:$S$92) -> -61712.62 | H92: =H87-H88-H91 -> -4000 | I92: =I87-I88-I91 -> -6000 | J92: =J87-J88-J91 -> -16000 | K92: =K87-K88-K91 -> -26000 | L92: =L87-L88-L91 -> -35806.94 | M92: =M87-M88-M91 -> -29966.32 | N92: =N87-N88-N91 -> -21830.02 | O92: =O87-O88-O91 -> -13057.16 | ... S92: =S87-S88-S91 -> 52811.2
B93: Поступления выручки на счёт (с лагом, за вычетом комиссии) | C93: ₽ | D93: =SUMIF($H$39:$S$39,"Разработка",$H$93:$S$93) -> 0 | E93: =SUMIF($H$39:$S$39,"Операционка",$H$93:$S$93) -> 345078.13 | F93: =SUM($H$93:$S$93) -> 345078.13 | H93: =IF(H$37-Лаг_выручки>=1,INDEX($H84:$S84,1,H$37-Лаг_выручки)-INDEX($H85:$S85,1,H$37-Лаг_выручки),0) -> 0 | I93: =IF(I$37-Лаг_выручки>=1,INDEX($H84:$S84,1,I$37-Лаг_выручки)-INDEX($H85:$S85,1,I$37-Лаг_выручки),0) -> 0 | J93: =IF(J$37-Лаг_выручки>=1,INDEX($H84:$S84,1,J$37-Лаг_выручки)-INDEX($H85:$S85,1,J$37-Лаг_выручки),0) -> 0 | K93: =IF(K$37-Лаг_выручки>=1,INDEX($H84:$S84,1,K$37-Лаг_выручки)-INDEX($H85:$S85,1,K$37-Лаг_выручки),0) -> 0 | L93: =IF(L$37-Лаг_выручки>=1,INDEX($H84:$S84,1,L$37-Лаг_выручки)-INDEX($H85:$S85,1,L$37-Лаг_выручки),0) -> 5739.81 | M93: =IF(M$37-Лаг_выручки>=1,INDEX($H84:$S84,1,M$37-Лаг_выручки)-INDEX($H85:$S85,1,M$37-Лаг_выручки),0) -> 12127.18 | N93: =IF(N$37-Лаг_выручки>=1,INDEX($H84:$S84,1,N$37-Лаг_выручки)-INDEX($H85:$S85,1,N$37-Лаг_выручки),0) -> 20992.48 | O93: =IF(O$37-Лаг_выручки>=1,INDEX($H84:$S84,1,O$37-Лаг_выручки)-INDEX($H85:$S85,1,O$37-Лаг_выручки),0) -> 30494.34 | ... S93: =IF(S$37-Лаг_выручки>=1,INDEX($H84:$S84,1,S$37-Лаг_выручки)-INDEX($H85:$S85,1,S$37-Лаг_выручки),0) -> 101101.2
B94: Чистый денежный поток | C94: ₽ | D94: =SUMIF($H$39:$S$39,"Разработка",$H$94:$S$94) -> 148000 | E94: =SUMIF($H$39:$S$39,"Операционка",$H$94:$S$94) -> -9712.62 | F94: =SUM($H$94:$S$94) -> 138287.38 | H94: =H93-H86-H91-H88+ДДС!H13 -> 196000 | I94: =I93-I86-I91-I88+ДДС!I13 -> -6000 | J94: =J93-J86-J91-J88+ДДС!J13 -> -16000 | K94: =K93-K86-K91-K88+ДДС!K13 -> -26000 | L94: =L93-L86-L91-L88+ДДС!L13 -> -35806.94 | M94: =M93-M86-M91-M88+ДДС!M13 -> -29966.32 | N94: =N93-N86-N91-N88+ДДС!N13 -> -21830.02 | O94: =O93-O86-O91-O88+ДДС!O13 -> -13057.16 | ... S94: =S93-S86-S91-S88+ДДС!S13 -> 52811.2
B95: Остаток денег на конец месяца | C95: ₽ | D95: =INDEX($H$95:$S$95,1,Дев_мес) -> 148000 | E95: =IF(Опер_мес>0,S95,"") -> 138287.38 | F95: =S95 -> 138287.38 | H95: =H94 -> 196000 | I95: =H95+I94 -> 190000 | J95: =I95+J94 -> 174000 | K95: =J95+K94 -> 148000 | L95: =K95+L94 -> 112193.06 | M95: =L95+M94 -> 82226.74 | N95: =M95+N94 -> 60396.72 | O95: =N95+O94 -> 47339.56 | P95: =O95+P94 -> 43522.92 | ... S95: =R95+S94 -> 138287.38
B96: Накопленный поток без привлечённого финансирования | C96: ₽ | D96: =INDEX($H$96:$S$96,1,Дев_мес) -> -52000 | E96: =IF(Опер_мес>0,S96,"") -> -61712.62 | F96: =S96 -> -61712.62 | H96: =H94-ДДС!H13-ДДС!H14 -> -4000 | I96: =H96+I94-ДДС!I13-ДДС!I14 -> -10000 | J96: =I96+J94-ДДС!J13-ДДС!J14 -> -26000 | K96: =J96+K94-ДДС!K13-ДДС!K14 -> -52000 | L96: =K96+L94-ДДС!L13-ДДС!L14 -> -87806.94 | M96: =L96+M94-ДДС!M13-ДДС!M14 -> -117773.26 | N96: =M96+N94-ДДС!N13-ДДС!N14 -> -139603.28 | O96: =N96+O94-ДДС!O13-ДДС!O14 -> -152660.44 | P96: =O96+P94-ДДС!P13-ДДС!P14 -> -156477.08 | ... S96: =R96+S94-ДДС!S13-ДДС!S14 -> -61712.62
B97: Точка пересечения нуля, мес. (служебная) | C97: мес. | H97: =IF(H96>=0,0,"") | I97: =IF(AND(I96>=0,H96<0),(I$37-1)+(-H96)/(I96-H96),"") | J97: =IF(AND(J96>=0,I96<0),(J$37-1)+(-I96)/(J96-I96),"") | K97: =IF(AND(K96>=0,J96<0),(K$37-1)+(-J96)/(K96-J96),"") | L97: =IF(AND(L96>=0,K96<0),(L$37-1)+(-K96)/(L96-K96),"") | M97: =IF(AND(M96>=0,L96<0),(M$37-1)+(-L96)/(M96-L96),"") | N97: =IF(AND(N96>=0,M96<0),(N$37-1)+(-M96)/(N96-M96),"") | O97: =IF(AND(O96>=0,N96<0),(O$37-1)+(-N96)/(O96-N96),"") | P97: =IF(AND(P96>=0,O96<0),(P$37-1)+(-O96)/(P96-O96),"") | ... S97: =IF(AND(S96>=0,R96<0),(S$37-1)+(-R96)/(S96-R96),"")
B99: ="Сценарий «"&(Допущения!$H$80)&"»: MAU ×"&(FIXED(Допущения!$H$82,1))&", eCPM ×"&(FIXED(Допущения!$H$83,1))&", конверсия ×"&(FIXED(Допущения!$H$84,1))&", маркетинг "&(FIXED(Допущения!$H$85,0))&" ₽/мес" -> Сценарий «Пессимистичный + меры»: MAU ×0.6, eCPM ×1.0, конверсия ×1.0, маркетинг 20,000 ₽/мес
B100: MAU | C100: чел. | D100: =INDEX($H$100:$S$100,1,Дев_мес) -> 0 | E100: =IF(Опер_мес>0,S100,"") -> 12000 | F100: =S100 -> 12000 | H100: =Выручка!H12*Допущения!$H$82 -> 0 | I100: =Выручка!I12*Допущения!$H$82 -> 0 | J100: =Выручка!J12*Допущения!$H$82 -> 0 | K100: =Выручка!K12*Допущения!$H$82 -> 0 | L100: =Выручка!L12*Допущения!$H$82 -> 900 | M100: =Выручка!M12*Допущения!$H$82 -> 1800 | N100: =Выручка!N12*Допущения!$H$82 -> 3000 | O100: =Выручка!O12*Допущения!$H$82 -> 4200 | ... S100: =Выручка!S12*Допущения!$H$82 -> 12000
B101: Доход от рекламы | C101: ₽ | D101: =SUMIF($H$39:$S$39,"Разработка",$H$101:$S$101) -> 0 | E101: =SUMIF($H$39:$S$39,"Операционка",$H$101:$S$101) -> 218590.65 | F101: =SUM($H$101:$S$101) -> 218590.65 | H101: =H100*(Выручка!H41+Выручка!H42)*Допущения!$H$83 -> 0 | I101: =I100*(Выручка!I41+Выручка!I42)*Допущения!$H$83 -> 0 | J101: =J100*(Выручка!J41+Выручка!J42)*Допущения!$H$83 -> 0 | K101: =K100*(Выручка!K41+Выручка!K42)*Допущения!$H$83 -> 0 | L101: =L100*(Выручка!L41+Выручка!L42)*Допущения!$H$83 -> 4232.25 | M101: =M100*(Выручка!M41+Выручка!M42)*Допущения!$H$83 -> 8529.3 | N101: =N100*(Выручка!N41+Выручка!N42)*Допущения!$H$83 -> 14431.5 | O101: =O100*(Выручка!O41+Выручка!O42)*Допущения!$H$83 -> 20506.5 | ... S101: =S100*(Выручка!S41+Выручка!S42)*Допущения!$H$83 -> 60750
B102: Доход от IAP | C102: ₽ | D102: =SUMIF($H$39:$S$39,"Разработка",$H$102:$S$102) -> 0 | E102: =SUMIF($H$39:$S$39,"Операционка",$H$102:$S$102) -> 148808.8 | F102: =SUM($H$102:$S$102) -> 148808.8 | H102: =ROUND(H100*(Выручка!H43*Допущения!$H$84),0)*Выручка!H30 -> 0 | I102: =ROUND(I100*(Выручка!I43*Допущения!$H$84),0)*Выручка!I30 -> 0 | J102: =ROUND(J100*(Выручка!J43*Допущения!$H$84),0)*Выручка!J30 -> 0 | K102: =ROUND(K100*(Выручка!K43*Допущения!$H$84),0)*Выручка!K30 -> 0 | L102: =ROUND(L100*(Выручка!L43*Допущения!$H$84),0)*Выручка!L30 -> 1773.6 | M102: =ROUND(M100*(Выручка!M43*Допущения!$H$84),0)*Выручка!M30 -> 4232.8 | N102: =ROUND(N100*(Выручка!N43*Допущения!$H$84),0)*Выручка!N30 -> 7718.8 | O102: =ROUND(O100*(Выручка!O43*Допущения!$H$84),0)*Выручка!O30 -> 11750.4 | ... S102: =ROUND(S100*(Выручка!S43*Допущения!$H$84),0)*Выручка!S30 -> 47472
B103: Выручка | C103: ₽ | D103: =SUMIF($H$39:$S$39,"Разработка",$H$103:$S$103) -> 0 | E103: =SUMIF($H$39:$S$39,"Операционка",$H$103:$S$103) -> 367399.45 | F103: =SUM($H$103:$S$103) -> 367399.45 | H103: =H101+H102 -> 0 | I103: =I101+I102 -> 0 | J103: =J101+J102 -> 0 | K103: =K101+K102 -> 0 | L103: =L101+L102 -> 6005.85 | M103: =M101+M102 -> 12762.1 | N103: =N101+N102 -> 22150.3 | O103: =O101+O102 -> 32256.9 | ... S103: =S101+S102 -> 108222
B104: Комиссия магазина | C104: ₽ | D104: =SUMIF($H$39:$S$39,"Разработка",$H$104:$S$104) -> 0 | E104: =SUMIF($H$39:$S$39,"Операционка",$H$104:$S$104) -> 22321.32 | F104: =SUM($H$104:$S$104) -> 22321.32 | H104: =H102*Комиссия_стора -> 0 | I104: =I102*Комиссия_стора -> 0 | J104: =J102*Комиссия_стора -> 0 | K104: =K102*Комиссия_стора -> 0 | L104: =L102*Комиссия_стора -> 266.04 | M104: =M102*Комиссия_стора -> 634.92 | N104: =N102*Комиссия_стора -> 1157.82 | O104: =O102*Комиссия_стора -> 1762.56 | ... S104: =S102*Комиссия_стора -> 7120.8
B105: Операционные расходы | C105: ₽ | D105: =SUMIF($H$39:$S$39,"Разработка",$H$105:$S$105) -> 52000 | E105: =SUMIF($H$39:$S$39,"Операционка",$H$105:$S$105) -> 314790.75 | F105: =SUM($H$105:$S$105) -> 366790.75 | H105: =(Расходы!H12-Энергия!H39+H100*Энергия!H40)+Расходы!H13+Расходы!H14+IF(H$39="Разработка",Расходы!H15,Допущения!$H$85) -> 4000 | I105: =(Расходы!I12-Энергия!I39+I100*Энергия!I40)+Расходы!I13+Расходы!I14+IF(I$39="Разработка",Расходы!I15,Допущения!$H$85) -> 6000 | J105: =(Расходы!J12-Энергия!J39+J100*Энергия!J40)+Расходы!J13+Расходы!J14+IF(J$39="Разработка",Расходы!J15,Допущения!$H$85) -> 16000 | K105: =(Расходы!K12-Энергия!K39+K100*Энергия!K40)+Расходы!K13+Расходы!K14+IF(K$39="Разработка",Расходы!K15,Допущения!$H$85) -> 26000 | L105: =(Расходы!L12-Энергия!L39+L100*Энергия!L40)+Расходы!L13+Расходы!L14+IF(L$39="Разработка",Расходы!L15,Допущения!$H$85) -> 36546.75 | M105: =(Расходы!M12-Энергия!M39+M100*Энергия!M40)+Расходы!M13+Расходы!M14+IF(M$39="Разработка",Расходы!M15,Допущения!$H$85) -> 37093.5 | N105: =(Расходы!N12-Энергия!N39+N100*Энергия!N40)+Расходы!N13+Расходы!N14+IF(N$39="Разработка",Расходы!N15,Допущения!$H$85) -> 37822.5 | O105: =(Расходы!O12-Энергия!O39+O100*Энергия!O40)+Расходы!O13+Расходы!O14+IF(O$39="Разработка",Расходы!O15,Допущения!$H$85) -> 38551.5 | ... S105: =(Расходы!S12-Энергия!S39+S100*Энергия!S40)+Расходы!S13+Расходы!S14+IF(S$39="Разработка",Расходы!S15,Допущения!$H$85) -> 43290
B106: EBITDA | C106: ₽ | D106: =SUMIF($H$39:$S$39,"Разработка",$H$106:$S$106) -> -52000 | E106: =SUMIF($H$39:$S$39,"Операционка",$H$106:$S$106) -> 30287.38 | F106: =SUM($H$106:$S$106) -> -21712.62 | H106: =H103-H104-H105 -> -4000 | I106: =I103-I104-I105 -> -6000 | J106: =J103-J104-J105 -> -16000 | K106: =K103-K104-K105 -> -26000 | L106: =L103-L104-L105 -> -30806.94 | M106: =M103-M104-M105 -> -24966.32 | N106: =N103-N104-N105 -> -16830.02 | O106: =O103-O104-O105 -> -8057.16 | ... S106: =S103-S104-S105 -> 57811.2
B107: Проценты по кредиту | C107: ₽ | D107: =SUMIF($H$39:$S$39,"Разработка",$H$107:$S$107) -> 0 | E107: =SUMIF($H$39:$S$39,"Операционка",$H$107:$S$107) -> 0 | F107: =SUM($H$107:$S$107) -> 0 | H107: =0 -> 0 | I107: =0 -> 0 | J107: =0 -> 0 | K107: =0 -> 0 | L107: =0 -> 0 | M107: =0 -> 0 | N107: =0 -> 0 | O107: =0 -> 0 | ... S107: =0 -> 0
B108: Поступления выручки с начала года (база УСН) | C108: ₽ | D108: =INDEX($H$108:$S$108,1,Дев_мес) -> 0 | E108: =IF(Опер_мес>0,S108,"") -> 367399.45 | F108: =S108 -> 367399.45 | H108: =IF(H$37-Лаг_выручки>=1,INDEX($H103:$S103,1,H$37-Лаг_выручки),0) -> 0 | I108: =IF(YEAR(I$38)=YEAR(H$38),H108,0)+IF(I$37-Лаг_выручки>=1,INDEX($H103:$S103,1,I$37-Лаг_выручки),0) -> 0 | J108: =IF(YEAR(J$38)=YEAR(I$38),I108,0)+IF(J$37-Лаг_выручки>=1,INDEX($H103:$S103,1,J$37-Лаг_выручки),0) -> 0 | K108: =IF(YEAR(K$38)=YEAR(J$38),J108,0)+IF(K$37-Лаг_выручки>=1,INDEX($H103:$S103,1,K$37-Лаг_выручки),0) -> 0 | L108: =IF(YEAR(L$38)=YEAR(K$38),K108,0)+IF(L$37-Лаг_выручки>=1,INDEX($H103:$S103,1,L$37-Лаг_выручки),0) -> 6005.85 | M108: =IF(YEAR(M$38)=YEAR(L$38),L108,0)+IF(M$37-Лаг_выручки>=1,INDEX($H103:$S103,1,M$37-Лаг_выручки),0) -> 18767.95 | N108: =IF(YEAR(N$38)=YEAR(M$38),M108,0)+IF(N$37-Лаг_выручки>=1,INDEX($H103:$S103,1,N$37-Лаг_выручки),0) -> 40918.25 | O108: =IF(YEAR(O$38)=YEAR(N$38),N108,0)+IF(O$37-Лаг_выручки>=1,INDEX($H103:$S103,1,O$37-Лаг_выручки),0) -> 73175.15 | P108: =IF(YEAR(P$38)=YEAR(O$38),O108,0)+IF(P$37-Лаг_выручки>=1,INDEX($H103:$S103,1,P$37-Лаг_выручки),0) -> 116092.65 | ... S108: =IF(YEAR(S$38)=YEAR(R$38),R108,0)+IF(S$37-Лаг_выручки>=1,INDEX($H103:$S103,1,S$37-Лаг_выручки),0) -> 367399.45
B109: Налог к уплате с начала года | C109: ₽ | D109: =INDEX($H$109:$S$109,1,Дев_мес) -> 0 | E109: =IF(Опер_мес>0,S109,"") -> 0 | F109: =S109 -> 0 | H109: =MAX(0,Ставка_УСН*H108-MIN(Взносы_вычет,Лимит_вычета*Ставка_УСН*H108)) -> 0 | I109: =MAX(0,Ставка_УСН*I108-MIN(Взносы_вычет,Лимит_вычета*Ставка_УСН*I108)) -> 0 | J109: =MAX(0,Ставка_УСН*J108-MIN(Взносы_вычет,Лимит_вычета*Ставка_УСН*J108)) -> 0 | K109: =MAX(0,Ставка_УСН*K108-MIN(Взносы_вычет,Лимит_вычета*Ставка_УСН*K108)) -> 0 | L109: =MAX(0,Ставка_УСН*L108-MIN(Взносы_вычет,Лимит_вычета*Ставка_УСН*L108)) -> 0 | M109: =MAX(0,Ставка_УСН*M108-MIN(Взносы_вычет,Лимит_вычета*Ставка_УСН*M108)) -> 0 | N109: =MAX(0,Ставка_УСН*N108-MIN(Взносы_вычет,Лимит_вычета*Ставка_УСН*N108)) -> 0 | O109: =MAX(0,Ставка_УСН*O108-MIN(Взносы_вычет,Лимит_вычета*Ставка_УСН*O108)) -> 0 | ... S109: =MAX(0,Ставка_УСН*S108-MIN(Взносы_вычет,Лимит_вычета*Ставка_УСН*S108)) -> 0
B110: Налог (УСН) | C110: ₽ | D110: =SUMIF($H$39:$S$39,"Разработка",$H$110:$S$110) -> 0 | E110: =SUMIF($H$39:$S$39,"Операционка",$H$110:$S$110) -> 0 | F110: =SUM($H$110:$S$110) -> 0 | H110: =H109 -> 0 | I110: =I109-IF(YEAR(I$38)=YEAR(H$38),H109,0) -> 0 | J110: =J109-IF(YEAR(J$38)=YEAR(I$38),I109,0) -> 0 | K110: =K109-IF(YEAR(K$38)=YEAR(J$38),J109,0) -> 0 | L110: =L109-IF(YEAR(L$38)=YEAR(K$38),K109,0) -> 0 | M110: =M109-IF(YEAR(M$38)=YEAR(L$38),L109,0) -> 0 | N110: =N109-IF(YEAR(N$38)=YEAR(M$38),M109,0) -> 0 | O110: =O109-IF(YEAR(O$38)=YEAR(N$38),N109,0) -> 0 | P110: =P109-IF(YEAR(P$38)=YEAR(O$38),O109,0) -> 0 | ... S110: =S109-IF(YEAR(S$38)=YEAR(R$38),R109,0) -> 0
B111: Чистая прибыль | C111: ₽ | D111: =SUMIF($H$39:$S$39,"Разработка",$H$111:$S$111) -> -52000 | E111: =SUMIF($H$39:$S$39,"Операционка",$H$111:$S$111) -> 30287.38 | F111: =SUM($H$111:$S$111) -> -21712.62 | H111: =H106-H107-H110 -> -4000 | I111: =I106-I107-I110 -> -6000 | J111: =J106-J107-J110 -> -16000 | K111: =K106-K107-K110 -> -26000 | L111: =L106-L107-L110 -> -30806.94 | M111: =M106-M107-M110 -> -24966.32 | N111: =N106-N107-N110 -> -16830.02 | O111: =O106-O107-O110 -> -8057.16 | ... S111: =S106-S107-S110 -> 57811.2
B112: Поступления выручки на счёт (с лагом, за вычетом комиссии) | C112: ₽ | D112: =SUMIF($H$39:$S$39,"Разработка",$H$112:$S$112) -> 0 | E112: =SUMIF($H$39:$S$39,"Операционка",$H$112:$S$112) -> 345078.13 | F112: =SUM($H$112:$S$112) -> 345078.13 | H112: =IF(H$37-Лаг_выручки>=1,INDEX($H103:$S103,1,H$37-Лаг_выручки)-INDEX($H104:$S104,1,H$37-Лаг_выручки),0) -> 0 | I112: =IF(I$37-Лаг_выручки>=1,INDEX($H103:$S103,1,I$37-Лаг_выручки)-INDEX($H104:$S104,1,I$37-Лаг_выручки),0) -> 0 | J112: =IF(J$37-Лаг_выручки>=1,INDEX($H103:$S103,1,J$37-Лаг_выручки)-INDEX($H104:$S104,1,J$37-Лаг_выручки),0) -> 0 | K112: =IF(K$37-Лаг_выручки>=1,INDEX($H103:$S103,1,K$37-Лаг_выручки)-INDEX($H104:$S104,1,K$37-Лаг_выручки),0) -> 0 | L112: =IF(L$37-Лаг_выручки>=1,INDEX($H103:$S103,1,L$37-Лаг_выручки)-INDEX($H104:$S104,1,L$37-Лаг_выручки),0) -> 5739.81 | M112: =IF(M$37-Лаг_выручки>=1,INDEX($H103:$S103,1,M$37-Лаг_выручки)-INDEX($H104:$S104,1,M$37-Лаг_выручки),0) -> 12127.18 | N112: =IF(N$37-Лаг_выручки>=1,INDEX($H103:$S103,1,N$37-Лаг_выручки)-INDEX($H104:$S104,1,N$37-Лаг_выручки),0) -> 20992.48 | O112: =IF(O$37-Лаг_выручки>=1,INDEX($H103:$S103,1,O$37-Лаг_выручки)-INDEX($H104:$S104,1,O$37-Лаг_выручки),0) -> 30494.34 | ... S112: =IF(S$37-Лаг_выручки>=1,INDEX($H103:$S103,1,S$37-Лаг_выручки)-INDEX($H104:$S104,1,S$37-Лаг_выручки),0) -> 101101.2
B113: Чистый денежный поток | C113: ₽ | D113: =SUMIF($H$39:$S$39,"Разработка",$H$113:$S$113) -> 148000 | E113: =SUMIF($H$39:$S$39,"Операционка",$H$113:$S$113) -> 30287.38 | F113: =SUM($H$113:$S$113) -> 178287.38 | H113: =H112-H105-H110-H107+ДДС!H13 -> 196000 | I113: =I112-I105-I110-I107+ДДС!I13 -> -6000 | J113: =J112-J105-J110-J107+ДДС!J13 -> -16000 | K113: =K112-K105-K110-K107+ДДС!K13 -> -26000 | L113: =L112-L105-L110-L107+ДДС!L13 -> -30806.94 | M113: =M112-M105-M110-M107+ДДС!M13 -> -24966.32 | N113: =N112-N105-N110-N107+ДДС!N13 -> -16830.02 | O113: =O112-O105-O110-O107+ДДС!O13 -> -8057.16 | ... S113: =S112-S105-S110-S107+ДДС!S13 -> 57811.2
...

Sheet Показатели
B2: Ключевые показатели и эффективность инвестиций
B3: ="Активный сценарий: «"&Сценарий&"». Все значения считаются формулами из листов модели." -> Активный сценарий: «Базовый». Все значения считаются формулами из листов модели.
B5: 1. Ключевые показатели (docx, раздел 11.1)
B6: Показатель | C6: Ед. | D6: Значение | E6: Комментарий
B7: Выручка за 12 мес. | C7: ₽ | D7: =ОПиУ!$F$15 -> 612516.15 | E7: docx: 984 227 ₽
B8: EBITDA | C8: ₽ | D8: =ОПиУ!$F$26 -> 110635.14 | E8: docx: 420 227 ₽
B9: Чистая прибыль | C9: ₽ | D9: =ОПиУ!$F$31 -> 110635.14 | E9: docx: 383 625 ₽
B10: Рентабельность по EBITDA | C10: % | D10: =IFERROR(ОПиУ!$F$26/ОПиУ!$F$15,0) -> 0.18062404
B11: Рентабельность по чистой прибыли | C11: % | D11: =IFERROR(ОПиУ!$F$31/ОПиУ!$F$15,0) -> 0.18062404 | E11: docx: 38,9%
B12: ROI на собственный капитал | C12: % | D12: =IFERROR(ОПиУ!$F$31/Собств_капитал,0) -> 0.5531757 | E12: docx: 192%
B13: Рентабельность всех вложений (собственные + кредит) | C13: % | D13: =IFERROR(ОПиУ!$F$31/Финансирование,0) -> 0.5531757
B14: Денежные средства на конец горизонта | C14: ₽ | D14: =ДДС!$S$27 -> 310635.14 | E14: docx: 583 625 ₽
B15: Минимальный остаток денежных средств | C15: ₽ | D15: =MIN(ДДС!$H$27:$S$27) -> 69242.96 | E15: месяц: | F15: =INDEX(ДДС!$H$5:$S$5,1,MATCH(MIN(ДДС!$H$27:$S$27),ДДС!$H$27:$S$27,0)) -> Мар 2027
B16: Кассовый разрыв | D16: =IF(MIN(ДДС!$H$27:$S$27)<0,"есть: не хватает "&FIXED(-MIN(ДДС!$H$27:$S$27),0)&" ₽","нет") -> нет
B17: Точка безубыточности (EBITDA = 0) | C17: MAU | D17: =BEP_MAU -> 6236.4282 | E17: docx: 5 428 MAU
B18: Первый месяц с EBITDA ≥ 0 | D18: =BEP_месяц -> Апр 2027 | E18: docx: март 2027
B19: Окупаемость вложений команды | C19: мес. | D19: =PP_docx -> 10.996171 | E19: docx: 12 и 11 мес. | F19: =PP_docx_мес -> Июл 2027
B20: Срок окупаемости проекта (поток до финансирования) | C20: мес. | D20: =PP_проект -> 10.996171 | F20: =PP_проект_мес -> Июл 2027
B21: Дисконтированный срок окупаемости | C21: мес. | D21: =PP_дисконт -> 11.118418
B22: Накопленная прибыль в плюсе (капитал команды восстановлен) | C22: мес. | D22: =PP_прибыль -> 10.996171 | F22: =PP_прибыль_мес -> Июл 2027
B23: ЧДД (NPV) проекта | C23: ₽ | D23: =ЧДД -> 79741.265
B24: ВНД (IRR) проекта | C24: % год. | D24: =ВНД -> 2.1072868
B25: Индекс доходности (PI) | C25: x | D25: =ИД_доходности -> 1.6592957
B26: Долговая нагрузка: кредит / EBITDA | C26: x | D26: =Debt_EBITDA -> 0 | E26: docx: 0,48
B27: DSCR за период погашения | C27: x | D27: =DSCR_период -> н/д
B28: LTV / CAC | C28: x | D28: =LTV_CAC -> 3.2 | E28: docx: 3,2
B31: 2. Точка безубыточности (docx, раздел 8)
B32: 2.1. Постоянные расходы в месяц после релиза
B33: Поддержка серверов и хостинг | C33: ₽/мес | D33: =Серверы_опер -> 2000
B34: Бухгалтерия и юр. сопровождение | C34: ₽/мес | D34: =Бух_опер -> 10000
B35: Маркетинг и реклама (по сценарию) | C35: ₽/мес | D35: =Сц_маркетинг -> 30000
B36: Затраты на ИИ-сервисы после релиза | C36: ₽/мес | D36: =Зп_опер -> 4000
B37: Итого постоянные расходы | C37: ₽/мес | D37: =SUM(D33:D36) -> 46000 | E37: docx: 52 000 ₽/мес
B39: 2.2. Доход с 1 пользователя в месяц (средние параметры за месяцы после релиза, метод docx)
B40: Interstitial | C40: ₽/MAU | D40: =DAU_MAU*Int_доля*Int_показов*Дней_в_месяце*Int_eCPM*Сц_eCPM/1000 -> 1.8225 | E40: ="DAU/MAU "&(FIXED((DAU_MAU)*100,0)&"%")&" × "&(FIXED((Int_доля)*100,0)&"%")&" × "&(FIXED(Int_показов,1))&" показ × "&(FIXED(Дней_в_месяце,0))&" дн. × eCPM "&(FIXED(Int_eCPM*Сц_eCPM,0))&" ₽ / 1000. docx: 3,00 ₽" -> DAU/MAU 30% × 90% × 1.5 показ × 30 дн. × eCPM 150 ₽ / 1000. docx: 3,00 ₽
B41: Rewarded | C41: ₽/MAU | D41: =DAU_MAU*Выручка!$E$22*Rew_просмотров*Дней_в_месяце*Rew_eCPM*Сц_eCPM/1000 -> 3.06 | E41: ="средняя доля смотрящих "&(FIXED((Выручка!$E$22)*100,1)&"%")&" × "&(FIXED(Rew_просмотров,1))&" просм. × "&(FIXED(Дней_в_месяце,0))&" дн. × eCPM "&(FIXED(Rew_eCPM*Сц_eCPM,0))&" ₽ / 1000 (с учётом DAU/MAU). docx: 5,40 ₽" -> средняя доля смотрящих 85.0% × 2.0 просм. × 30 дн. × eCPM 200 ₽ / 1000 (с учётом DAU/MAU). docx: 5,40 ₽
B42: IAP (за вычетом комиссии магазина) | C42: ₽/MAU | D42: =Выручка!$E$28*Выручка!$E$30*(1-Комиссия_стора) -> 2.493517 | E42: ="средняя конверсия "&(FIXED(Выручка!$E$28*100,3)&"%")&" × средний чек "&(FIXED(Выручка!$E$30,0))&" ₽. docx брал округлённые 0,85% × 139 ₽ = 1,18 ₽" -> средняя конверсия 0.834% × средний чек 352 ₽. docx брал округлённые 0,85% × 139 ₽ = 1,18 ₽
B43: Итого доход с 1 пользователя | C43: ₽/MAU | D43: =D40+D41+D42 -> 7.376017 | E43: docx: 9,58 ₽/мес
B45: 2.3. Точка безубыточности
B46: Точка безубыточности (EBITDA = 0) | C46: MAU | D46: =IFERROR(Пост_расходы/ARPU_ср,0) -> 6236.4282 | E46: docx: 52 000 / 9,58 = 5 428 MAU
B47: То же с учётом средних процентов по кредиту после релиза | C47: MAU | D47: =IFERROR(Пост_расходы/ARPU_ср,0) -> 6236.4282 | E47: Проценты не зависят от MAU, поэтому в docx их не включали
B48: Первый месяц с EBITDA ≥ 0 | D48: =IFERROR(INDEX($H$98:$S$98,1,MATCH(1,$H$114:$S$114,0)),"не достигнут") -> Апр 2027 | E48: docx: март 2027 (7-й месяц проекта, 3-й после релиза)
B49: MAU в этом месяце | C49: чел. | D49: =IFERROR(INDEX($H$105:$S$105,1,MATCH(1,$H$114:$S$114,0)),0) -> 7000 | E49: docx: 7 000
B51: 2.4. Проверка для первого прибыльного месяца (docx, раздел 8.6)
B52: Выручка | C52: ₽ | D52: =IFERROR(INDEX($H$106:$S$106,1,MATCH(1,$H$114:$S$114,0)),0) -> 53531.1 | E52: docx: 62 745 ₽
B53: Операционные расходы | C53: ₽ | D53: =IFERROR(INDEX($H$108:$S$108,1,MATCH(1,$H$114:$S$114,0)),0) -> 50252.5 | E53: docx: 52 000 ₽
B54: Проценты по кредиту | C54: ₽ | D54: =0 -> 0 | E54: docx: 2 799 ₽
B55: Прибыль до налога | C55: ₽ | D55: =IFERROR(INDEX($H$109:$S$109,1,MATCH(1,$H$114:$S$114,0)),0)-D54 -> 375.56 | E55: docx: 7 946 ₽
B57: 3. Окупаемость и эффективность инвестиций (docx, раздел 9)
B58: Вложения команды (собственный капитал) | C58: ₽ | D58: =Финансирование -> 200000 | E58: docx: 400 000 ₽
B59: Срок окупаемости вложений команды | C59: мес. | D59: =IF(COUNT($H$120:$S$120)=0,"за горизонтом",MIN($H$120:$S$120)) -> 10.996171 | E59: =IF(ISNUMBER(D59),INDEX($H$98:$S$98,1,MAX(1,ROUNDUP(D59,0))),"за горизонтом") -> Июл 2027 | F59: поток без привлечённых денег выходит в плюс. Это и есть окупаемость вложений команды.
B60: Остаток кредита на конец месяца окупаемости | C60: ₽ | D60: =0 -> 0 | E60: 0 = к этому месяцу кредит погашен полностью
B61: Срок окупаемости проекта (поток до финансирования) | C61: мес. | D61: =IF(COUNT($H$123:$S$123)=0,"за горизонтом",MIN($H$123:$S$123)) -> 10.996171 | E61: =IF(ISNUMBER(D61),INDEX($H$98:$S$98,1,MAX(1,ROUNDUP(D61,0))),"за горизонтом") -> Июл 2027 | F61: операционный поток покрывает расходы периода разработки
B62: Дисконтированный срок окупаемости проекта | C62: мес. | D62: =IF(COUNT($H$127:$S$127)=0,"за горизонтом",MIN($H$127:$S$127)) -> 11.118418 | E62: =IF(ISNUMBER(D62),INDEX($H$98:$S$98,1,MAX(1,ROUNDUP(D62,0))),"за горизонтом") -> Авг 2027 | F62: ="ставка дисконтирования "&(FIXED((Ставка_дисконта)*100,0)&"%")&" годовых" -> ставка дисконтирования 22% годовых
B63: Накопленная чистая прибыль выходит в плюс (капитал команды восстановлен) | C63: мес. | D63: =IF(COUNT($H$130:$S$130)=0,"за горизонтом",MIN($H$130:$S$130)) -> 10.996171 | E63: =IF(ISNUMBER(D63),INDEX($H$98:$S$98,1,MAX(1,ROUNDUP(D63,0))),"за горизонтом") -> Июл 2027 | F63: прибыль перекрыла убытки периода разработки: активы за вычетом долга снова не меньше вложений команды
B64: ="ЧДД (NPV) проекта за 12 мес. при ставке "&FIXED(Ставка_дисконта*100,0)&"% годовых" -> ЧДД (NPV) проекта за 12 мес. при ставке 22% годовых | C64: ₽ | D64: =SUM($H$125:$S$125) -> 79741.265 | E64: без остаточной стоимости после 12-го месяца (консервативно)
B65: ВНД (IRR) проекта, в пересчёте на год | C65: % год. | D65: =IFERROR((1+IRR($H$121:$S$121))^12-1,"н/д") -> 2.1072868 | E65: очень высокая, потому что вложения малы и окупаются внутри года; для защиты надёжнее ЧДД и срок окупаемости
B66: Индекс доходности (PI) | C66: x | D66: =IFERROR(SUMIF($H$125:$S$125,">0")/-SUMIF($H$125:$S$125,"<0"),"н/д") -> 1.6592957 | E66: дисконтированные притоки / дисконтированные оттоки
B68: 4. Юнит-экономика, долговая нагрузка и альтернативы
B69: ARPU: выручка на 1 MAU в месяц (среднее за период) | C69: ₽ | D69: =Выручка!$F$38 -> 8.3335531 | E69: выручка / сумма MAU по месяцам
B70: ARPPU: средний чек плательщика | C70: ₽ | D70: =IFERROR(Выручка!$F$31/Выручка!$F$29,0) -> 373.79277
B71: CAC: стоимость привлечения | C71: ₽ | D71: =Юнит_CAC -> 25 | E71: docx: 20-25 ₽
B72: LTV: доход с пользователя за жизнь | C72: ₽ | D72: =Юнит_LTV -> 80 | E72: docx: ~80 ₽ (задан, не рассчитан)
B73: LTV / CAC | C73: x | D73: =IFERROR(Юнит_LTV/Юнит_CAC,0) -> 3.2 | E73: docx: 3,2
B74: Подразумеваемый срок жизни пользователя (LTV / ARPU) | C74: мес. | D74: =IFERROR(Юнит_LTV/D69,0) -> 9.5997469 | E74: проверьте по данным удержания после релиза
B75: Платных установок в месяц после релиза (маркетинг / CAC) | C75: шт. | D75: =IFERROR(Сц_маркетинг/Юнит_CAC,0) -> 1200 | E75: docx: ~1 600 установок в месяц
B76: Долговая нагрузка: кредит / EBITDA за 12 мес. | C76: x | D76: =0 -> 0 | E76: docx: 0,48 (норма банков < 3,0)
B77: DSCR за период погашения (поток / платежи по кредиту) | C77: x | D77: ="н/д" -> н/д | E77: банки обычно хотят не ниже 1,2-1,3
B78: Минимальный месячный DSCR | C78: x | D78: =IF(COUNT($H$134:$S$134)=0,"н/д",MIN($H$134:$S$134)) -> н/д | E78: =IF(COUNT($H$134:$S$134)=0,"",INDEX($H$98:$S$98,1,MATCH(D78,$H$134:$S$134,0))) | F78: в первые месяцы после релиза платежи идут из денег на счёте, а не из потока
B80: Сравнение с альтернативами для собственных средств команды (docx, раздел 11.2)
B81: Вариант вложения | D81: Доход за год, ₽ | E81: Проект больше в
B82: ="Банковский депозит ("&FIXED(Ставка_депозита*100,0)&"% годовых)" -> Банковский депозит (14% годовых) | D82: =Собств_капитал*Ставка_депозита -> 28000 | E82: =IFERROR(ОПиУ!$F$31/D82,"") -> 3.951255
B83: ="Индекс Мосбиржи (~"&FIXED(Доходность_индекса*100,0)&"% годовых)" -> Индекс Мосбиржи (~15% годовых) | D83: =Собств_капитал*Доходность_индекса -> 30000 | E83: =IFERROR(ОПиУ!$F$31/D83,"") -> 3.687838
B84: ="Проект "&Проект&" (чистая прибыль, сценарий «"&Сценарий&"»)" -> Проект «Наследие» (чистая прибыль, сценарий «Базовый») | D84: =ОПиУ!$F$31 -> 110635.14
B85: docx: депозит 36 000 ₽ (в 10,7 раза меньше), индекс 30 000 ₽ (в 12,8 раза меньше). Корректнее сравнивать с учётом риска: депозит почти безрисковый, проект венчурный.
B87: Структура выручки
B88: Реклама | C88: ₽ | D88: =Выручка!$F$34 -> 364317.75 | E88: =IFERROR(D88/Выручка!$F$36,0) -> 0.59478881 | F88: docx: 842 408 ₽, 85,6%
B89: Внутриигровые покупки (IAP) | C89: ₽ | D89: =Выручка!$F$35 -> 248198.4 | E89: =IFERROR(D89/Выручка!$F$36,0) -> 0.40521119 | F89: docx: 141 819 ₽, 14,4%
B96: 5. Помесячная аналитика
B98: Показатель | C98: Ед. | D98: ="Разработка"&CHAR(10)&"("&Дев_мес&" мес.)" -> Разработка (4 мес.) | E98: ="Операционка"&CHAR(10)&"("&Опер_мес&" мес.)" -> Операционка (8 мес.) | F98: ="Итого"&CHAR(10)&"12 мес." -> Итого 12 мес. | H98: =Выручка!H$5 -> Сен 2026 | I98: =Выручка!I$5 -> Окт 2026 | J98: =Выручка!J$5 -> Ноя 2026 | K98: =Выручка!K$5 -> Дек 2026 | L98: =Выручка!L$5 -> Янв 2027 | M98: =Выручка!M$5 -> Фев 2027 | N98: =Выручка!N$5 -> Мар 2027 | O98: =Выручка!O$5 -> Апр 2027 | ... S98: =Выручка!S$5 -> Авг 2027
B99: № месяца проекта | H99: =Выручка!H$6 -> 1 | I99: =Выручка!I$6 -> 2 | J99: =Выручка!J$6 -> 3 | K99: =Выручка!K$6 -> 4 | L99: =Выручка!L$6 -> 5 | M99: =Выручка!M$6 -> 6 | N99: =Выручка!N$6 -> 7 | O99: =Выручка!O$6 -> 8 | ... S99: =Выручка!S$6 -> 12
B100: Дата (начало месяца) | H100: =Выручка!H$7 -> 46266 | I100: =Выручка!I$7 -> 46296 | J100: =Выручка!J$7 -> 46327 | K100: =Выручка!K$7 -> 46357 | L100: =Выручка!L$7 -> 46388 | M100: =Выручка!M$7 -> 46419 | N100: =Выручка!N$7 -> 46447 | O100: =Выручка!O$7 -> 46478 | ... S100: =Выручка!S$7 -> 46600
B101: Фаза | H101: =Выручка!H$8 -> Разработка | I101: =Выручка!I$8 -> Разработка | J101: =Выручка!J$8 -> Разработка | K101: =Выручка!K$8 -> Разработка | L101: =Выручка!L$8 -> Операционка | M101: =Выручка!M$8 -> Операционка | N101: =Выручка!N$8 -> Операционка | O101: =Выручка!O$8 -> Операционка | ... S101: =Выручка!S$8 -> Операционка
B102: Месяцев после релиза | H102: =Выручка!H$9 -> 0 | I102: =Выручка!I$9 -> 0 | J102: =Выручка!J$9 -> 0 | K102: =Выручка!K$9 -> 0 | L102: =Выручка!L$9 -> 1 | M102: =Выручка!M$9 -> 2 | N102: =Выручка!N$9 -> 3 | O102: =Выручка!O$9 -> 4 | ... S102: =Выручка!S$9 -> 8
B104: Безубыточность по месяцам (docx, раздел 8.5)
B105: MAU | C105: чел. | D105: =INDEX($H$105:$S$105,1,Дев_мес) -> 0 | E105: =IF(Опер_мес>0,S105,"") -> 20000 | F105: =S105 -> 20000 | H105: =Выручка!H13 -> 0 | I105: =Выручка!I13 -> 0 | J105: =Выручка!J13 -> 0 | K105: =Выручка!K13 -> 0 | L105: =Выручка!L13 -> 1500 | M105: =Выручка!M13 -> 3000 | N105: =Выручка!N13 -> 5000 | O105: =Выручка!O13 -> 7000 | ... S105: =Выручка!S13 -> 20000
B106: Выручка | C106: ₽ | D106: =SUMIF($H$101:$S$101,"Разработка",$H$106:$S$106) -> 0 | E106: =SUMIF($H$101:$S$101,"Операционка",$H$106:$S$106) -> 612516.15 | F106: =SUM($H$106:$S$106) -> 612516.15 | H106: =Выручка!H36 -> 0 | I106: =Выручка!I36 -> 0 | J106: =Выручка!J36 -> 0 | K106: =Выручка!K36 -> 0 | L106: =Выручка!L36 -> 10305.35 | M106: =Выручка!M36 -> 21378.7 | N106: =Выручка!N36 -> 36805.3 | O106: =Выручка!O36 -> 53531.1 | ... S106: =Выручка!S36 -> 180370
B107: Комиссия магазина | C107: ₽ | D107: =SUMIF($H$101:$S$101,"Разработка",$H$107:$S$107) -> 0 | E107: =SUMIF($H$101:$S$101,"Операционка",$H$107:$S$107) -> 37229.76 | F107: =SUM($H$107:$S$107) -> 37229.76 | H107: =Расходы!H19 -> 0 | I107: =Расходы!I19 -> 0 | J107: =Расходы!J19 -> 0 | K107: =Расходы!K19 -> 0 | L107: =Расходы!L19 -> 487.74 | M107: =Расходы!M19 -> 1074.48 | N107: =Расходы!N19 -> 1912.92 | O107: =Расходы!O19 -> 2903.04 | ... S107: =Расходы!S19 -> 11868
B108: Операционные расходы (OpEx) | C108: ₽ | D108: =SUMIF($H$101:$S$101,"Разработка",$H$108:$S$108) -> 52000 | E108: =SUMIF($H$101:$S$101,"Операционка",$H$108:$S$108) -> 412651.25 | F108: =SUM($H$108:$S$108) -> 464651.25 | H108: =Расходы!H16 -> 4000 | I108: =Расходы!I16 -> 6000 | J108: =Расходы!J16 -> 16000 | K108: =Расходы!K16 -> 26000 | L108: =Расходы!L16 -> 46911.25 | M108: =Расходы!M16 -> 47822.5 | N108: =Расходы!N16 -> 49037.5 | O108: =Расходы!O16 -> 50252.5 | ... S108: =Расходы!S16 -> 58150
B109: Результат: EBITDA | C109: ₽ | D109: =SUMIF($H$101:$S$101,"Разработка",$H$109:$S$109) -> -52000 | E109: =SUMIF($H$101:$S$101,"Операционка",$H$109:$S$109) -> 162635.14 | F109: =SUM($H$109:$S$109) -> 110635.14 | H109: =ОПиУ!H26 -> -4000 | I109: =ОПиУ!I26 -> -6000 | J109: =ОПиУ!J26 -> -16000 | K109: =ОПиУ!K26 -> -26000 | L109: =ОПиУ!L26 -> -37093.64 | M109: =ОПиУ!M26 -> -27518.28 | N109: =ОПиУ!N26 -> -14145.12 | O109: =ОПиУ!O26 -> 375.56 | ... S109: =ОПиУ!S26 -> 110352
B110: Статус месяца | H110: =IF(H$102=0,"разработка",IF(H109>=0,"прибыль","убыток")) -> разработка | I110: =IF(I$102=0,"разработка",IF(I109>=0,"прибыль","убыток")) -> разработка | J110: =IF(J$102=0,"разработка",IF(J109>=0,"прибыль","убыток")) -> разработка | K110: =IF(K$102=0,"разработка",IF(K109>=0,"прибыль","убыток")) -> разработка | L110: =IF(L$102=0,"разработка",IF(L109>=0,"прибыль","убыток")) -> убыток | M110: =IF(M$102=0,"разработка",IF(M109>=0,"прибыль","убыток")) -> убыток | N110: =IF(N$102=0,"разработка",IF(N109>=0,"прибыль","убыток")) -> убыток | O110: =IF(O$102=0,"разработка",IF(O109>=0,"прибыль","убыток")) -> прибыль | ... S110: =IF(S$102=0,"разработка",IF(S109>=0,"прибыль","убыток")) -> прибыль
B111: Чистый доход на 1 MAU (за вычетом комиссии) | C111: ₽ | H111: =IF(H105>0,(H106-H107)/H105,0) -> 0 | I111: =IF(I105>0,(I106-I107)/I105,0) -> 0 | J111: =IF(J105>0,(J106-J107)/J105,0) -> 0 | K111: =IF(K105>0,(K106-K107)/K105,0) -> 0 | L111: =IF(L105>0,(L106-L107)/L105,0) -> 6.5450733 | M111: =IF(M105>0,(M106-M107)/M105,0) -> 6.7680733 | N111: =IF(N105>0,(N106-N107)/N105,0) -> 6.978476 | O111: =IF(O105>0,(O106-O107)/O105,0) -> 7.23258 | ... S111: =IF(S105>0,(S106-S107)/S105,0) -> 8.4251
B112: MAU, нужный для безубыточности в этом месяце | C112: чел. | H112: =IF(AND(H$102>0,H111>0),H108/H111,0) -> 0 | I112: =IF(AND(I$102>0,I111>0),I108/I111,0) -> 0 | J112: =IF(AND(J$102>0,J111>0),J108/J111,0) -> 0 | K112: =IF(AND(K$102>0,K111>0),K108/K111,0) -> 0 | L112: =IF(AND(L$102>0,L111>0),L108/L111,0) -> 7167.414 | M112: =IF(AND(M$102>0,M111>0),M108/M111,0) -> 7065.8957 | N112: =IF(AND(N$102>0,N111>0),N108/N111,0) -> 7026.9641 | O112: =IF(AND(O$102>0,O111>0),O108/O111,0) -> 6948.0739 | ... S112: =IF(AND(S$102>0,S111>0),S108/S111,0) -> 6901.9952
B113: Запас прочности по MAU | C113: % | H113: =IF(AND(H$102>0,H105>0),(H105-H112)/H105,0) -> 0 | I113: =IF(AND(I$102>0,I105>0),(I105-I112)/I105,0) -> 0 | J113: =IF(AND(J$102>0,J105>0),(J105-J112)/J105,0) -> 0 | K113: =IF(AND(K$102>0,K105>0),(K105-K112)/K105,0) -> 0 | L113: =IF(AND(L$102>0,L105>0),(L105-L112)/L105,0) -> -3.778276 | M113: =IF(AND(M$102>0,M105>0),(M105-M112)/M105,0) -> -1.3552986 | N113: =IF(AND(N$102>0,N105>0),(N105-N112)/N105,0) -> -0.40539281 | O113: =IF(AND(O$102>0,O105>0),(O105-O112)/O105,0) -> 0.0074180208 | ... S113: =IF(AND(S$102>0,S105>0),(S105-S112)/S105,0) -> 0.65490024
B114: Флаг: EBITDA ≥ 0 после релиза | C114: 1/0 | H114: =IF(AND(H$102>0,H109>=0),1,0) -> 0 | I114: =IF(AND(I$102>0,I109>=0),1,0) -> 0 | J114: =IF(AND(J$102>0,J109>=0),1,0) -> 0 | K114: =IF(AND(K$102>0,K109>=0),1,0) -> 0 | L114: =IF(AND(L$102>0,L109>=0),1,0) -> 0 | M114: =IF(AND(M$102>0,M109>=0),1,0) -> 0 | N114: =IF(AND(N$102>0,N109>=0),1,0) -> 0 | O114: =IF(AND(O$102>0,O109>=0),1,0) -> 1 | ... S114: =IF(AND(S$102>0,S109>=0),1,0) -> 1
B116: Окупаемость (docx, раздел 9.2)
B117: Поток без привлечённого финансирования (метод docx) | C117: ₽ | D117: =SUMIF($H$101:$S$101,"Разработка",$H$117:$S$117) -> -52000 | E117: =SUMIF($H$101:$S$101,"Операционка",$H$117:$S$117) -> 162635.14 | F117: =SUM($H$117:$S$117) -> 110635.14 | H117: =ДДС!H33 -> -4000 | I117: =ДДС!I33 -> -6000 | J117: =ДДС!J33 -> -16000 | K117: =ДДС!K33 -> -26000 | L117: =ДДС!L33 -> -37093.64 | M117: =ДДС!M33 -> -27518.28 | N117: =ДДС!N33 -> -14145.12 | O117: =ДДС!O33 -> 375.56 | ... S117: =ДДС!S33 -> 110352
B118: Накопленный поток (метод docx) | C118: ₽ | D118: =INDEX($H$118:$S$118,1,Дев_мес) -> -52000 | E118: =IF(Опер_мес>0,S118,"") -> 110635.14 | F118: =S118 -> 110635.14 | H118: =ДДС!H34 -> -4000 | I118: =ДДС!I34 -> -10000 | J118: =ДДС!J34 -> -26000 | K118: =ДДС!K34 -> -52000 | L118: =ДДС!L34 -> -89093.64 | M118: =ДДС!M34 -> -116611.92 | N118: =ДДС!N34 -> -130757.04 | O118: =ДДС!O34 -> -130381.48 | ... S118: =ДДС!S34 -> 110635.14
B119: Статус | H119: =IF(H$101="Разработка","разработка",IF(H118>=0,"окупился",IF(H117>0,"поток в плюсе","поток в минусе"))) -> разработка | I119: =IF(I$101="Разработка","разработка",IF(I118>=0,"окупился",IF(I117>0,"поток в плюсе","поток в минусе"))) -> разработка | J119: =IF(J$101="Разработка","разработка",IF(J118>=0,"окупился",IF(J117>0,"поток в плюсе","поток в минусе"))) -> разработка | K119: =IF(K$101="Разработка","разработка",IF(K118>=0,"окупился",IF(K117>0,"поток в плюсе","поток в минусе"))) -> разработка | L119: =IF(L$101="Разработка","разработка",IF(L118>=0,"окупился",IF(L117>0,"поток в плюсе","поток в минусе"))) -> поток в минусе | M119: =IF(M$101="Разработка","разработка",IF(M118>=0,"окупился",IF(M117>0,"поток в плюсе","поток в минусе"))) -> поток в минусе | N119: =IF(N$101="Разработка","разработка",IF(N118>=0,"окупился",IF(N117>0,"поток в плюсе","поток в минусе"))) -> поток в минусе | O119: =IF(O$101="Разработка","разработка",IF(O118>=0,"окупился",IF(O117>0,"поток в плюсе","поток в минусе"))) -> поток в плюсе | ... S119: =IF(S$101="Разработка","разработка",IF(S118>=0,"окупился",IF(S117>0,"поток в плюсе","поток в минусе"))) -> окупился
B120: Точка пересечения нуля, мес. (служебная) | C120: мес. | H120: =IF(H118>=0,0,"") | I120: =IF(AND(I118>=0,H118<0),(I$99-1)+(-H118)/I117,"") | J120: =IF(AND(J118>=0,I118<0),(J$99-1)+(-I118)/J117,"") | K120: =IF(AND(K118>=0,J118<0),(K$99-1)+(-J118)/K117,"") | L120: =IF(AND(L118>=0,K118<0),(L$99-1)+(-K118)/L117,"") | M120: =IF(AND(M118>=0,L118<0),(M$99-1)+(-L118)/M117,"") | N120: =IF(AND(N118>=0,M118<0),(N$99-1)+(-M118)/N117,"") | O120: =IF(AND(O118>=0,N118<0),(O$99-1)+(-N118)/O117,"") | P120: =IF(AND(P118>=0,O118<0),(P$99-1)+(-O118)/P117,"") | ... S120: =IF(AND(S118>=0,R118<0),(S$99-1)+(-R118)/S117,"")
...

Sheet Чувствительность
B2: Анализ чувствительности
B3: ="Центр анализа: активный сценарий «"&Сценарий&"». Показатель: чистая прибыль за 12 мес. Каждый фактор меняется при прочих равных." -> Центр анализа: активный сценарий «Базовый». Показатель: чистая прибыль за 12 мес. Каждый фактор меняется при прочих равных.
B5: 1. Торнадо: какие допущения сильнее всего влияют на чистую прибыль
B6: Шаг изменения факторов | C6: 0.2 | D6: можно поменять, например 10% или 30%
B7: Фактор | C7: Значение в модели | D7: ="−"&FIXED(Шаг_чувств*100,0)&"%" -> −20% | E7: База | F7: ="+"&FIXED(Шаг_чувств*100,0)&"%" -> +20% | G7: Δ при −шаг | H7: Δ при +шаг | I7: Размах
B8: MAU (аудитория, все месяцы) | C8: =Выручка!$F$13 -> 20000 | D8: =Q85 -> 3907.74 | E8: =Q84 -> 110635.14 | F8: =Q86 -> 216247 | G8: =D8-E8 -> -106727.4 | H8: =F8-E8 -> 105611.86 | I8: =ABS(H8-G8) -> 212339.26
B9: eCPM Interstitial | C9: =Int_eCPM*Сц_eCPM -> 150 | D9: =Q87 -> 83844.39 | E9: =Q84 -> 110635.14 | F9: =Q88 -> 137425.89 | G9: =D9-E9 -> -26790.75 | H9: =F9-E9 -> 26790.75 | I9: =ABS(H9-G9) -> 53581.5
B10: eCPM Rewarded | C10: =Rew_eCPM*Сц_eCPM -> 200 | D10: =Q89 -> 64562.34 | E10: =Q84 -> 110635.14 | F10: =Q90 -> 156707.94 | G10: =D10-E10 -> -46072.8 | H10: =F10-E10 -> 46072.8 | I10: =ABS(H10-G10) -> 92145.6
B11: Конверсия в плательщиков (средняя) | C11: =Выручка!$E$28 -> 0.0083375 | D11: =Q91 -> 67841.04 | E11: =Q84 -> 110635.14 | F11: =Q92 -> 152313.7 | G11: =D11-E11 -> -42794.1 | H11: =F11-E11 -> 41678.56 | I11: =ABS(H11-G11) -> 84472.66
B12: Средний чек IAP (ARPPU, средний) | C12: =Выручка!$E$30 -> 351.85 | D12: =Q93 -> 68441.412 | E12: =Q84 -> 110635.14 | F12: =Q94 -> 152828.87 | G12: =D12-E12 -> -42193.728 | H12: =F12-E12 -> 42193.728 | I12: =ABS(H12-G12) -> 84387.456
B13: Маркетинг после релиза, ₽/мес | C13: =Сц_маркетинг -> 30000 | D13: =Q95 -> 158635.14 | E13: =Q84 -> 110635.14 | F13: =Q96 -> 62635.14 | G13: =D13-E13 -> 48000 | H13: =F13-E13 -> -48000 | I13: =ABS(H13-G13) -> 96000
B14: Бухгалтерия и юр. сопровождение, ₽/мес | C14: =Бух_опер -> 10000 | D14: =Q97 -> 128635.14 | E14: =Q84 -> 110635.14 | F14: =Q98 -> 92635.14 | G14: =D14-E14 -> 18000 | H14: =F14-E14 -> -18000 | I14: =ABS(H14-G14) -> 36000
B15: Δ: изменение чистой прибыли к базе. Чем больше размах, тем сильнее результат зависит от фактора.
B18: 2. Чистая прибыль при одновременном изменении MAU и eCPM
B19: Множители к активному сценарию. Строки: MAU; столбцы: eCPM обеих рекламных сетей.
B20: MAU (строки) × eCPM (столбцы) | C20: 0.6 | D20: 0.8 | E20: 1 | F20: 1.2 | G20: 1.4
B21: 0.6 | C21: =Q99 -> -189148.88 | D21: =Q100 -> -145430.75 | E21: =Q101 -> -101712.62 | F21: =Q102 -> -57994.49 | G21: =Q103 -> -14276.36
B22: 0.8 | C22: =Q104 -> -112673.94 | D22: =Q105 -> -54383.1 | E22: =Q106 -> 3907.74 | F22: =Q107 -> 62198.58 | G22: =Q108 -> 120489.42
B23: 1 | C23: =Q109 -> -35091.96 | D23: =Q110 -> 37771.59 | E23: =Q111 -> 110635.14 | F23: =Q112 -> 183498.69 | G23: =Q113 -> 256362.24
B24: 1.2 | C24: =Q114 -> 41374.48 | D24: =Q115 -> 128810.74 | E24: =Q116 -> 216247 | F24: =Q117 -> 303683.26 | G24: =Q118 -> 390562.37
B25: 1.4 | C25: =Q119 -> 118134.68 | D25: =Q120 -> 220143.65 | E25: =Q121 -> 322152.62 | F25: =Q122 -> 420641.69 | G25: =Q123 -> 516530.12
B26: Центральная ячейка (1,0x × 1,0x) равна чистой прибыли активного сценария. Красный цвет: убыток.
B28: 3. Главное допущение: сколько MAU реально видят рекламу каждый день (DAU/MAU)
B29: В docx каждый MAU заходит в игру все 30 дней (DAU/MAU = 100%). Ниже видно, что будет при более осторожной оценке. Значения в синих ячейках можно менять.
B30: DAU/MAU | C30: 1 | D30: 0.75 | E30: 0.5 | F30: 0.3 | G30: 0.2
B31: Выручка за 12 мес., ₽ | C31: =O124 -> 1462590.9 | D31: =O125 -> 1158992.8 | E31: =O126 -> 855394.65 | F31: =O127 -> 612516.15 | G31: =O128 -> 491076.9
B32: Чистая прибыль за 12 мес., ₽ | C32: =Q124 -> 822768.19 | D32: =Q125 -> 574595.32 | E32: =Q126 -> 323746.14 | F32: =Q127 -> 110635.14 | G32: =Q128 -> 4079.64
B33: Точка безубыточности, MAU | C33: =IFERROR(Пост_расходы/((ARPU_int+ARPU_rew)*IFERROR(C$30/DAU_MAU,0)+ARPU_iap),0) -> 2450.9129 | D33: =IFERROR(Пост_расходы/((ARPU_int+ARPU_rew)*IFERROR(D$30/DAU_MAU,0)+ARPU_iap),0) -> 3129.3013 | E33: =IFERROR(Пост_расходы/((ARPU_int+ARPU_rew)*IFERROR(E$30/DAU_MAU,0)+ARPU_iap),0) -> 4326.9614 | F33: =IFERROR(Пост_расходы/((ARPU_int+ARPU_rew)*IFERROR(F$30/DAU_MAU,0)+ARPU_iap),0) -> 6236.4282 | G33: =IFERROR(Пост_расходы/((ARPU_int+ARPU_rew)*IFERROR(G$30/DAU_MAU,0)+ARPU_iap),0) -> 8002.0639
B69: Расчётный блок (не редактировать): чистая прибыль при изменённых факторах; налог по поступлениям за каждый год
B70: Налоговый год 1 | D70: =YEAR(Дата_начала) -> 2026
B71: Налоговый год 2 | D71: =D70+1 -> 2027
B72: Interstitial, всего за 12 мес. | D72: =SUM(Выручка!$H$19:$S$19) -> 133953.75
B73: Rewarded, всего за 12 мес. | D73: =SUM(Выручка!$H$25:$S$25) -> 230364
B74: Interstitial, поступления в году 1 | D74: =SUMPRODUCT((YEAR(DATE(YEAR(Выручка!$H$7:$S$7),MONTH(Выручка!$H$7:$S$7)+Лаг_выручки,1))=D70)*(Выручка!$H$6:$S$6+Лаг_выручки<=12)*Выручка!$H$19:$S$19) -> 0
B75: Interstitial, поступления в году 2 | D75: =SUMPRODUCT((YEAR(DATE(YEAR(Выручка!$H$7:$S$7),MONTH(Выручка!$H$7:$S$7)+Лаг_выручки,1))=D71)*(Выручка!$H$6:$S$6+Лаг_выручки<=12)*Выручка!$H$19:$S$19) -> 133953.75
B76: Rewarded, поступления в году 1 | D76: =SUMPRODUCT((YEAR(DATE(YEAR(Выручка!$H$7:$S$7),MONTH(Выручка!$H$7:$S$7)+Лаг_выручки,1))=D70)*(Выручка!$H$6:$S$6+Лаг_выручки<=12)*Выручка!$H$25:$S$25) -> 0
B77: Rewarded, поступления в году 2 | D77: =SUMPRODUCT((YEAR(DATE(YEAR(Выручка!$H$7:$S$7),MONTH(Выручка!$H$7:$S$7)+Лаг_выручки,1))=D71)*(Выручка!$H$6:$S$6+Лаг_выручки<=12)*Выручка!$H$25:$S$25) -> 230364
B78: OpEx за 12 мес. | D78: =Расходы!$F$16 -> 464651.25
B79: Маркетинг после релиза за период | D79: =Расходы!$E$15 -> 240000
B80: Бухгалтерия и юр. за 12 мес. | D80: =Расходы!$F$14 -> 90000
B81: Проценты по кредиту за 12 мес. | D81: =0 -> 0
B83: Случай | C83: mMAU | D83: mINT | E83: mREW | F83: mCONV | G83: mARPPU | H83: ΔOpEx | I83: Реклама | J83: IAP | K83: Поступления г1 | L83: Поступления г2 | M83: Налог г1 | N83: Налог г2 | O83: Выручка | P83: Комиссия | Q83: Чистая прибыль
B84: База (все множители = 1) | C84: =1 -> 1 | D84: =1 -> 1 | E84: =1 -> 1 | F84: =1 -> 1 | G84: =1 -> 1 | H84: =0+(C84-1)*Энергия!$F$39 -> 0 | I84: =C84*(D84*$D$72+E84*$D$73) -> 364317.75 | J84: =G84*SUMPRODUCT(ROUND((Выручка!$H$13:$S$13*C84)*(Выручка!$H$28:$S$28*F84),0)*Выручка!$H$30:$S$30) -> 248198.4 | K84: =C84*(D84*$D$74+E84*$D$76)+G84*SUMPRODUCT((YEAR(DATE(YEAR(Выручка!$H$7:$S$7),MONTH(Выручка!$H$7:$S$7)+Лаг_выручки,1))=$D$70)*(Выручка!$H$6:$S$6+Лаг_выручки<=12)*ROUND((Выручка!$H$13:$S$13*C84)*(Выручка!$H$28:$S$28*F84),0)*Выручка!$H$30:$S$30) -> 0 | L84: =C84*(D84*$D$75+E84*$D$77)+G84*SUMPRODUCT((YEAR(DATE(YEAR(Выручка!$H$7:$S$7),MONTH(Выручка!$H$7:$S$7)+Лаг_выручки,1))=$D$71)*(Выручка!$H$6:$S$6+Лаг_выручки<=12)*ROUND((Выручка!$H$13:$S$13*C84)*(Выручка!$H$28:$S$28*F84),0)*Выручка!$H$30:$S$30) -> 612516.15 | M84: =MAX(0,Ставка_УСН*K84-MIN(Взносы_вычет,Лимит_вычета*Ставка_УСН*K84)) -> 0 | N84: =MAX(0,Ставка_УСН*L84-MIN(Взносы_вычет,Лимит_вычета*Ставка_УСН*L84)) -> 0 | O84: =I84+J84 -> 612516.15 | P84: =Комиссия_стора*J84 -> 37229.76 | Q84: =O84-P84-($D$78+H84)-$D$81-M84-N84 -> 110635.14
B85: MAU (аудитория, все месяцы) −шаг | C85: =1-Шаг_чувств -> 0.8 | D85: =1 -> 1 | E85: =1 -> 1 | F85: =1 -> 1 | G85: =1 -> 1 | H85: =0+(C85-1)*Энергия!$F$39 -> -8930.25 | I85: =C85*(D85*$D$72+E85*$D$73) -> 291454.2 | J85: =G85*SUMPRODUCT(ROUND((Выручка!$H$13:$S$13*C85)*(Выручка!$H$28:$S$28*F85),0)*Выручка!$H$30:$S$30) -> 197852.4 | K85: =C85*(D85*$D$74+E85*$D$76)+G85*SUMPRODUCT((YEAR(DATE(YEAR(Выручка!$H$7:$S$7),MONTH(Выручка!$H$7:$S$7)+Лаг_выручки,1))=$D$70)*(Выручка!$H$6:$S$6+Лаг_выручки<=12)*ROUND((Выручка!$H$13:$S$13*C85)*(Выручка!$H$28:$S$28*F85),0)*Выручка!$H$30:$S$30) -> 0 | L85: =C85*(D85*$D$75+E85*$D$77)+G85*SUMPRODUCT((YEAR(DATE(YEAR(Выручка!$H$7:$S$7),MONTH(Выручка!$H$7:$S$7)+Лаг_выручки,1))=$D$71)*(Выручка!$H$6:$S$6+Лаг_выручки<=12)*ROUND((Выручка!$H$13:$S$13*C85)*(Выручка!$H$28:$S$28*F85),0)*Выручка!$H$30:$S$30) -> 489306.6 | M85: =MAX(0,Ставка_УСН*K85-MIN(Взносы_вычет,Лимит_вычета*Ставка_УСН*K85)) -> 0 | N85: =MAX(0,Ставка_УСН*L85-MIN(Взносы_вычет,Лимит_вычета*Ставка_УСН*L85)) -> 0 | O85: =I85+J85 -> 489306.6 | P85: =Комиссия_стора*J85 -> 29677.86 | Q85: =O85-P85-($D$78+H85)-$D$81-M85-N85 -> 3907.74
B86: MAU (аудитория, все месяцы) +шаг | C86: =1+Шаг_чувств -> 1.2 | D86: =1 -> 1 | E86: =1 -> 1 | F86: =1 -> 1 | G86: =1 -> 1 | H86: =0+(C86-1)*Энергия!$F$39 -> 8930.25 | I86: =C86*(D86*$D$72+E86*$D$73) -> 437181.3 | J86: =G86*SUMPRODUCT(ROUND((Выручка!$H$13:$S$13*C86)*(Выручка!$H$28:$S$28*F86),0)*Выручка!$H$30:$S$30) -> 297232 | K86: =C86*(D86*$D$74+E86*$D$76)+G86*SUMPRODUCT((YEAR(DATE(YEAR(Выручка!$H$7:$S$7),MONTH(Выручка!$H$7:$S$7)+Лаг_выручки,1))=$D$70)*(Выручка!$H$6:$S$6+Лаг_выручки<=12)*ROUND((Выручка!$H$13:$S$13*C86)*(Выручка!$H$28:$S$28*F86),0)*Выручка!$H$30:$S$30) -> 0 | L86: =C86*(D86*$D$75+E86*$D$77)+G86*SUMPRODUCT((YEAR(DATE(YEAR(Выручка!$H$7:$S$7),MONTH(Выручка!$H$7:$S$7)+Лаг_выручки,1))=$D$71)*(Выручка!$H$6:$S$6+Лаг_выручки<=12)*ROUND((Выручка!$H$13:$S$13*C86)*(Выручка!$H$28:$S$28*F86),0)*Выручка!$H$30:$S$30) -> 734413.3 | M86: =MAX(0,Ставка_УСН*K86-MIN(Взносы_вычет,Лимит_вычета*Ставка_УСН*K86)) -> 0 | N86: =MAX(0,Ставка_УСН*L86-MIN(Взносы_вычет,Лимит_вычета*Ставка_УСН*L86)) -> 0 | O86: =I86+J86 -> 734413.3 | P86: =Комиссия_стора*J86 -> 44584.8 | Q86: =O86-P86-($D$78+H86)-$D$81-M86-N86 -> 216247
B87: eCPM Interstitial −шаг | C87: =1 -> 1 | D87: =1-Шаг_чувств -> 0.8 | E87: =1 -> 1 | F87: =1 -> 1 | G87: =1 -> 1 | H87: =0+(C87-1)*Энергия!$F$39 -> 0 | I87: =C87*(D87*$D$72+E87*$D$73) -> 337527 | J87: =G87*SUMPRODUCT(ROUND((Выручка!$H$13:$S$13*C87)*(Выручка!$H$28:$S$28*F87),0)*Выручка!$H$30:$S$30) -> 248198.4 | K87: =C87*(D87*$D$74+E87*$D$76)+G87*SUMPRODUCT((YEAR(DATE(YEAR(Выручка!$H$7:$S$7),MONTH(Выручка!$H$7:$S$7)+Лаг_выручки,1))=$D$70)*(Выручка!$H$6:$S$6+Лаг_выручки<=12)*ROUND((Выручка!$H$13:$S$13*C87)*(Выручка!$H$28:$S$28*F87),0)*Выручка!$H$30:$S$30) -> 0 | L87: =C87*(D87*$D$75+E87*$D$77)+G87*SUMPRODUCT((YEAR(DATE(YEAR(Выручка!$H$7:$S$7),MONTH(Выручка!$H$7:$S$7)+Лаг_выручки,1))=$D$71)*(Выручка!$H$6:$S$6+Лаг_выручки<=12)*ROUND((Выручка!$H$13:$S$13*C87)*(Выручка!$H$28:$S$28*F87),0)*Выручка!$H$30:$S$30) -> 585725.4 | M87: =MAX(0,Ставка_УСН*K87-MIN(Взносы_вычет,Лимит_вычета*Ставка_УСН*K87)) -> 0 | N87: =MAX(0,Ставка_УСН*L87-MIN(Взносы_вычет,Лимит_вычета*Ставка_УСН*L87)) -> 0 | O87: =I87+J87 -> 585725.4 | P87: =Комиссия_стора*J87 -> 37229.76 | Q87: =O87-P87-($D$78+H87)-$D$81-M87-N87 -> 83844.39
B88: eCPM Interstitial +шаг | C88: =1 -> 1 | D88: =1+Шаг_чувств -> 1.2 | E88: =1 -> 1 | F88: =1 -> 1 | G88: =1 -> 1 | H88: =0+(C88-1)*Энергия!$F$39 -> 0 | I88: =C88*(D88*$D$72+E88*$D$73) -> 391108.5 | J88: =G88*SUMPRODUCT(ROUND((Выручка!$H$13:$S$13*C88)*(Выручка!$H$28:$S$28*F88),0)*Выручка!$H$30:$S$30) -> 248198.4 | K88: =C88*(D88*$D$74+E88*$D$76)+G88*SUMPRODUCT((YEAR(DATE(YEAR(Выручка!$H$7:$S$7),MONTH(Выручка!$H$7:$S$7)+Лаг_выручки,1))=$D$70)*(Выручка!$H$6:$S$6+Лаг_выручки<=12)*ROUND((Выручка!$H$13:$S$13*C88)*(Выручка!$H$28:$S$28*F88),0)*Выручка!$H$30:$S$30) -> 0 | L88: =C88*(D88*$D$75+E88*$D$77)+G88*SUMPRODUCT((YEAR(DATE(YEAR(Выручка!$H$7:$S$7),MONTH(Выручка!$H$7:$S$7)+Лаг_выручки,1))=$D$71)*(Выручка!$H$6:$S$6+Лаг_выручки<=12)*ROUND((Выручка!$H$13:$S$13*C88)*(Выручка!$H$28:$S$28*F88),0)*Выручка!$H$30:$S$30) -> 639306.9 | M88: =MAX(0,Ставка_УСН*K88-MIN(Взносы_вычет,Лимит_вычета*Ставка_УСН*K88)) -> 0 | N88: =MAX(0,Ставка_УСН*L88-MIN(Взносы_вычет,Лимит_вычета*Ставка_УСН*L88)) -> 0 | O88: =I88+J88 -> 639306.9 | P88: =Комиссия_стора*J88 -> 37229.76 | Q88: =O88-P88-($D$78+H88)-$D$81-M88-N88 -> 137425.89
B89: eCPM Rewarded −шаг | C89: =1 -> 1 | D89: =1 -> 1 | E89: =1-Шаг_чувств -> 0.8 | F89: =1 -> 1 | G89: =1 -> 1 | H89: =0+(C89-1)*Энергия!$F$39 -> 0 | I89: =C89*(D89*$D$72+E89*$D$73) -> 318244.95 | J89: =G89*SUMPRODUCT(ROUND((Выручка!$H$13:$S$13*C89)*(Выручка!$H$28:$S$28*F89),0)*Выручка!$H$30:$S$30) -> 248198.4 | K89: =C89*(D89*$D$74+E89*$D$76)+G89*SUMPRODUCT((YEAR(DATE(YEAR(Выручка!$H$7:$S$7),MONTH(Выручка!$H$7:$S$7)+Лаг_выручки,1))=$D$70)*(Выручка!$H$6:$S$6+Лаг_выручки<=12)*ROUND((Выручка!$H$13:$S$13*C89)*(Выручка!$H$28:$S$28*F89),0)*Выручка!$H$30:$S$30) -> 0 | L89: =C89*(D89*$D$75+E89*$D$77)+G89*SUMPRODUCT((YEAR(DATE(YEAR(Выручка!$H$7:$S$7),MONTH(Выручка!$H$7:$S$7)+Лаг_выручки,1))=$D$71)*(Выручка!$H$6:$S$6+Лаг_выручки<=12)*ROUND((Выручка!$H$13:$S$13*C89)*(Выручка!$H$28:$S$28*F89),0)*Выручка!$H$30:$S$30) -> 566443.35 | M89: =MAX(0,Ставка_УСН*K89-MIN(Взносы_вычет,Лимит_вычета*Ставка_УСН*K89)) -> 0 | N89: =MAX(0,Ставка_УСН*L89-MIN(Взносы_вычет,Лимит_вычета*Ставка_УСН*L89)) -> 0 | O89: =I89+J89 -> 566443.35 | P89: =Комиссия_стора*J89 -> 37229.76 | Q89: =O89-P89-($D$78+H89)-$D$81-M89-N89 -> 64562.34
B90: eCPM Rewarded +шаг | C90: =1 -> 1 | D90: =1 -> 1 | E90: =1+Шаг_чувств -> 1.2 | F90: =1 -> 1 | G90: =1 -> 1 | H90: =0+(C90-1)*Энергия!$F$39 -> 0 | I90: =C90*(D90*$D$72+E90*$D$73) -> 410390.55 | J90: =G90*SUMPRODUCT(ROUND((Выручка!$H$13:$S$13*C90)*(Выручка!$H$28:$S$28*F90),0)*Выручка!$H$30:$S$30) -> 248198.4 | K90: =C90*(D90*$D$74+E90*$D$76)+G90*SUMPRODUCT((YEAR(DATE(YEAR(Выручка!$H$7:$S$7),MONTH(Выручка!$H$7:$S$7)+Лаг_выручки,1))=$D$70)*(Выручка!$H$6:$S$6+Лаг_выручки<=12)*ROUND((Выручка!$H$13:$S$13*C90)*(Выручка!$H$28:$S$28*F90),0)*Выручка!$H$30:$S$30) -> 0 | L90: =C90*(D90*$D$75+E90*$D$77)+G90*SUMPRODUCT((YEAR(DATE(YEAR(Выручка!$H$7:$S$7),MONTH(Выручка!$H$7:$S$7)+Лаг_выручки,1))=$D$71)*(Выручка!$H$6:$S$6+Лаг_выручки<=12)*ROUND((Выручка!$H$13:$S$13*C90)*(Выручка!$H$28:$S$28*F90),0)*Выручка!$H$30:$S$30) -> 658588.95 | M90: =MAX(0,Ставка_УСН*K90-MIN(Взносы_вычет,Лимит_вычета*Ставка_УСН*K90)) -> 0 | N90: =MAX(0,Ставка_УСН*L90-MIN(Взносы_вычет,Лимит_вычета*Ставка_УСН*L90)) -> 0 | O90: =I90+J90 -> 658588.95 | P90: =Комиссия_стора*J90 -> 37229.76 | Q90: =O90-P90-($D$78+H90)-$D$81-M90-N90 -> 156707.94
B91: Конверсия в плательщиков (средняя) −шаг | C91: =1 -> 1 | D91: =1 -> 1 | E91: =1 -> 1 | F91: =1-Шаг_чувств -> 0.8 | G91: =1 -> 1 | H91: =0+(C91-1)*Энергия!$F$39 -> 0 | I91: =C91*(D91*$D$72+E91*$D$73) -> 364317.75 | J91: =G91*SUMPRODUCT(ROUND((Выручка!$H$13:$S$13*C91)*(Выручка!$H$28:$S$28*F91),0)*Выручка!$H$30:$S$30) -> 197852.4 | K91: =C91*(D91*$D$74+E91*$D$76)+G91*SUMPRODUCT((YEAR(DATE(YEAR(Выручка!$H$7:$S$7),MONTH(Выручка!$H$7:$S$7)+Лаг_выручки,1))=$D$70)*(Выручка!$H$6:$S$6+Лаг_выручки<=12)*ROUND((Выручка!$H$13:$S$13*C91)*(Выручка!$H$28:$S$28*F91),0)*Выручка!$H$30:$S$30) -> 0 | L91: =C91*(D91*$D$75+E91*$D$77)+G91*SUMPRODUCT((YEAR(DATE(YEAR(Выручка!$H$7:$S$7),MONTH(Выручка!$H$7:$S$7)+Лаг_выручки,1))=$D$71)*(Выручка!$H$6:$S$6+Лаг_выручки<=12)*ROUND((Выручка!$H$13:$S$13*C91)*(Выручка!$H$28:$S$28*F91),0)*Выручка!$H$30:$S$30) -> 562170.15 | M91: =MAX(0,Ставка_УСН*K91-MIN(Взносы_вычет,Лимит_вычета*Ставка_УСН*K91)) -> 0 | N91: =MAX(0,Ставка_УСН*L91-MIN(Взносы_вычет,Лимит_вычета*Ставка_УСН*L91)) -> 0 | O91: =I91+J91 -> 562170.15 | P91: =Комиссия_стора*J91 -> 29677.86 | Q91: =O91-P91-($D$78+H91)-$D$81-M91-N91 -> 67841.04
B92: Конверсия в плательщиков (средняя) +шаг | C92: =1 -> 1 | D92: =1 -> 1 | E92: =1 -> 1 | F92: =1+Шаг_чувств -> 1.2 | G92: =1 -> 1 | H92: =0+(C92-1)*Энергия!$F$39 -> 0 | I92: =C92*(D92*$D$72+E92*$D$73) -> 364317.75 | J92: =G92*SUMPRODUCT(ROUND((Выручка!$H$13:$S$13*C92)*(Выручка!$H$28:$S$28*F92),0)*Выручка!$H$30:$S$30) -> 297232 | K92: =C92*(D92*$D$74+E92*$D$76)+G92*SUMPRODUCT((YEAR(DATE(YEAR(Выручка!$H$7:$S$7),MONTH(Выручка!$H$7:$S$7)+Лаг_выручки,1))=$D$70)*(Выручка!$H$6:$S$6+Лаг_выручки<=12)*ROUND((Выручка!$H$13:$S$13*C92)*(Выручка!$H$28:$S$28*F92),0)*Выручка!$H$30:$S$30) -> 0 | L92: =C92*(D92*$D$75+E92*$D$77)+G92*SUMPRODUCT((YEAR(DATE(YEAR(Выручка!$H$7:$S$7),MONTH(Выручка!$H$7:$S$7)+Лаг_выручки,1))=$D$71)*(Выручка!$H$6:$S$6+Лаг_выручки<=12)*ROUND((Выручка!$H$13:$S$13*C92)*(Выручка!$H$28:$S$28*F92),0)*Выручка!$H$30:$S$30) -> 661549.75 | M92: =MAX(0,Ставка_УСН*K92-MIN(Взносы_вычет,Лимит_вычета*Ставка_УСН*K92)) -> 0 | N92: =MAX(0,Ставка_УСН*L92-MIN(Взносы_вычет,Лимит_вычета*Ставка_УСН*L92)) -> 0 | O92: =I92+J92 -> 661549.75 | P92: =Комиссия_стора*J92 -> 44584.8 | Q92: =O92-P92-($D$78+H92)-$D$81-M92-N92 -> 152313.7
B93: Средний чек IAP (ARPPU, средний) −шаг | C93: =1 -> 1 | D93: =1 -> 1 | E93: =1 -> 1 | F93: =1 -> 1 | G93: =1-Шаг_чувств -> 0.8 | H93: =0+(C93-1)*Энергия!$F$39 -> 0 | I93: =C93*(D93*$D$72+E93*$D$73) -> 364317.75 | J93: =G93*SUMPRODUCT(ROUND((Выручка!$H$13:$S$13*C93)*(Выручка!$H$28:$S$28*F93),0)*Выручка!$H$30:$S$30) -> 198558.72 | K93: =C93*(D93*$D$74+E93*$D$76)+G93*SUMPRODUCT((YEAR(DATE(YEAR(Выручка!$H$7:$S$7),MONTH(Выручка!$H$7:$S$7)+Лаг_выручки,1))=$D$70)*(Выручка!$H$6:$S$6+Лаг_выручки<=12)*ROUND((Выручка!$H$13:$S$13*C93)*(Выручка!$H$28:$S$28*F93),0)*Выручка!$H$30:$S$30) -> 0 | L93: =C93*(D93*$D$75+E93*$D$77)+G93*SUMPRODUCT((YEAR(DATE(YEAR(Выручка!$H$7:$S$7),MONTH(Выручка!$H$7:$S$7)+Лаг_выручки,1))=$D$71)*(Выручка!$H$6:$S$6+Лаг_выручки<=12)*ROUND((Выручка!$H$13:$S$13*C93)*(Выручка!$H$28:$S$28*F93),0)*Выручка!$H$30:$S$30) -> 562876.47 | M93: =MAX(0,Ставка_УСН*K93-MIN(Взносы_вычет,Лимит_вычета*Ставка_УСН*K93)) -> 0 | N93: =MAX(0,Ставка_УСН*L93-MIN(Взносы_вычет,Лимит_вычета*Ставка_УСН*L93)) -> 0 | O93: =I93+J93 -> 562876.47 | P93: =Комиссия_стора*J93 -> 29783.808 | Q93: =O93-P93-($D$78+H93)-$D$81-M93-N93 -> 68441.412
B94: Средний чек IAP (ARPPU, средний) +шаг | C94: =1 -> 1 | D94: =1 -> 1 | E94: =1 -> 1 | F94: =1 -> 1 | G94: =1+Шаг_чувств -> 1.2 | H94: =0+(C94-1)*Энергия!$F$39 -> 0 | I94: =C94*(D94*$D$72+E94*$D$73) -> 364317.75 | J94: =G94*SUMPRODUCT(ROUND((Выручка!$H$13:$S$13*C94)*(Выручка!$H$28:$S$28*F94),0)*Выручка!$H$30:$S$30) -> 297838.08 | K94: =C94*(D94*$D$74+E94*$D$76)+G94*SUMPRODUCT((YEAR(DATE(YEAR(Выручка!$H$7:$S$7),MONTH(Выручка!$H$7:$S$7)+Лаг_выручки,1))=$D$70)*(Выручка!$H$6:$S$6+Лаг_выручки<=12)*ROUND((Выручка!$H$13:$S$13*C94)*(Выручка!$H$28:$S$28*F94),0)*Выручка!$H$30:$S$30) -> 0 | L94: =C94*(D94*$D$75+E94*$D$77)+G94*SUMPRODUCT((YEAR(DATE(YEAR(Выручка!$H$7:$S$7),MONTH(Выручка!$H$7:$S$7)+Лаг_выручки,1))=$D$71)*(Выручка!$H$6:$S$6+Лаг_выручки<=12)*ROUND((Выручка!$H$13:$S$13*C94)*(Выручка!$H$28:$S$28*F94),0)*Выручка!$H$30:$S$30) -> 662155.83 | M94: =MAX(0,Ставка_УСН*K94-MIN(Взносы_вычет,Лимит_вычета*Ставка_УСН*K94)) -> 0 | N94: =MAX(0,Ставка_УСН*L94-MIN(Взносы_вычет,Лимит_вычета*Ставка_УСН*L94)) -> 0 | O94: =I94+J94 -> 662155.83 | P94: =Комиссия_стора*J94 -> 44675.712 | Q94: =O94-P94-($D$78+H94)-$D$81-M94-N94 -> 152828.87
B95: Маркетинг после релиза, ₽/мес −шаг | C95: =1 -> 1 | D95: =1 -> 1 | E95: =1 -> 1 | F95: =1 -> 1 | G95: =1 -> 1 | H95: =-Шаг_чувств*$D$79+(C95-1)*Энергия!$F$39 -> -48000 | I95: =C95*(D95*$D$72+E95*$D$73) -> 364317.75 | J95: =G95*SUMPRODUCT(ROUND((Выручка!$H$13:$S$13*C95)*(Выручка!$H$28:$S$28*F95),0)*Выручка!$H$30:$S$30) -> 248198.4 | K95: =C95*(D95*$D$74+E95*$D$76)+G95*SUMPRODUCT((YEAR(DATE(YEAR(Выручка!$H$7:$S$7),MONTH(Выручка!$H$7:$S$7)+Лаг_выручки,1))=$D$70)*(Выручка!$H$6:$S$6+Лаг_выручки<=12)*ROUND((Выручка!$H$13:$S$13*C95)*(Выручка!$H$28:$S$28*F95),0)*Выручка!$H$30:$S$30) -> 0 | L95: =C95*(D95*$D$75+E95*$D$77)+G95*SUMPRODUCT((YEAR(DATE(YEAR(Выручка!$H$7:$S$7),MONTH(Выручка!$H$7:$S$7)+Лаг_выручки,1))=$D$71)*(Выручка!$H$6:$S$6+Лаг_выручки<=12)*ROUND((Выручка!$H$13:$S$13*C95)*(Выручка!$H$28:$S$28*F95),0)*Выручка!$H$30:$S$30) -> 612516.15 | M95: =MAX(0,Ставка_УСН*K95-MIN(Взносы_вычет,Лимит_вычета*Ставка_УСН*K95)) -> 0 | N95: =MAX(0,Ставка_УСН*L95-MIN(Взносы_вычет,Лимит_вычета*Ставка_УСН*L95)) -> 0 | O95: =I95+J95 -> 612516.15 | P95: =Комиссия_стора*J95 -> 37229.76 | Q95: =O95-P95-($D$78+H95)-$D$81-M95-N95 -> 158635.14
B96: Маркетинг после релиза, ₽/мес +шаг | C96: =1 -> 1 | D96: =1 -> 1 | E96: =1 -> 1 | F96: =1 -> 1 | G96: =1 -> 1 | H96: =Шаг_чувств*$D$79+(C96-1)*Энергия!$F$39 -> 48000 | I96: =C96*(D96*$D$72+E96*$D$73) -> 364317.75 | J96: =G96*SUMPRODUCT(ROUND((Выручка!$H$13:$S$13*C96)*(Выручка!$H$28:$S$28*F96),0)*Выручка!$H$30:$S$30) -> 248198.4 | K96: =C96*(D96*$D$74+E96*$D$76)+G96*SUMPRODUCT((YEAR(DATE(YEAR(Выручка!$H$7:$S$7),MONTH(Выручка!$H$7:$S$7)+Лаг_выручки,1))=$D$70)*(Выручка!$H$6:$S$6+Лаг_выручки<=12)*ROUND((Выручка!$H$13:$S$13*C96)*(Выручка!$H$28:$S$28*F96),0)*Выручка!$H$30:$S$30) -> 0 | L96: =C96*(D96*$D$75+E96*$D$77)+G96*SUMPRODUCT((YEAR(DATE(YEAR(Выручка!$H$7:$S$7),MONTH(Выручка!$H$7:$S$7)+Лаг_выручки,1))=$D$71)*(Выручка!$H$6:$S$6+Лаг_выручки<=12)*ROUND((Выручка!$H$13:$S$13*C96)*(Выручка!$H$28:$S$28*F96),0)*Выручка!$H$30:$S$30) -> 612516.15 | M96: =MAX(0,Ставка_УСН*K96-MIN(Взносы_вычет,Лимит_вычета*Ставка_УСН*K96)) -> 0 | N96: =MAX(0,Ставка_УСН*L96-MIN(Взносы_вычет,Лимит_вычета*Ставка_УСН*L96)) -> 0 | O96: =I96+J96 -> 612516.15 | P96: =Комиссия_стора*J96 -> 37229.76 | Q96: =O96-P96-($D$78+H96)-$D$81-M96-N96 -> 62635.14
B97: Бухгалтерия и юр. сопровождение, ₽/мес −шаг | C97: =1 -> 1 | D97: =1 -> 1 | E97: =1 -> 1 | F97: =1 -> 1 | G97: =1 -> 1 | H97: =-Шаг_чувств*$D$80+(C97-1)*Энергия!$F$39 -> -18000 | I97: =C97*(D97*$D$72+E97*$D$73) -> 364317.75 | J97: =G97*SUMPRODUCT(ROUND((Выручка!$H$13:$S$13*C97)*(Выручка!$H$28:$S$28*F97),0)*Выручка!$H$30:$S$30) -> 248198.4 | K97: =C97*(D97*$D$74+E97*$D$76)+G97*SUMPRODUCT((YEAR(DATE(YEAR(Выручка!$H$7:$S$7),MONTH(Выручка!$H$7:$S$7)+Лаг_выручки,1))=$D$70)*(Выручка!$H$6:$S$6+Лаг_выручки<=12)*ROUND((Выручка!$H$13:$S$13*C97)*(Выручка!$H$28:$S$28*F97),0)*Выручка!$H$30:$S$30) -> 0 | L97: =C97*(D97*$D$75+E97*$D$77)+G97*SUMPRODUCT((YEAR(DATE(YEAR(Выручка!$H$7:$S$7),MONTH(Выручка!$H$7:$S$7)+Лаг_выручки,1))=$D$71)*(Выручка!$H$6:$S$6+Лаг_выручки<=12)*ROUND((Выручка!$H$13:$S$13*C97)*(Выручка!$H$28:$S$28*F97),0)*Выручка!$H$30:$S$30) -> 612516.15 | M97: =MAX(0,Ставка_УСН*K97-MIN(Взносы_вычет,Лимит_вычета*Ставка_УСН*K97)) -> 0 | N97: =MAX(0,Ставка_УСН*L97-MIN(Взносы_вычет,Лимит_вычета*Ставка_УСН*L97)) -> 0 | O97: =I97+J97 -> 612516.15 | P97: =Комиссия_стора*J97 -> 37229.76 | Q97: =O97-P97-($D$78+H97)-$D$81-M97-N97 -> 128635.14
B98: Бухгалтерия и юр. сопровождение, ₽/мес +шаг | C98: =1 -> 1 | D98: =1 -> 1 | E98: =1 -> 1 | F98: =1 -> 1 | G98: =1 -> 1 | H98: =Шаг_чувств*$D$80+(C98-1)*Энергия!$F$39 -> 18000 | I98: =C98*(D98*$D$72+E98*$D$73) -> 364317.75 | J98: =G98*SUMPRODUCT(ROUND((Выручка!$H$13:$S$13*C98)*(Выручка!$H$28:$S$28*F98),0)*Выручка!$H$30:$S$30) -> 248198.4 | K98: =C98*(D98*$D$74+E98*$D$76)+G98*SUMPRODUCT((YEAR(DATE(YEAR(Выручка!$H$7:$S$7),MONTH(Выручка!$H$7:$S$7)+Лаг_выручки,1))=$D$70)*(Выручка!$H$6:$S$6+Лаг_выручки<=12)*ROUND((Выручка!$H$13:$S$13*C98)*(Выручка!$H$28:$S$28*F98),0)*Выручка!$H$30:$S$30) -> 0 | L98: =C98*(D98*$D$75+E98*$D$77)+G98*SUMPRODUCT((YEAR(DATE(YEAR(Выручка!$H$7:$S$7),MONTH(Выручка!$H$7:$S$7)+Лаг_выручки,1))=$D$71)*(Выручка!$H$6:$S$6+Лаг_выручки<=12)*ROUND((Выручка!$H$13:$S$13*C98)*(Выручка!$H$28:$S$28*F98),0)*Выручка!$H$30:$S$30) -> 612516.15 | M98: =MAX(0,Ставка_УСН*K98-MIN(Взносы_вычет,Лимит_вычета*Ставка_УСН*K98)) -> 0 | N98: =MAX(0,Ставка_УСН*L98-MIN(Взносы_вычет,Лимит_вычета*Ставка_УСН*L98)) -> 0 | O98: =I98+J98 -> 612516.15 | P98: =Комиссия_стора*J98 -> 37229.76 | Q98: =O98-P98-($D$78+H98)-$D$81-M98-N98 -> 92635.14
B99: сетка MAU 0.6 × eCPM 0.6 | C99: =$B$21 -> 0.6 | D99: =C$20 -> 0.6 | E99: =C$20 -> 0.6 | F99: =1 -> 1 | G99: =1 -> 1 | H99: =0+(C99-1)*Энергия!$F$39 -> -17860.5 | I99: =C99*(D99*$D$72+E99*$D$73) -> 131154.39 | J99: =G99*SUMPRODUCT(ROUND((Выручка!$H$13:$S$13*C99)*(Выручка!$H$28:$S$28*F99),0)*Выручка!$H$30:$S$30) -> 148808.8 | K99: =C99*(D99*$D$74+E99*$D$76)+G99*SUMPRODUCT((YEAR(DATE(YEAR(Выручка!$H$7:$S$7),MONTH(Выручка!$H$7:$S$7)+Лаг_выручки,1))=$D$70)*(Выручка!$H$6:$S$6+Лаг_выручки<=12)*ROUND((Выручка!$H$13:$S$13*C99)*(Выручка!$H$28:$S$28*F99),0)*Выручка!$H$30:$S$30) -> 0 | L99: =C99*(D99*$D$75+E99*$D$77)+G99*SUMPRODUCT((YEAR(DATE(YEAR(Выручка!$H$7:$S$7),MONTH(Выручка!$H$7:$S$7)+Лаг_выручки,1))=$D$71)*(Выручка!$H$6:$S$6+Лаг_выручки<=12)*ROUND((Выручка!$H$13:$S$13*C99)*(Выручка!$H$28:$S$28*F99),0)*Выручка!$H$30:$S$30) -> 279963.19 | M99: =MAX(0,Ставка_УСН*K99-MIN(Взносы_вычет,Лимит_вычета*Ставка_УСН*K99)) -> 0 | N99: =MAX(0,Ставка_УСН*L99-MIN(Взносы_вычет,Лимит_вычета*Ставка_УСН*L99)) -> 0 | O99: =I99+J99 -> 279963.19 | P99: =Комиссия_стора*J99 -> 22321.32 | Q99: =O99-P99-($D$78+H99)-$D$81-M99-N99 -> -189148.88
B100: сетка MAU 0.6 × eCPM 0.8 | C100: =$B$21 -> 0.6 | D100: =D$20 -> 0.8 | E100: =D$20 -> 0.8 | F100: =1 -> 1 | G100: =1 -> 1 | H100: =0+(C100-1)*Энергия!$F$39 -> -17860.5 | I100: =C100*(D100*$D$72+E100*$D$73) -> 174872.52 | J100: =G100*SUMPRODUCT(ROUND((Выручка!$H$13:$S$13*C100)*(Выручка!$H$28:$S$28*F100),0)*Выручка!$H$30:$S$30) -> 148808.8 | K100: =C100*(D100*$D$74+E100*$D$76)+G100*SUMPRODUCT((YEAR(DATE(YEAR(Выручка!$H$7:$S$7),MONTH(Выручка!$H$7:$S$7)+Лаг_выручки,1))=$D$70)*(Выручка!$H$6:$S$6+Лаг_выручки<=12)*ROUND((Выручка!$H$13:$S$13*C100)*(Выручка!$H$28:$S$28*F100),0)*Выручка!$H$30:$S$30) -> 0 | L100: =C100*(D100*$D$75+E100*$D$77)+G100*SUMPRODUCT((YEAR(DATE(YEAR(Выручка!$H$7:$S$7),MONTH(Выручка!$H$7:$S$7)+Лаг_выручки,1))=$D$71)*(Выручка!$H$6:$S$6+Лаг_выручки<=12)*ROUND((Выручка!$H$13:$S$13*C100)*(Выручка!$H$28:$S$28*F100),0)*Выручка!$H$30:$S$30) -> 323681.32 | M100: =MAX(0,Ставка_УСН*K100-MIN(Взносы_вычет,Лимит_вычета*Ставка_УСН*K100)) -> 0 | N100: =MAX(0,Ставка_УСН*L100-MIN(Взносы_вычет,Лимит_вычета*Ставка_УСН*L100)) -> 0 | O100: =I100+J100 -> 323681.32 | P100: =Комиссия_стора*J100 -> 22321.32 | Q100: =O100-P100-($D$78+H100)-$D$81-M100-N100 -> -145430.75
B101: сетка MAU 0.6 × eCPM 1.0 | C101: =$B$21 -> 0.6 | D101: =E$20 -> 1 | E101: =E$20 -> 1 | F101: =1 -> 1 | G101: =1 -> 1 | H101: =0+(C101-1)*Энергия!$F$39 -> -17860.5 | I101: =C101*(D101*$D$72+E101*$D$73) -> 218590.65 | J101: =G101*SUMPRODUCT(ROUND((Выручка!$H$13:$S$13*C101)*(Выручка!$H$28:$S$28*F101),0)*Выручка!$H$30:$S$30) -> 148808.8 | K101: =C101*(D101*$D$74+E101*$D$76)+G101*SUMPRODUCT((YEAR(DATE(YEAR(Выручка!$H$7:$S$7),MONTH(Выручка!$H$7:$S$7)+Лаг_выручки,1))=$D$70)*(Выручка!$H$6:$S$6+Лаг_выручки<=12)*ROUND((Выручка!$H$13:$S$13*C101)*(Выручка!$H$28:$S$28*F101),0)*Выручка!$H$30:$S$30) -> 0 | L101: =C101*(D101*$D$75+E101*$D$77)+G101*SUMPRODUCT((YEAR(DATE(YEAR(Выручка!$H$7:$S$7),MONTH(Выручка!$H$7:$S$7)+Лаг_выручки,1))=$D$71)*(Выручка!$H$6:$S$6+Лаг_выручки<=12)*ROUND((Выручка!$H$13:$S$13*C101)*(Выручка!$H$28:$S$28*F101),0)*Выручка!$H$30:$S$30) -> 367399.45 | M101: =MAX(0,Ставка_УСН*K101-MIN(Взносы_вычет,Лимит_вычета*Ставка_УСН*K101)) -> 0 | N101: =MAX(0,Ставка_УСН*L101-MIN(Взносы_вычет,Лимит_вычета*Ставка_УСН*L101)) -> 0 | O101: =I101+J101 -> 367399.45 | P101: =Комиссия_стора*J101 -> 22321.32 | Q101: =O101-P101-($D$78+H101)-$D$81-M101-N101 -> -101712.62
B102: сетка MAU 0.6 × eCPM 1.2 | C102: =$B$21 -> 0.6 | D102: =F$20 -> 1.2 | E102: =F$20 -> 1.2 | F102: =1 -> 1 | G102: =1 -> 1 | H102: =0+(C102-1)*Энергия!$F$39 -> -17860.5 | I102: =C102*(D102*$D$72+E102*$D$73) -> 262308.78 | J102: =G102*SUMPRODUCT(ROUND((Выручка!$H$13:$S$13*C102)*(Выручка!$H$28:$S$28*F102),0)*Выручка!$H$30:$S$30) -> 148808.8 | K102: =C102*(D102*$D$74+E102*$D$76)+G102*SUMPRODUCT((YEAR(DATE(YEAR(Выручка!$H$7:$S$7),MONTH(Выручка!$H$7:$S$7)+Лаг_выручки,1))=$D$70)*(Выручка!$H$6:$S$6+Лаг_выручки<=12)*ROUND((Выручка!$H$13:$S$13*C102)*(Выручка!$H$28:$S$28*F102),0)*Выручка!$H$30:$S$30) -> 0 | L102: =C102*(D102*$D$75+E102*$D$77)+G102*SUMPRODUCT((YEAR(DATE(YEAR(Выручка!$H$7:$S$7),MONTH(Выручка!$H$7:$S$7)+Лаг_выручки,1))=$D$71)*(Выручка!$H$6:$S$6+Лаг_выручки<=12)*ROUND((Выручка!$H$13:$S$13*C102)*(Выручка!$H$28:$S$28*F102),0)*Выручка!$H$30:$S$30) -> 411117.58 | M102: =MAX(0,Ставка_УСН*K102-MIN(Взносы_вычет,Лимит_вычета*Ставка_УСН*K102)) -> 0 | N102: =MAX(0,Ставка_УСН*L102-MIN(Взносы_вычет,Лимит_вычета*Ставка_УСН*L102)) -> 0 | O102: =I102+J102 -> 411117.58 | P102: =Комиссия_стора*J102 -> 22321.32 | Q102: =O102-P102-($D$78+H102)-$D$81-M102-N102 -> -57994.49
B103: сетка MAU 0.6 × eCPM 1.4 | C103: =$B$21 -> 0.6 | D103: =G$20 -> 1.4 | E103: =G$20 -> 1.4 | F103: =1 -> 1 | G103: =1 -> 1 | H103: =0+(C103-1)*Энергия!$F$39 -> -17860.5 | I103: =C103*(D103*$D$72+E103*$D$73) -> 306026.91 | J103: =G103*SUMPRODUCT(ROUND((Выручка!$H$13:$S$13*C103)*(Выручка!$H$28:$S$28*F103),0)*Выручка!$H$30:$S$30) -> 148808.8 | K103: =C103*(D103*$D$74+E103*$D$76)+G103*SUMPRODUCT((YEAR(DATE(YEAR(Выручка!$H$7:$S$7),MONTH(Выручка!$H$7:$S$7)+Лаг_выручки,1))=$D$70)*(Выручка!$H$6:$S$6+Лаг_выручки<=12)*ROUND((Выручка!$H$13:$S$13*C103)*(Выручка!$H$28:$S$28*F103),0)*Выручка!$H$30:$S$30) -> 0 | L103: =C103*(D103*$D$75+E103*$D$77)+G103*SUMPRODUCT((YEAR(DATE(YEAR(Выручка!$H$7:$S$7),MONTH(Выручка!$H$7:$S$7)+Лаг_выручки,1))=$D$71)*(Выручка!$H$6:$S$6+Лаг_выручки<=12)*ROUND((Выручка!$H$13:$S$13*C103)*(Выручка!$H$28:$S$28*F103),0)*Выручка!$H$30:$S$30) -> 454835.71 | M103: =MAX(0,Ставка_УСН*K103-MIN(Взносы_вычет,Лимит_вычета*Ставка_УСН*K103)) -> 0 | N103: =MAX(0,Ставка_УСН*L103-MIN(Взносы_вычет,Лимит_вычета*Ставка_УСН*L103)) -> 0 | O103: =I103+J103 -> 454835.71 | P103: =Комиссия_стора*J103 -> 22321.32 | Q103: =O103-P103-($D$78+H103)-$D$81-M103-N103 -> -14276.36
B104: сетка MAU 0.8 × eCPM 0.6 | C104: =$B$22 -> 0.8 | D104: =C$20 -> 0.6 | E104: =C$20 -> 0.6 | F104: =1 -> 1 | G104: =1 -> 1 | H104: =0+(C104-1)*Энергия!$F$39 -> -8930.25 | I104: =C104*(D104*$D$72+E104*$D$73) -> 174872.52 | J104: =G104*SUMPRODUCT(ROUND((Выручка!$H$13:$S$13*C104)*(Выручка!$H$28:$S$28*F104),0)*Выручка!$H$30:$S$30) -> 197852.4 | K104: =C104*(D104*$D$74+E104*$D$76)+G104*SUMPRODUCT((YEAR(DATE(YEAR(Выручка!$H$7:$S$7),MONTH(Выручка!$H$7:$S$7)+Лаг_выручки,1))=$D$70)*(Выручка!$H$6:$S$6+Лаг_выручки<=12)*ROUND((Выручка!$H$13:$S$13*C104)*(Выручка!$H$28:$S$28*F104),0)*Выручка!$H$30:$S$30) -> 0 | L104: =C104*(D104*$D$75+E104*$D$77)+G104*SUMPRODUCT((YEAR(DATE(YEAR(Выручка!$H$7:$S$7),MONTH(Выручка!$H$7:$S$7)+Лаг_выручки,1))=$D$71)*(Выручка!$H$6:$S$6+Лаг_выручки<=12)*ROUND((Выручка!$H$13:$S$13*C104)*(Выручка!$H$28:$S$28*F104),0)*Выручка!$H$30:$S$30) -> 372724.92 | M104: =MAX(0,Ставка_УСН*K104-MIN(Взносы_вычет,Лимит_вычета*Ставка_УСН*K104)) -> 0 | N104: =MAX(0,Ставка_УСН*L104-MIN(Взносы_вычет,Лимит_вычета*Ставка_УСН*L104)) -> 0 | O104: =I104+J104 -> 372724.92 | P104: =Комиссия_стора*J104 -> 29677.86 | Q104: =O104-P104-($D$78+H104)-$D$81-M104-N104 -> -112673.94
B105: сетка MAU 0.8 × eCPM 0.8 | C105: =$B$22 -> 0.8 | D105: =D$20 -> 0.8 | E105: =D$20 -> 0.8 | F105: =1 -> 1 | G105: =1 -> 1 | H105: =0+(C105-1)*Энергия!$F$39 -> -8930.25 | I105: =C105*(D105*$D$72+E105*$D$73) -> 233163.36 | J105: =G105*SUMPRODUCT(ROUND((Выручка!$H$13:$S$13*C105)*(Выручка!$H$28:$S$28*F105),0)*Выручка!$H$30:$S$30) -> 197852.4 | K105: =C105*(D105*$D$74+E105*$D$76)+G105*SUMPRODUCT((YEAR(DATE(YEAR(Выручка!$H$7:$S$7),MONTH(Выручка!$H$7:$S$7)+Лаг_выручки,1))=$D$70)*(Выручка!$H$6:$S$6+Лаг_выручки<=12)*ROUND((Выручка!$H$13:$S$13*C105)*(Выручка!$H$28:$S$28*F105),0)*Выручка!$H$30:$S$30) -> 0 | L105: =C105*(D105*$D$75+E105*$D$77)+G105*SUMPRODUCT((YEAR(DATE(YEAR(Выручка!$H$7:$S$7),MONTH(Выручка!$H$7:$S$7)+Лаг_выручки,1))=$D$71)*(Выручка!$H$6:$S$6+Лаг_выручки<=12)*ROUND((Выручка!$H$13:$S$13*C105)*(Выручка!$H$28:$S$28*F105),0)*Выручка!$H$30:$S$30) -> 431015.76 | M105: =MAX(0,Ставка_УСН*K105-MIN(Взносы_вычет,Лимит_вычета*Ставка_УСН*K105)) -> 0 | N105: =MAX(0,Ставка_УСН*L105-MIN(Взносы_вычет,Лимит_вычета*Ставка_УСН*L105)) -> 0 | O105: =I105+J105 -> 431015.76 | P105: =Комиссия_стора*J105 -> 29677.86 | Q105: =O105-P105-($D$78+H105)-$D$81-M105-N105 -> -54383.1
B106: сетка MAU 0.8 × eCPM 1.0 | C106: =$B$22 -> 0.8 | D106: =E$20 -> 1 | E106: =E$20 -> 1 | F106: =1 -> 1 | G106: =1 -> 1 | H106: =0+(C106-1)*Энергия!$F$39 -> -8930.25 | I106: =C106*(D106*$D$72+E106*$D$73) -> 291454.2 | J106: =G106*SUMPRODUCT(ROUND((Выручка!$H$13:$S$13*C106)*(Выручка!$H$28:$S$28*F106),0)*Выручка!$H$30:$S$30) -> 197852.4 | K106: =C106*(D106*$D$74+E106*$D$76)+G106*SUMPRODUCT((YEAR(DATE(YEAR(Выручка!$H$7:$S$7),MONTH(Выручка!$H$7:$S$7)+Лаг_выручки,1))=$D$70)*(Выручка!$H$6:$S$6+Лаг_выручки<=12)*ROUND((Выручка!$H$13:$S$13*C106)*(Выручка!$H$28:$S$28*F106),0)*Выручка!$H$30:$S$30) -> 0 | L106: =C106*(D106*$D$75+E106*$D$77)+G106*SUMPRODUCT((YEAR(DATE(YEAR(Выручка!$H$7:$S$7),MONTH(Выручка!$H$7:$S$7)+Лаг_выручки,1))=$D$71)*(Выручка!$H$6:$S$6+Лаг_выручки<=12)*ROUND((Выручка!$H$13:$S$13*C106)*(Выручка!$H$28:$S$28*F106),0)*Выручка!$H$30:$S$30) -> 489306.6 | M106: =MAX(0,Ставка_УСН*K106-MIN(Взносы_вычет,Лимит_вычета*Ставка_УСН*K106)) -> 0 | N106: =MAX(0,Ставка_УСН*L106-MIN(Взносы_вычет,Лимит_вычета*Ставка_УСН*L106)) -> 0 | O106: =I106+J106 -> 489306.6 | P106: =Комиссия_стора*J106 -> 29677.86 | Q106: =O106-P106-($D$78+H106)-$D$81-M106-N106 -> 3907.74
B107: сетка MAU 0.8 × eCPM 1.2 | C107: =$B$22 -> 0.8 | D107: =F$20 -> 1.2 | E107: =F$20 -> 1.2 | F107: =1 -> 1 | G107: =1 -> 1 | H107: =0+(C107-1)*Энергия!$F$39 -> -8930.25 | I107: =C107*(D107*$D$72+E107*$D$73) -> 349745.04 | J107: =G107*SUMPRODUCT(ROUND((Выручка!$H$13:$S$13*C107)*(Выручка!$H$28:$S$28*F107),0)*Выручка!$H$30:$S$30) -> 197852.4 | K107: =C107*(D107*$D$74+E107*$D$76)+G107*SUMPRODUCT((YEAR(DATE(YEAR(Выручка!$H$7:$S$7),MONTH(Выручка!$H$7:$S$7)+Лаг_выручки,1))=$D$70)*(Выручка!$H$6:$S$6+Лаг_выручки<=12)*ROUND((Выручка!$H$13:$S$13*C107)*(Выручка!$H$28:$S$28*F107),0)*Выручка!$H$30:$S$30) -> 0 | L107: =C107*(D107*$D$75+E107*$D$77)+G107*SUMPRODUCT((YEAR(DATE(YEAR(Выручка!$H$7:$S$7),MONTH(Выручка!$H$7:$S$7)+Лаг_выручки,1))=$D$71)*(Выручка!$H$6:$S$6+Лаг_выручки<=12)*ROUND((Выручка!$H$13:$S$13*C107)*(Выручка!$H$28:$S$28*F107),0)*Выручка!$H$30:$S$30) -> 547597.44 | M107: =MAX(0,Ставка_УСН*K107-MIN(Взносы_вычет,Лимит_вычета*Ставка_УСН*K107)) -> 0 | N107: =MAX(0,Ставка_УСН*L107-MIN(Взносы_вычет,Лимит_вычета*Ставка_УСН*L107)) -> 0 | O107: =I107+J107 -> 547597.44 | P107: =Комиссия_стора*J107 -> 29677.86 | Q107: =O107-P107-($D$78+H107)-$D$81-M107-N107 -> 62198.58
B108: сетка MAU 0.8 × eCPM 1.4 | C108: =$B$22 -> 0.8 | D108: =G$20 -> 1.4 | E108: =G$20 -> 1.4 | F108: =1 -> 1 | G108: =1 -> 1 | H108: =0+(C108-1)*Энергия!$F$39 -> -8930.25 | I108: =C108*(D108*$D$72+E108*$D$73) -> 408035.88 | J108: =G108*SUMPRODUCT(ROUND((Выручка!$H$13:$S$13*C108)*(Выручка!$H$28:$S$28*F108),0)*Выручка!$H$30:$S$30) -> 197852.4 | K108: =C108*(D108*$D$74+E108*$D$76)+G108*SUMPRODUCT((YEAR(DATE(YEAR(Выручка!$H$7:$S$7),MONTH(Выручка!$H$7:$S$7)+Лаг_выручки,1))=$D$70)*(Выручка!$H$6:$S$6+Лаг_выручки<=12)*ROUND((Выручка!$H$13:$S$13*C108)*(Выручка!$H$28:$S$28*F108),0)*Выручка!$H$30:$S$30) -> 0 | L108: =C108*(D108*$D$75+E108*$D$77)+G108*SUMPRODUCT((YEAR(DATE(YEAR(Выручка!$H$7:$S$7),MONTH(Выручка!$H$7:$S$7)+Лаг_выручки,1))=$D$71)*(Выручка!$H$6:$S$6+Лаг_выручки<=12)*ROUND((Выручка!$H$13:$S$13*C108)*(Выручка!$H$28:$S$28*F108),0)*Выручка!$H$30:$S$30) -> 605888.28 | M108: =MAX(0,Ставка_УСН*K108-MIN(Взносы_вычет,Лимит_вычета*Ставка_УСН*K108)) -> 0 | N108: =MAX(0,Ставка_УСН*L108-MIN(Взносы_вычет,Лимит_вычета*Ставка_УСН*L108)) -> 0 | O108: =I108+J108 -> 605888.28 | P108: =Комиссия_стора*J108 -> 29677.86 | Q108: =O108-P108-($D$78+H108)-$D$81-M108-N108 -> 120489.42
B109: сетка MAU 1.0 × eCPM 0.6 | C109: =$B$23 -> 1 | D109: =C$20 -> 0.6 | E109: =C$20 -> 0.6 | F109: =1 -> 1 | G109: =1 -> 1 | H109: =0+(C109-1)*Энергия!$F$39 -> 0 | I109: =C109*(D109*$D$72+E109*$D$73) -> 218590.65 | J109: =G109*SUMPRODUCT(ROUND((Выручка!$H$13:$S$13*C109)*(Выручка!$H$28:$S$28*F109),0)*Выручка!$H$30:$S$30) -> 248198.4 | K109: =C109*(D109*$D$74+E109*$D$76)+G109*SUMPRODUCT((YEAR(DATE(YEAR(Выручка!$H$7:$S$7),MONTH(Выручка!$H$7:$S$7)+Лаг_выручки,1))=$D$70)*(Выручка!$H$6:$S$6+Лаг_выручки<=12)*ROUND((Выручка!$H$13:$S$13*C109)*(Выручка!$H$28:$S$28*F109),0)*Выручка!$H$30:$S$30) -> 0 | L109: =C109*(D109*$D$75+E109*$D$77)+G109*SUMPRODUCT((YEAR(DATE(YEAR(Выручка!$H$7:$S$7),MONTH(Выручка!$H$7:$S$7)+Лаг_выручки,1))=$D$71)*(Выручка!$H$6:$S$6+Лаг_выручки<=12)*ROUND((Выручка!$H$13:$S$13*C109)*(Выручка!$H$28:$S$28*F109),0)*Выручка!$H$30:$S$30) -> 466789.05 | M109: =MAX(0,Ставка_УСН*K109-MIN(Взносы_вычет,Лимит_вычета*Ставка_УСН*K109)) -> 0 | N109: =MAX(0,Ставка_УСН*L109-MIN(Взносы_вычет,Лимит_вычета*Ставка_УСН*L109)) -> 0 | O109: =I109+J109 -> 466789.05 | P109: =Комиссия_стора*J109 -> 37229.76 | Q109: =O109-P109-($D$78+H109)-$D$81-M109-N109 -> -35091.96
B110: сетка MAU 1.0 × eCPM 0.8 | C110: =$B$23 -> 1 | D110: =D$20 -> 0.8 | E110: =D$20 -> 0.8 | F110: =1 -> 1 | G110: =1 -> 1 | H110: =0+(C110-1)*Энергия!$F$39 -> 0 | I110: =C110*(D110*$D$72+E110*$D$73) -> 291454.2 | J110: =G110*SUMPRODUCT(ROUND((Выручка!$H$13:$S$13*C110)*(Выручка!$H$28:$S$28*F110),0)*Выручка!$H$30:$S$30) -> 248198.4 | K110: =C110*(D110*$D$74+E110*$D$76)+G110*SUMPRODUCT((YEAR(DATE(YEAR(Выручка!$H$7:$S$7),MONTH(Выручка!$H$7:$S$7)+Лаг_выручки,1))=$D$70)*(Выручка!$H$6:$S$6+Лаг_выручки<=12)*ROUND((Выручка!$H$13:$S$13*C110)*(Выручка!$H$28:$S$28*F110),0)*Выручка!$H$30:$S$30) -> 0 | L110: =C110*(D110*$D$75+E110*$D$77)+G110*SUMPRODUCT((YEAR(DATE(YEAR(Выручка!$H$7:$S$7),MONTH(Выручка!$H$7:$S$7)+Лаг_выручки,1))=$D$71)*(Выручка!$H$6:$S$6+Лаг_выручки<=12)*ROUND((Выручка!$H$13:$S$13*C110)*(Выручка!$H$28:$S$28*F110),0)*Выручка!$H$30:$S$30) -> 539652.6 | M110: =MAX(0,Ставка_УСН*K110-MIN(Взносы_вычет,Лимит_вычета*Ставка_УСН*K110)) -> 0 | N110: =MAX(0,Ставка_УСН*L110-MIN(Взносы_вычет,Лимит_вычета*Ставка_УСН*L110)) -> 0 | O110: =I110+J110 -> 539652.6 | P110: =Комиссия_стора*J110 -> 37229.76 | Q110: =O110-P110-($D$78+H110)-$D$81-M110-N110 -> 37771.59
